Workbook

Sheet Ma journée
A1: ☀ MA JOURNÉE
A2: L'onglet à ouvrir chaque matin : tes relances, les prospects les plus chauds à appeler, les alertes et tes objectifs du jour. Tout est automatique.
A3: =HYPERLINK("#'Saisie'!A1","↩ Saisie") | E3: =HYPERLINK("#'Tableau de bord'!A1","📊 Tableau de bord")
B4: =TODAY() | E4: =IF(WEEKDAY(TODAY(),2)=1,"📅 Lundi : fais ta revue hebdo de 15 min (voir SOP)","")
B6: 🎯 OBJECTIFS DU JOUR
B7: Objectif | C7: Fait | D7: Cible | E7: % | F7: Progression | I7: Reste
B8: Nouveaux prospects | C8: =COUNTIFS('Prospects'!$B$5:$B$504,TODAY()) | D8: ='Paramètres'!$B$6 | E8: =IFERROR(C8/D8,0) | F8: =REPT("█",ROUND(MIN(1,E8)*20,0))&REPT("░",20-ROUND(MIN(1,E8)*20,0)) | I8: =MAX(0,D8-C8)
B9: Appels | C9: =COUNTIFS('Saisie'!$A$5:$A$2004,TODAY(),'Saisie'!$D$5:$D$2004,"Appel",'Saisie'!$AU$5:$AU$2004,1) | D9: ='Paramètres'!$B$7 | E9: =IFERROR(C9/D9,0) | F9: =REPT("█",ROUND(MIN(1,E9)*20,0))&REPT("░",20-ROUND(MIN(1,E9)*20,0)) | I9: =MAX(0,D9-C9)
B10: DM | C10: =COUNTIFS('Saisie'!$A$5:$A$2004,TODAY(),'Saisie'!$D$5:$D$2004,"DM",'Saisie'!$AU$5:$AU$2004,1) | D10: ='Paramètres'!$B$8 | E10: =IFERROR(C10/D10,0) | F10: =REPT("█",ROUND(MIN(1,E10)*20,0))&REPT("░",20-ROUND(MIN(1,E10)*20,0)) | I10: =MAX(0,D10-C10)
B12: 🔴 À RELANCER AUJOURD'HUI ET EN RETARD
B13: Entreprise | C13: Contact | D13: Téléphone | E13: WhatsApp | F13: Canal | G13: Étape | H13: Prochaine action | I13: Relance | J13: Heure | K13: Retard (j)
B14: =IFERROR(INDEX('Prospects'!$C$5:$C$504,MATCH(1,'Prospects'!$BU$5:$BU$504,0))&"","") | C14: =IFERROR(INDEX('Prospects'!$J$5:$J$504,MATCH(1,'Prospects'!$BU$5:$BU$504,0))&"","") | D14: =IFERROR(INDEX('Prospects'!$K$5:$K$504,MATCH(1,'Prospects'!$BU$5:$BU$504,0))&"","") | E14: =IF(D14="","",HYPERLINK("https://wa.me/"&IF(LEFT(SUBSTITUTE(D14," ",""),1)="0",'Paramètres'!$B$35&MID(SUBSTITUTE(D14," ",""),2,20),SUBSTITUTE(D14," ","")),"Ouvrir")) | F14: =IFERROR(INDEX('Prospects'!$N$5:$N$504,MATCH(1,'Prospects'!$BU$5:$BU$504,0))&"","") | G14: =IFERROR(INDEX('Prospects'!$D$5:$D$504,MATCH(1,'Prospects'!$BU$5:$BU$504,0))&"","") | H14: =IFERROR(INDEX('Prospects'!$I$5:$I$504,MATCH(1,'Prospects'!$BU$5:$BU$504,0))&"","") | I14: =IFERROR(IF(INDEX('Prospects'!$G$5:$G$504,MATCH(1,'Prospects'!$BU$5:$BU$504,0))="","",INDEX('Prospects'!$G$5:$G$504,MATCH(1,'Prospects'!$BU$5:$BU$504,0))),"") | J14: =IFERROR(IF(INDEX('Prospects'!$H$5:$H$504,MATCH(1,'Prospects'!$BU$5:$BU$504,0))="","",INDEX('Prospects'!$H$5:$H$504,MATCH(1,'Prospects'!$BU$5:$BU$504,0))),"") | K14: =IF(I14="","",TODAY()-I14)
B15: =IFERROR(INDEX('Prospects'!$C$5:$C$504,MATCH(2,'Prospects'!$BU$5:$BU$504,0))&"","") | C15: =IFERROR(INDEX('Prospects'!$J$5:$J$504,MATCH(2,'Prospects'!$BU$5:$BU$504,0))&"","") | D15: =IFERROR(INDEX('Prospects'!$K$5:$K$504,MATCH(2,'Prospects'!$BU$5:$BU$504,0))&"","") | E15: =IF(D15="","",HYPERLINK("https://wa.me/"&IF(LEFT(SUBSTITUTE(D15," ",""),1)="0",'Paramètres'!$B$35&MID(SUBSTITUTE(D15," ",""),2,20),SUBSTITUTE(D15," ","")),"Ouvrir")) | F15: =IFERROR(INDEX('Prospects'!$N$5:$N$504,MATCH(2,'Prospects'!$BU$5:$BU$504,0))&"","") | G15: =IFERROR(INDEX('Prospects'!$D$5:$D$504,MATCH(2,'Prospects'!$BU$5:$BU$504,0))&"","") | H15: =IFERROR(INDEX('Prospects'!$I$5:$I$504,MATCH(2,'Prospects'!$BU$5:$BU$504,0))&"","") | I15: =IFERROR(IF(INDEX('Prospects'!$G$5:$G$504,MATCH(2,'Prospects'!$BU$5:$BU$504,0))="","",INDEX('Prospects'!$G$5:$G$504,MATCH(2,'Prospects'!$BU$5:$BU$504,0))),"") | J15: =IFERROR(IF(INDEX('Prospects'!$H$5:$H$504,MATCH(2,'Prospects'!$BU$5:$BU$504,0))="","",INDEX('Prospects'!$H$5:$H$504,MATCH(2,'Prospects'!$BU$5:$BU$504,0))),"") | K15: =IF(I15="","",TODAY()-I15)
B16: =IFERROR(INDEX('Prospects'!$C$5:$C$504,MATCH(3,'Prospects'!$BU$5:$BU$504,0))&"","") | C16: =IFERROR(INDEX('Prospects'!$J$5:$J$504,MATCH(3,'Prospects'!$BU$5:$BU$504,0))&"","") | D16: =IFERROR(INDEX('Prospects'!$K$5:$K$504,MATCH(3,'Prospects'!$BU$5:$BU$504,0))&"","") | E16: =IF(D16="","",HYPERLINK("https://wa.me/"&IF(LEFT(SUBSTITUTE(D16," ",""),1)="0",'Paramètres'!$B$35&MID(SUBSTITUTE(D16," ",""),2,20),SUBSTITUTE(D16," ","")),"Ouvrir")) | F16: =IFERROR(INDEX('Prospects'!$N$5:$N$504,MATCH(3,'Prospects'!$BU$5:$BU$504,0))&"","") | G16: =IFERROR(INDEX('Prospects'!$D$5:$D$504,MATCH(3,'Prospects'!$BU$5:$BU$504,0))&"","") | H16: =IFERROR(INDEX('Prospects'!$I$5:$I$504,MATCH(3,'Prospects'!$BU$5:$BU$504,0))&"","") | I16: =IFERROR(IF(INDEX('Prospects'!$G$5:$G$504,MATCH(3,'Prospects'!$BU$5:$BU$504,0))="","",INDEX('Prospects'!$G$5:$G$504,MATCH(3,'Prospects'!$BU$5:$BU$504,0))),"") | J16: =IFERROR(IF(INDEX('Prospects'!$H$5:$H$504,MATCH(3,'Prospects'!$BU$5:$BU$504,0))="","",INDEX('Prospects'!$H$5:$H$504,MATCH(3,'Prospects'!$BU$5:$BU$504,0))),"") | K16: =IF(I16="","",TODAY()-I16)
B17: =IFERROR(INDEX('Prospects'!$C$5:$C$504,MATCH(4,'Prospects'!$BU$5:$BU$504,0))&"","") | C17: =IFERROR(INDEX('Prospects'!$J$5:$J$504,MATCH(4,'Prospects'!$BU$5:$BU$504,0))&"","") | D17: =IFERROR(INDEX('Prospects'!$K$5:$K$504,MATCH(4,'Prospects'!$BU$5:$BU$504,0))&"","") | E17: =IF(D17="","",HYPERLINK("https://wa.me/"&IF(LEFT(SUBSTITUTE(D17," ",""),1)="0",'Paramètres'!$B$35&MID(SUBSTITUTE(D17," ",""),2,20),SUBSTITUTE(D17," ","")),"Ouvrir")) | F17: =IFERROR(INDEX('Prospects'!$N$5:$N$504,MATCH(4,'Prospects'!$BU$5:$BU$504,0))&"","") | G17: =IFERROR(INDEX('Prospects'!$D$5:$D$504,MATCH(4,'Prospects'!$BU$5:$BU$504,0))&"","") | H17: =IFERROR(INDEX('Prospects'!$I$5:$I$504,MATCH(4,'Prospects'!$BU$5:$BU$504,0))&"","") | I17: =IFERROR(IF(INDEX('Prospects'!$G$5:$G$504,MATCH(4,'Prospects'!$BU$5:$BU$504,0))="","",INDEX('Prospects'!$G$5:$G$504,MATCH(4,'Prospects'!$BU$5:$BU$504,0))),"") | J17: =IFERROR(IF(INDEX('Prospects'!$H$5:$H$504,MATCH(4,'Prospects'!$BU$5:$BU$504,0))="","",INDEX('Prospects'!$H$5:$H$504,MATCH(4,'Prospects'!$BU$5:$BU$504,0))),"") | K17: =IF(I17="","",TODAY()-I17)
B18: =IFERROR(INDEX('Prospects'!$C$5:$C$504,MATCH(5,'Prospects'!$BU$5:$BU$504,0))&"","") | C18: =IFERROR(INDEX('Prospects'!$J$5:$J$504,MATCH(5,'Prospects'!$BU$5:$BU$504,0))&"","") | D18: =IFERROR(INDEX('Prospects'!$K$5:$K$504,MATCH(5,'Prospects'!$BU$5:$BU$504,0))&"","") | E18: =IF(D18="","",HYPERLINK("https://wa.me/"&IF(LEFT(SUBSTITUTE(D18," ",""),1)="0",'Paramètres'!$B$35&MID(SUBSTITUTE(D18," ",""),2,20),SUBSTITUTE(D18," ","")),"Ouvrir")) | F18: =IFERROR(INDEX('Prospects'!$N$5:$N$504,MATCH(5,'Prospects'!$BU$5:$BU$504,0))&"","") | G18: =IFERROR(INDEX('Prospects'!$D$5:$D$504,MATCH(5,'Prospects'!$BU$5:$BU$504,0))&"","") | H18: =IFERROR(INDEX('Prospects'!$I$5:$I$504,MATCH(5,'Prospects'!$BU$5:$BU$504,0))&"","") | I18: =IFERROR(IF(INDEX('Prospects'!$G$5:$G$504,MATCH(5,'Prospects'!$BU$5:$BU$504,0))="","",INDEX('Prospects'!$G$5:$G$504,MATCH(5,'Prospects'!$BU$5:$BU$504,0))),"") | J18: =IFERROR(IF(INDEX('Prospects'!$H$5:$H$504,MATCH(5,'Prospects'!$BU$5:$BU$504,0))="","",INDEX('Prospects'!$H$5:$H$504,MATCH(5,'Prospects'!$BU$5:$BU$504,0))),"") | K18: =IF(I18="","",TODAY()-I18)
B19: =IFERROR(INDEX('Prospects'!$C$5:$C$504,MATCH(6,'Prospects'!$BU$5:$BU$504,0))&"","") | C19: =IFERROR(INDEX('Prospects'!$J$5:$J$504,MATCH(6,'Prospects'!$BU$5:$BU$504,0))&"","") | D19: =IFERROR(INDEX('Prospects'!$K$5:$K$504,MATCH(6,'Prospects'!$BU$5:$BU$504,0))&"","") | E19: =IF(D19="","",HYPERLINK("https://wa.me/"&IF(LEFT(SUBSTITUTE(D19," ",""),1)="0",'Paramètres'!$B$35&MID(SUBSTITUTE(D19," ",""),2,20),SUBSTITUTE(D19," ","")),"Ouvrir")) | F19: =IFERROR(INDEX('Prospects'!$N$5:$N$504,MATCH(6,'Prospects'!$BU$5:$BU$504,0))&"","") | G19: =IFERROR(INDEX('Prospects'!$D$5:$D$504,MATCH(6,'Prospects'!$BU$5:$BU$504,0))&"","") | H19: =IFERROR(INDEX('Prospects'!$I$5:$I$504,MATCH(6,'Prospects'!$BU$5:$BU$504,0))&"","") | I19: =IFERROR(IF(INDEX('Prospects'!$G$5:$G$504,MATCH(6,'Prospects'!$BU$5:$BU$504,0))="","",INDEX('Prospects'!$G$5:$G$504,MATCH(6,'Prospects'!$BU$5:$BU$504,0))),"") | J19: =IFERROR(IF(INDEX('Prospects'!$H$5:$H$504,MATCH(6,'Prospects'!$BU$5:$BU$504,0))="","",INDEX('Prospects'!$H$5:$H$504,MATCH(6,'Prospects'!$BU$5:$BU$504,0))),"") | K19: =IF(I19="","",TODAY()-I19)
B20: =IFERROR(INDEX('Prospects'!$C$5:$C$504,MATCH(7,'Prospects'!$BU$5:$BU$504,0))&"","") | C20: =IFERROR(INDEX('Prospects'!$J$5:$J$504,MATCH(7,'Prospects'!$BU$5:$BU$504,0))&"","") | D20: =IFERROR(INDEX('Prospects'!$K$5:$K$504,MATCH(7,'Prospects'!$BU$5:$BU$504,0))&"","") | E20: =IF(D20="","",HYPERLINK("https://wa.me/"&IF(LEFT(SUBSTITUTE(D20," ",""),1)="0",'Paramètres'!$B$35&MID(SUBSTITUTE(D20," ",""),2,20),SUBSTITUTE(D20," ","")),"Ouvrir")) | F20: =IFERROR(INDEX('Prospects'!$N$5:$N$504,MATCH(7,'Prospects'!$BU$5:$BU$504,0))&"","") | G20: =IFERROR(INDEX('Prospects'!$D$5:$D$504,MATCH(7,'Prospects'!$BU$5:$BU$504,0))&"","") | H20: =IFERROR(INDEX('Prospects'!$I$5:$I$504,MATCH(7,'Prospects'!$BU$5:$BU$504,0))&"","") | I20: =IFERROR(IF(INDEX('Prospects'!$G$5:$G$504,MATCH(7,'Prospects'!$BU$5:$BU$504,0))="","",INDEX('Prospects'!$G$5:$G$504,MATCH(7,'Prospects'!$BU$5:$BU$504,0))),"") | J20: =IFERROR(IF(INDEX('Prospects'!$H$5:$H$504,MATCH(7,'Prospects'!$BU$5:$BU$504,0))="","",INDEX('Prospects'!$H$5:$H$504,MATCH(7,'Prospects'!$BU$5:$BU$504,0))),"") | K20: =IF(I20="","",TODAY()-I20)
B21: =IFERROR(INDEX('Prospects'!$C$5:$C$504,MATCH(8,'Prospects'!$BU$5:$BU$504,0))&"","") | C21: =IFERROR(INDEX('Prospects'!$J$5:$J$504,MATCH(8,'Prospects'!$BU$5:$BU$504,0))&"","") | D21: =IFERROR(INDEX('Prospects'!$K$5:$K$504,MATCH(8,'Prospects'!$BU$5:$BU$504,0))&"","") | E21: =IF(D21="","",HYPERLINK("https://wa.me/"&IF(LEFT(SUBSTITUTE(D21," ",""),1)="0",'Paramètres'!$B$35&MID(SUBSTITUTE(D21," ",""),2,20),SUBSTITUTE(D21," ","")),"Ouvrir")) | F21: =IFERROR(INDEX('Prospects'!$N$5:$N$504,MATCH(8,'Prospects'!$BU$5:$BU$504,0))&"","") | G21: =IFERROR(INDEX('Prospects'!$D$5:$D$504,MATCH(8,'Prospects'!$BU$5:$BU$504,0))&"","") | H21: =IFERROR(INDEX('Prospects'!$I$5:$I$504,MATCH(8,'Prospects'!$BU$5:$BU$504,0))&"","") | I21: =IFERROR(IF(INDEX('Prospects'!$G$5:$G$504,MATCH(8,'Prospects'!$BU$5:$BU$504,0))="","",INDEX('Prospects'!$G$5:$G$504,MATCH(8,'Prospects'!$BU$5:$BU$504,0))),"") | J21: =IFERROR(IF(INDEX('Prospects'!$H$5:$H$504,MATCH(8,'Prospects'!$BU$5:$BU$504,0))="","",INDEX('Prospects'!$H$5:$H$504,MATCH(8,'Prospects'!$BU$5:$BU$504,0))),"") | K21: =IF(I21="","",TODAY()-I21)
B22: =IFERROR(INDEX('Prospects'!$C$5:$C$504,MATCH(9,'Prospects'!$BU$5:$BU$504,0))&"","") | C22: =IFERROR(INDEX('Prospects'!$J$5:$J$504,MATCH(9,'Prospects'!$BU$5:$BU$504,0))&"","") | D22: =IFERROR(INDEX('Prospects'!$K$5:$K$504,MATCH(9,'Prospects'!$BU$5:$BU$504,0))&"","") | E22: =IF(D22="","",HYPERLINK("https://wa.me/"&IF(LEFT(SUBSTITUTE(D22," ",""),1)="0",'Paramètres'!$B$35&MID(SUBSTITUTE(D22," ",""),2,20),SUBSTITUTE(D22," ","")),"Ouvrir")) | F22: =IFERROR(INDEX('Prospects'!$N$5:$N$504,MATCH(9,'Prospects'!$BU$5:$BU$504,0))&"","") | G22: =IFERROR(INDEX('Prospects'!$D$5:$D$504,MATCH(9,'Prospects'!$BU$5:$BU$504,0))&"","") | H22: =IFERROR(INDEX('Prospects'!$I$5:$I$504,MATCH(9,'Prospects'!$BU$5:$BU$504,0))&"","") | I22: =IFERROR(IF(INDEX('Prospects'!$G$5:$G$504,MATCH(9,'Prospects'!$BU$5:$BU$504,0))="","",INDEX('Prospects'!$G$5:$G$504,MATCH(9,'Prospects'!$BU$5:$BU$504,0))),"") | J22: =IFERROR(IF(INDEX('Prospects'!$H$5:$H$504,MATCH(9,'Prospects'!$BU$5:$BU$504,0))="","",INDEX('Prospects'!$H$5:$H$504,MATCH(9,'Prospects'!$BU$5:$BU$504,0))),"") | K22: =IF(I22="","",TODAY()-I22)
B23: =IFERROR(INDEX('Prospects'!$C$5:$C$504,MATCH(10,'Prospects'!$BU$5:$BU$504,0))&"","") | C23: =IFERROR(INDEX('Prospects'!$J$5:$J$504,MATCH(10,'Prospects'!$BU$5:$BU$504,0))&"","") | D23: =IFERROR(INDEX('Prospects'!$K$5:$K$504,MATCH(10,'Prospects'!$BU$5:$BU$504,0))&"","") | E23: =IF(D23="","",HYPERLINK("https://wa.me/"&IF(LEFT(SUBSTITUTE(D23," ",""),1)="0",'Paramètres'!$B$35&MID(SUBSTITUTE(D23," ",""),2,20),SUBSTITUTE(D23," ","")),"Ouvrir")) | F23: =IFERROR(INDEX('Prospects'!$N$5:$N$504,MATCH(10,'Prospects'!$BU$5:$BU$504,0))&"","") | G23: =IFERROR(INDEX('Prospects'!$D$5:$D$504,MATCH(10,'Prospects'!$BU$5:$BU$504,0))&"","") | H23: =IFERROR(INDEX('Prospects'!$I$5:$I$504,MATCH(10,'Prospects'!$BU$5:$BU$504,0))&"","") | I23: =IFERROR(IF(INDEX('Prospects'!$G$5:$G$504,MATCH(10,'Prospects'!$BU$5:$BU$504,0))="","",INDEX('Prospects'!$G$5:$G$504,MATCH(10,'Prospects'!$BU$5:$BU$504,0))),"") | J23: =IFERROR(IF(INDEX('Prospects'!$H$5:$H$504,MATCH(10,'Prospects'!$BU$5:$BU$504,0))="","",INDEX('Prospects'!$H$5:$H$504,MATCH(10,'Prospects'!$BU$5:$BU$504,0))),"") | K23: =IF(I23="","",TODAY()-I23)
B24: =IFERROR(INDEX('Prospects'!$C$5:$C$504,MATCH(11,'Prospects'!$BU$5:$BU$504,0))&"","") | C24: =IFERROR(INDEX('Prospects'!$J$5:$J$504,MATCH(11,'Prospects'!$BU$5:$BU$504,0))&"","") | D24: =IFERROR(INDEX('Prospects'!$K$5:$K$504,MATCH(11,'Prospects'!$BU$5:$BU$504,0))&"","") | E24: =IF(D24="","",HYPERLINK("https://wa.me/"&IF(LEFT(SUBSTITUTE(D24," ",""),1)="0",'Paramètres'!$B$35&MID(SUBSTITUTE(D24," ",""),2,20),SUBSTITUTE(D24," ","")),"Ouvrir")) | F24: =IFERROR(INDEX('Prospects'!$N$5:$N$504,MATCH(11,'Prospects'!$BU$5:$BU$504,0))&"","") | G24: =IFERROR(INDEX('Prospects'!$D$5:$D$504,MATCH(11,'Prospects'!$BU$5:$BU$504,0))&"","") | H24: =IFERROR(INDEX('Prospects'!$I$5:$I$504,MATCH(11,'Prospects'!$BU$5:$BU$504,0))&"","") | I24: =IFERROR(IF(INDEX('Prospects'!$G$5:$G$504,MATCH(11,'Prospects'!$BU$5:$BU$504,0))="","",INDEX('Prospects'!$G$5:$G$504,MATCH(11,'Prospects'!$BU$5:$BU$504,0))),"") | J24: =IFERROR(IF(INDEX('Prospects'!$H$5:$H$504,MATCH(11,'Prospects'!$BU$5:$BU$504,0))="","",INDEX('Prospects'!$H$5:$H$504,MATCH(11,'Prospects'!$BU$5:$BU$504,0))),"") | K24: =IF(I24="","",TODAY()-I24)
B25: =IFERROR(INDEX('Prospects'!$C$5:$C$504,MATCH(12,'Prospects'!$BU$5:$BU$504,0))&"","") | C25: =IFERROR(INDEX('Prospects'!$J$5:$J$504,MATCH(12,'Prospects'!$BU$5:$BU$504,0))&"","") | D25: =IFERROR(INDEX('Prospects'!$K$5:$K$504,MATCH(12,'Prospects'!$BU$5:$BU$504,0))&"","") | E25: =IF(D25="","",HYPERLINK("https://wa.me/"&IF(LEFT(SUBSTITUTE(D25," ",""),1)="0",'Paramètres'!$B$35&MID(SUBSTITUTE(D25," ",""),2,20),SUBSTITUTE(D25," ","")),"Ouvrir")) | F25: =IFERROR(INDEX('Prospects'!$N$5:$N$504,MATCH(12,'Prospects'!$BU$5:$BU$504,0))&"","") | G25: =IFERROR(INDEX('Prospects'!$D$5:$D$504,MATCH(12,'Prospects'!$BU$5:$BU$504,0))&"","") | H25: =IFERROR(INDEX('Prospects'!$I$5:$I$504,MATCH(12,'Prospects'!$BU$5:$BU$504,0))&"","") | I25: =IFERROR(IF(INDEX('Prospects'!$G$5:$G$504,MATCH(12,'Prospects'!$BU$5:$BU$504,0))="","",INDEX('Prospects'!$G$5:$G$504,MATCH(12,'Prospects'!$BU$5:$BU$504,0))),"") | J25: =IFERROR(IF(INDEX('Prospects'!$H$5:$H$504,MATCH(12,'Prospects'!$BU$5:$BU$504,0))="","",INDEX('Prospects'!$H$5:$H$504,MATCH(12,'Prospects'!$BU$5:$BU$504,0))),"") | K25: =IF(I25="","",TODAY()-I25)
B26: =IFERROR(INDEX('Prospects'!$C$5:$C$504,MATCH(13,'Prospects'!$BU$5:$BU$504,0))&"","") | C26: =IFERROR(INDEX('Prospects'!$J$5:$J$504,MATCH(13,'Prospects'!$BU$5:$BU$504,0))&"","") | D26: =IFERROR(INDEX('Prospects'!$K$5:$K$504,MATCH(13,'Prospects'!$BU$5:$BU$504,0))&"","") | E26: =IF(D26="","",HYPERLINK("https://wa.me/"&IF(LEFT(SUBSTITUTE(D26," ",""),1)="0",'Paramètres'!$B$35&MID(SUBSTITUTE(D26," ",""),2,20),SUBSTITUTE(D26," ","")),"Ouvrir")) | F26: =IFERROR(INDEX('Prospects'!$N$5:$N$504,MATCH(13,'Prospects'!$BU$5:$BU$504,0))&"","") | G26: =IFERROR(INDEX('Prospects'!$D$5:$D$504,MATCH(13,'Prospects'!$BU$5:$BU$504,0))&"","") | H26: =IFERROR(INDEX('Prospects'!$I$5:$I$504,MATCH(13,'Prospects'!$BU$5:$BU$504,0))&"","") | I26: =IFERROR(IF(INDEX('Prospects'!$G$5:$G$504,MATCH(13,'Prospects'!$BU$5:$BU$504,0))="","",INDEX('Prospects'!$G$5:$G$504,MATCH(13,'Prospects'!$BU$5:$BU$504,0))),"") | J26: =IFERROR(IF(INDEX('Prospects'!$H$5:$H$504,MATCH(13,'Prospects'!$BU$5:$BU$504,0))="","",INDEX('Prospects'!$H$5:$H$504,MATCH(13,'Prospects'!$BU$5:$BU$504,0))),"") | K26: =IF(I26="","",TODAY()-I26)
B27: =IFERROR(INDEX('Prospects'!$C$5:$C$504,MATCH(14,'Prospects'!$BU$5:$BU$504,0))&"","") | C27: =IFERROR(INDEX('Prospects'!$J$5:$J$504,MATCH(14,'Prospects'!$BU$5:$BU$504,0))&"","") | D27: =IFERROR(INDEX('Prospects'!$K$5:$K$504,MATCH(14,'Prospects'!$BU$5:$BU$504,0))&"","") | E27: =IF(D27="","",HYPERLINK("https://wa.me/"&IF(LEFT(SUBSTITUTE(D27," ",""),1)="0",'Paramètres'!$B$35&MID(SUBSTITUTE(D27," ",""),2,20),SUBSTITUTE(D27," ","")),"Ouvrir")) | F27: =IFERROR(INDEX('Prospects'!$N$5:$N$504,MATCH(14,'Prospects'!$BU$5:$BU$504,0))&"","") | G27: =IFERROR(INDEX('Prospects'!$D$5:$D$504,MATCH(14,'Prospects'!$BU$5:$BU$504,0))&"","") | H27: =IFERROR(INDEX('Prospects'!$I$5:$I$504,MATCH(14,'Prospects'!$BU$5:$BU$504,0))&"","") | I27: =IFERROR(IF(INDEX('Prospects'!$G$5:$G$504,MATCH(14,'Prospects'!$BU$5:$BU$504,0))="","",INDEX('Prospects'!$G$5:$G$504,MATCH(14,'Prospects'!$BU$5:$BU$504,0))),"") | J27: =IFERROR(IF(INDEX('Prospects'!$H$5:$H$504,MATCH(14,'Prospects'!$BU$5:$BU$504,0))="","",INDEX('Prospects'!$H$5:$H$504,MATCH(14,'Prospects'!$BU$5:$BU$504,0))),"") | K27: =IF(I27="","",TODAY()-I27)
B28: =IFERROR(INDEX('Prospects'!$C$5:$C$504,MATCH(15,'Prospects'!$BU$5:$BU$504,0))&"","") | C28: =IFERROR(INDEX('Prospects'!$J$5:$J$504,MATCH(15,'Prospects'!$BU$5:$BU$504,0))&"","") | D28: =IFERROR(INDEX('Prospects'!$K$5:$K$504,MATCH(15,'Prospects'!$BU$5:$BU$504,0))&"","") | E28: =IF(D28="","",HYPERLINK("https://wa.me/"&IF(LEFT(SUBSTITUTE(D28," ",""),1)="0",'Paramètres'!$B$35&MID(SUBSTITUTE(D28," ",""),2,20),SUBSTITUTE(D28," ","")),"Ouvrir")) | F28: =IFERROR(INDEX('Prospects'!$N$5:$N$504,MATCH(15,'Prospects'!$BU$5:$BU$504,0))&"","") | G28: =IFERROR(INDEX('Prospects'!$D$5:$D$504,MATCH(15,'Prospects'!$BU$5:$BU$504,0))&"","") | H28: =IFERROR(INDEX('Prospects'!$I$5:$I$504,MATCH(15,'Prospects'!$BU$5:$BU$504,0))&"","") | I28: =IFERROR(IF(INDEX('Prospects'!$G$5:$G$504,MATCH(15,'Prospects'!$BU$5:$BU$504,0))="","",INDEX('Prospects'!$G$5:$G$504,MATCH(15,'Prospects'!$BU$5:$BU$504,0))),"") | J28: =IFERROR(IF(INDEX('Prospects'!$H$5:$H$504,MATCH(15,'Prospects'!$BU$5:$BU$504,0))="","",INDEX('Prospects'!$H$5:$H$504,MATCH(15,'Prospects'!$BU$5:$BU$504,0))),"") | K28: =IF(I28="","",TODAY()-I28)
B29: =IF(MAX('Prospects'!$BU$5:$BU$504)>15,"+ "&(MAX('Prospects'!$BU$5:$BU$504)-15)&" autres relances : filtre la colonne Prochaine relance dans Prospects.","")
B31: 🔥 LES 10 PROSPECTS LES PLUS CHAUDS À APPELER
B32: Entreprise | C32: Contact | D32: Téléphone | E32: Instagram | F32: Score | G32: Étape | H32: Besoin / dernière action | I32: Tentatives | J32: Pub active | K32: Secteur
B33: =IFERROR(INDEX('Prospects'!$C$5:$C$504,MATCH(LARGE('Prospects'!$BT$5:$BT$504,1),'Prospects'!$BT$5:$BT$504,0)),"") | C33: =IFERROR(INDEX('Prospects'!$J$5:$J$504,MATCH(LARGE('Prospects'!$BT$5:$BT$504,1),'Prospects'!$BT$5:$BT$504,0)),"") | D33: =IFERROR(INDEX('Prospects'!$K$5:$K$504,MATCH(LARGE('Prospects'!$BT$5:$BT$504,1),'Prospects'!$BT$5:$BT$504,0)),"") | E33: =IFERROR(INDEX('Prospects'!$BC$5:$BC$504,MATCH(LARGE('Prospects'!$BT$5:$BT$504,1),'Prospects'!$BT$5:$BT$504,0)),"") | F33: =IFERROR(INDEX('Prospects'!$E$5:$E$504,MATCH(LARGE('Prospects'!$BT$5:$BT$504,1),'Prospects'!$BT$5:$BT$504,0)),"") | G33: =IFERROR(INDEX('Prospects'!$D$5:$D$504,MATCH(LARGE('Prospects'!$BT$5:$BT$504,1),'Prospects'!$BT$5:$BT$504,0)),"") | H33: =IFERROR(INDEX('Prospects'!$I$5:$I$504,MATCH(LARGE('Prospects'!$BT$5:$BT$504,1),'Prospects'!$BT$5:$BT$504,0)),"") | I33: =IFERROR(INDEX('Prospects'!$O$5:$O$504,MATCH(LARGE('Prospects'!$BT$5:$BT$504,1),'Prospects'!$BT$5:$BT$504,0)),"") | J33: =IFERROR(INDEX('Prospects'!$Z$5:$Z$504,MATCH(LARGE('Prospects'!$BT$5:$BT$504,1),'Prospects'!$BT$5:$BT$504,0)),"") | K33: =IFERROR(INDEX('Prospects'!$S$5:$S$504,MATCH(LARGE('Prospects'!$BT$5:$BT$504,1),'Prospects'!$BT$5:$BT$504,0)),"")
B34: =IFERROR(INDEX('Prospects'!$C$5:$C$504,MATCH(LARGE('Prospects'!$BT$5:$BT$504,2),'Prospects'!$BT$5:$BT$504,0)),"") | C34: =IFERROR(INDEX('Prospects'!$J$5:$J$504,MATCH(LARGE('Prospects'!$BT$5:$BT$504,2),'Prospects'!$BT$5:$BT$504,0)),"") | D34: =IFERROR(INDEX('Prospects'!$K$5:$K$504,MATCH(LARGE('Prospects'!$BT$5:$BT$504,2),'Prospects'!$BT$5:$BT$504,0)),"") | E34: =IFERROR(INDEX('Prospects'!$BC$5:$BC$504,MATCH(LARGE('Prospects'!$BT$5:$BT$504,2),'Prospects'!$BT$5:$BT$504,0)),"") | F34: =IFERROR(INDEX('Prospects'!$E$5:$E$504,MATCH(LARGE('Prospects'!$BT$5:$BT$504,2),'Prospects'!$BT$5:$BT$504,0)),"") | G34: =IFERROR(INDEX('Prospects'!$D$5:$D$504,MATCH(LARGE('Prospects'!$BT$5:$BT$504,2),'Prospects'!$BT$5:$BT$504,0)),"") | H34: =IFERROR(INDEX('Prospects'!$I$5:$I$504,MATCH(LARGE('Prospects'!$BT$5:$BT$504,2),'Prospects'!$BT$5:$BT$504,0)),"") | I34: =IFERROR(INDEX('Prospects'!$O$5:$O$504,MATCH(LARGE('Prospects'!$BT$5:$BT$504,2),'Prospects'!$BT$5:$BT$504,0)),"") | J34: =IFERROR(INDEX('Prospects'!$Z$5:$Z$504,MATCH(LARGE('Prospects'!$BT$5:$BT$504,2),'Prospects'!$BT$5:$BT$504,0)),"") | K34: =IFERROR(INDEX('Prospects'!$S$5:$S$504,MATCH(LARGE('Prospects'!$BT$5:$BT$504,2),'Prospects'!$BT$5:$BT$504,0)),"")
B35: =IFERROR(INDEX('Prospects'!$C$5:$C$504,MATCH(LARGE('Prospects'!$BT$5:$BT$504,3),'Prospects'!$BT$5:$BT$504,0)),"") | C35: =IFERROR(INDEX('Prospects'!$J$5:$J$504,MATCH(LARGE('Prospects'!$BT$5:$BT$504,3),'Prospects'!$BT$5:$BT$504,0)),"") | D35: =IFERROR(INDEX('Prospects'!$K$5:$K$504,MATCH(LARGE('Prospects'!$BT$5:$BT$504,3),'Prospects'!$BT$5:$BT$504,0)),"") | E35: =IFERROR(INDEX('Prospects'!$BC$5:$BC$504,MATCH(LARGE('Prospects'!$BT$5:$BT$504,3),'Prospects'!$BT$5:$BT$504,0)),"") | F35: =IFERROR(INDEX('Prospects'!$E$5:$E$504,MATCH(LARGE('Prospects'!$BT$5:$BT$504,3),'Prospects'!$BT$5:$BT$504,0)),"") | G35: =IFERROR(INDEX('Prospects'!$D$5:$D$504,MATCH(LARGE('Prospects'!$BT$5:$BT$504,3),'Prospects'!$BT$5:$BT$504,0)),"") | H35: =IFERROR(INDEX('Prospects'!$I$5:$I$504,MATCH(LARGE('Prospects'!$BT$5:$BT$504,3),'Prospects'!$BT$5:$BT$504,0)),"") | I35: =IFERROR(INDEX('Prospects'!$O$5:$O$504,MATCH(LARGE('Prospects'!$BT$5:$BT$504,3),'Prospects'!$BT$5:$BT$504,0)),"") | J35: =IFERROR(INDEX('Prospects'!$Z$5:$Z$504,MATCH(LARGE('Prospects'!$BT$5:$BT$504,3),'Prospects'!$BT$5:$BT$504,0)),"") | K35: =IFERROR(INDEX('Prospects'!$S$5:$S$504,MATCH(LARGE('Prospects'!$BT$5:$BT$504,3),'Prospects'!$BT$5:$BT$504,0)),"")
B36: =IFERROR(INDEX('Prospects'!$C$5:$C$504,MATCH(LARGE('Prospects'!$BT$5:$BT$504,4),'Prospects'!$BT$5:$BT$504,0)),"") | C36: =IFERROR(INDEX('Prospects'!$J$5:$J$504,MATCH(LARGE('Prospects'!$BT$5:$BT$504,4),'Prospects'!$BT$5:$BT$504,0)),"") | D36: =IFERROR(INDEX('Prospects'!$K$5:$K$504,MATCH(LARGE('Prospects'!$BT$5:$BT$504,4),'Prospects'!$BT$5:$BT$504,0)),"") | E36: =IFERROR(INDEX('Prospects'!$BC$5:$BC$504,MATCH(LARGE('Prospects'!$BT$5:$BT$504,4),'Prospects'!$BT$5:$BT$504,0)),"") | F36: =IFERROR(INDEX('Prospects'!$E$5:$E$504,MATCH(LARGE('Prospects'!$BT$5:$BT$504,4),'Prospects'!$BT$5:$BT$504,0)),"") | G36: =IFERROR(INDEX('Prospects'!$D$5:$D$504,MATCH(LARGE('Prospects'!$BT$5:$BT$504,4),'Prospects'!$BT$5:$BT$504,0)),"") | H36: =IFERROR(INDEX('Prospects'!$I$5:$I$504,MATCH(LARGE('Prospects'!$BT$5:$BT$504,4),'Prospects'!$BT$5:$BT$504,0)),"") | I36: =IFERROR(INDEX('Prospects'!$O$5:$O$504,MATCH(LARGE('Prospects'!$BT$5:$BT$504,4),'Prospects'!$BT$5:$BT$504,0)),"") | J36: =IFERROR(INDEX('Prospects'!$Z$5:$Z$504,MATCH(LARGE('Prospects'!$BT$5:$BT$504,4),'Prospects'!$BT$5:$BT$504,0)),"") | K36: =IFERROR(INDEX('Prospects'!$S$5:$S$504,MATCH(LARGE('Prospects'!$BT$5:$BT$504,4),'Prospects'!$BT$5:$BT$504,0)),"")
B37: =IFERROR(INDEX('Prospects'!$C$5:$C$504,MATCH(LARGE('Prospects'!$BT$5:$BT$504,5),'Prospects'!$BT$5:$BT$504,0)),"") | C37: =IFERROR(INDEX('Prospects'!$J$5:$J$504,MATCH(LARGE('Prospects'!$BT$5:$BT$504,5),'Prospects'!$BT$5:$BT$504,0)),"") | D37: =IFERROR(INDEX('Prospects'!$K$5:$K$504,MATCH(LARGE('Prospects'!$BT$5:$BT$504,5),'Prospects'!$BT$5:$BT$504,0)),"") | E37: =IFERROR(INDEX('Prospects'!$BC$5:$BC$504,MATCH(LARGE('Prospects'!$BT$5:$BT$504,5),'Prospects'!$BT$5:$BT$504,0)),"") | F37: =IFERROR(INDEX('Prospects'!$E$5:$E$504,MATCH(LARGE('Prospects'!$BT$5:$BT$504,5),'Prospects'!$BT$5:$BT$504,0)),"") | G37: =IFERROR(INDEX('Prospects'!$D$5:$D$504,MATCH(LARGE('Prospects'!$BT$5:$BT$504,5),'Prospects'!$BT$5:$BT$504,0)),"") | H37: =IFERROR(INDEX('Prospects'!$I$5:$I$504,MATCH(LARGE('Prospects'!$BT$5:$BT$504,5),'Prospects'!$BT$5:$BT$504,0)),"") | I37: =IFERROR(INDEX('Prospects'!$O$5:$O$504,MATCH(LARGE('Prospects'!$BT$5:$BT$504,5),'Prospects'!$BT$5:$BT$504,0)),"") | J37: =IFERROR(INDEX('Prospects'!$Z$5:$Z$504,MATCH(LARGE('Prospects'!$BT$5:$BT$504,5),'Prospects'!$BT$5:$BT$504,0)),"") | K37: =IFERROR(INDEX('Prospects'!$S$5:$S$504,MATCH(LARGE('Prospects'!$BT$5:$BT$504,5),'Prospects'!$BT$5:$BT$504,0)),"")
B38: =IFERROR(INDEX('Prospects'!$C$5:$C$504,MATCH(LARGE('Prospects'!$BT$5:$BT$504,6),'Prospects'!$BT$5:$BT$504,0)),"") | C38: =IFERROR(INDEX('Prospects'!$J$5:$J$504,MATCH(LARGE('Prospects'!$BT$5:$BT$504,6),'Prospects'!$BT$5:$BT$504,0)),"") | D38: =IFERROR(INDEX('Prospects'!$K$5:$K$504,MATCH(LARGE('Prospects'!$BT$5:$BT$504,6),'Prospects'!$BT$5:$BT$504,0)),"") | E38: =IFERROR(INDEX('Prospects'!$BC$5:$BC$504,MATCH(LARGE('Prospects'!$BT$5:$BT$504,6),'Prospects'!$BT$5:$BT$504,0)),"") | F38: =IFERROR(INDEX('Prospects'!$E$5:$E$504,MATCH(LARGE('Prospects'!$BT$5:$BT$504,6),'Prospects'!$BT$5:$BT$504,0)),"") | G38: =IFERROR(INDEX('Prospects'!$D$5:$D$504,MATCH(LARGE('Prospects'!$BT$5:$BT$504,6),'Prospects'!$BT$5:$BT$504,0)),"") | H38: =IFERROR(INDEX('Prospects'!$I$5:$I$504,MATCH(LARGE('Prospects'!$BT$5:$BT$504,6),'Prospects'!$BT$5:$BT$504,0)),"") | I38: =IFERROR(INDEX('Prospects'!$O$5:$O$504,MATCH(LARGE('Prospects'!$BT$5:$BT$504,6),'Prospects'!$BT$5:$BT$504,0)),"") | J38: =IFERROR(INDEX('Prospects'!$Z$5:$Z$504,MATCH(LARGE('Prospects'!$BT$5:$BT$504,6),'Prospects'!$BT$5:$BT$504,0)),"") | K38: =IFERROR(INDEX('Prospects'!$S$5:$S$504,MATCH(LARGE('Prospects'!$BT$5:$BT$504,6),'Prospects'!$BT$5:$BT$504,0)),"")
B39: =IFERROR(INDEX('Prospects'!$C$5:$C$504,MATCH(LARGE('Prospects'!$BT$5:$BT$504,7),'Prospects'!$BT$5:$BT$504,0)),"") | C39: =IFERROR(INDEX('Prospects'!$J$5:$J$504,MATCH(LARGE('Prospects'!$BT$5:$BT$504,7),'Prospects'!$BT$5:$BT$504,0)),"") | D39: =IFERROR(INDEX('Prospects'!$K$5:$K$504,MATCH(LARGE('Prospects'!$BT$5:$BT$504,7),'Prospects'!$BT$5:$BT$504,0)),"") | E39: =IFERROR(INDEX('Prospects'!$BC$5:$BC$504,MATCH(LARGE('Prospects'!$BT$5:$BT$504,7),'Prospects'!$BT$5:$BT$504,0)),"") | F39: =IFERROR(INDEX('Prospects'!$E$5:$E$504,MATCH(LARGE('Prospects'!$BT$5:$BT$504,7),'Prospects'!$BT$5:$BT$504,0)),"") | G39: =IFERROR(INDEX('Prospects'!$D$5:$D$504,MATCH(LARGE('Prospects'!$BT$5:$BT$504,7),'Prospects'!$BT$5:$BT$504,0)),"") | H39: =IFERROR(INDEX('Prospects'!$I$5:$I$504,MATCH(LARGE('Prospects'!$BT$5:$BT$504,7),'Prospects'!$BT$5:$BT$504,0)),"") | I39: =IFERROR(INDEX('Prospects'!$O$5:$O$504,MATCH(LARGE('Prospects'!$BT$5:$BT$504,7),'Prospects'!$BT$5:$BT$504,0)),"") | J39: =IFERROR(INDEX('Prospects'!$Z$5:$Z$504,MATCH(LARGE('Prospects'!$BT$5:$BT$504,7),'Prospects'!$BT$5:$BT$504,0)),"") | K39: =IFERROR(INDEX('Prospects'!$S$5:$S$504,MATCH(LARGE('Prospects'!$BT$5:$BT$504,7),'Prospects'!$BT$5:$BT$504,0)),"")
B40: =IFERROR(INDEX('Prospects'!$C$5:$C$504,MATCH(LARGE('Prospects'!$BT$5:$BT$504,8),'Prospects'!$BT$5:$BT$504,0)),"") | C40: =IFERROR(INDEX('Prospects'!$J$5:$J$504,MATCH(LARGE('Prospects'!$BT$5:$BT$504,8),'Prospects'!$BT$5:$BT$504,0)),"") | D40: =IFERROR(INDEX('Prospects'!$K$5:$K$504,MATCH(LARGE('Prospects'!$BT$5:$BT$504,8),'Prospects'!$BT$5:$BT$504,0)),"") | E40: =IFERROR(INDEX('Prospects'!$BC$5:$BC$504,MATCH(LARGE('Prospects'!$BT$5:$BT$504,8),'Prospects'!$BT$5:$BT$504,0)),"") | F40: =IFERROR(INDEX('Prospects'!$E$5:$E$504,MATCH(LARGE('Prospects'!$BT$5:$BT$504,8),'Prospects'!$BT$5:$BT$504,0)),"") | G40: =IFERROR(INDEX('Prospects'!$D$5:$D$504,MATCH(LARGE('Prospects'!$BT$5:$BT$504,8),'Prospects'!$BT$5:$BT$504,0)),"") | H40: =IFERROR(INDEX('Prospects'!$I$5:$I$504,MATCH(LARGE('Prospects'!$BT$5:$BT$504,8),'Prospects'!$BT$5:$BT$504,0)),"") | I40: =IFERROR(INDEX('Prospects'!$O$5:$O$504,MATCH(LARGE('Prospects'!$BT$5:$BT$504,8),'Prospects'!$BT$5:$BT$504,0)),"") | J40: =IFERROR(INDEX('Prospects'!$Z$5:$Z$504,MATCH(LARGE('Prospects'!$BT$5:$BT$504,8),'Prospects'!$BT$5:$BT$504,0)),"") | K40: =IFERROR(INDEX('Prospects'!$S$5:$S$504,MATCH(LARGE('Prospects'!$BT$5:$BT$504,8),'Prospects'!$BT$5:$BT$504,0)),"")
B41: =IFERROR(INDEX('Prospects'!$C$5:$C$504,MATCH(LARGE('Prospects'!$BT$5:$BT$504,9),'Prospects'!$BT$5:$BT$504,0)),"") | C41: =IFERROR(INDEX('Prospects'!$J$5:$J$504,MATCH(LARGE('Prospects'!$BT$5:$BT$504,9),'Prospects'!$BT$5:$BT$504,0)),"") | D41: =IFERROR(INDEX('Prospects'!$K$5:$K$504,MATCH(LARGE('Prospects'!$BT$5:$BT$504,9),'Prospects'!$BT$5:$BT$504,0)),"") | E41: =IFERROR(INDEX('Prospects'!$BC$5:$BC$504,MATCH(LARGE('Prospects'!$BT$5:$BT$504,9),'Prospects'!$BT$5:$BT$504,0)),"") | F41: =IFERROR(INDEX('Prospects'!$E$5:$E$504,MATCH(LARGE('Prospects'!$BT$5:$BT$504,9),'Prospects'!$BT$5:$BT$504,0)),"") | G41: =IFERROR(INDEX('Prospects'!$D$5:$D$504,MATCH(LARGE('Prospects'!$BT$5:$BT$504,9),'Prospects'!$BT$5:$BT$504,0)),"") | H41: =IFERROR(INDEX('Prospects'!$I$5:$I$504,MATCH(LARGE('Prospects'!$BT$5:$BT$504,9),'Prospects'!$BT$5:$BT$504,0)),"") | I41: =IFERROR(INDEX('Prospects'!$O$5:$O$504,MATCH(LARGE('Prospects'!$BT$5:$BT$504,9),'Prospects'!$BT$5:$BT$504,0)),"") | J41: =IFERROR(INDEX('Prospects'!$Z$5:$Z$504,MATCH(LARGE('Prospects'!$BT$5:$BT$504,9),'Prospects'!$BT$5:$BT$504,0)),"") | K41: =IFERROR(INDEX('Prospects'!$S$5:$S$504,MATCH(LARGE('Prospects'!$BT$5:$BT$504,9),'Prospects'!$BT$5:$BT$504,0)),"")
B42: =IFERROR(INDEX('Prospects'!$C$5:$C$504,MATCH(LARGE('Prospects'!$BT$5:$BT$504,10),'Prospects'!$BT$5:$BT$504,0)),"") | C42: =IFERROR(INDEX('Prospects'!$J$5:$J$504,MATCH(LARGE('Prospects'!$BT$5:$BT$504,10),'Prospects'!$BT$5:$BT$504,0)),"") | D42: =IFERROR(INDEX('Prospects'!$K$5:$K$504,MATCH(LARGE('Prospects'!$BT$5:$BT$504,10),'Prospects'!$BT$5:$BT$504,0)),"") | E42: =IFERROR(INDEX('Prospects'!$BC$5:$BC$504,MATCH(LARGE('Prospects'!$BT$5:$BT$504,10),'Prospects'!$BT$5:$BT$504,0)),"") | F42: =IFERROR(INDEX('Prospects'!$E$5:$E$504,MATCH(LARGE('Prospects'!$BT$5:$BT$504,10),'Prospects'!$BT$5:$BT$504,0)),"") | G42: =IFERROR(INDEX('Prospects'!$D$5:$D$504,MATCH(LARGE('Prospects'!$BT$5:$BT$504,10),'Prospects'!$BT$5:$BT$504,0)),"") | H42: =IFERROR(INDEX('Prospects'!$I$5:$I$504,MATCH(LARGE('Prospects'!$BT$5:$BT$504,10),'Prospects'!$BT$5:$BT$504,0)),"") | I42: =IFERROR(INDEX('Prospects'!$O$5:$O$504,MATCH(LARGE('Prospects'!$BT$5:$BT$504,10),'Prospects'!$BT$5:$BT$504,0)),"") | J42: =IFERROR(INDEX('Prospects'!$Z$5:$Z$504,MATCH(LARGE('Prospects'!$BT$5:$BT$504,10),'Prospects'!$BT$5:$BT$504,0)),"") | K42: =IFERROR(INDEX('Prospects'!$S$5:$S$504,MATCH(LARGE('Prospects'!$BT$5:$BT$504,10),'Prospects'!$BT$5:$BT$504,0)),"")
B44: 🟠 ALERTES PROSPECTS
B45: Entreprise | C45: Alerte | E45: Étape | F45: Jours sans action | G45: Contact | H45: Téléphone | I45: Offre | J45: Montant proposé
B46: =IFERROR(INDEX('Prospects'!$C$5:$C$504,MATCH(1,'Prospects'!$BV$5:$BV$504,0))&"","") | C46: =IFERROR(INDEX('Prospects'!$F$5:$F$504,MATCH(1,'Prospects'!$BV$5:$BV$504,0))&"","") | E46: =IFERROR(INDEX('Prospects'!$D$5:$D$504,MATCH(1,'Prospects'!$BV$5:$BV$504,0))&"","") | F46: =IFERROR(INDEX('Prospects'!$R$5:$R$504,MATCH(1,'Prospects'!$BV$5:$BV$504,0)),"") | G46: =IFERROR(INDEX('Prospects'!$J$5:$J$504,MATCH(1,'Prospects'!$BV$5:$BV$504,0))&"","") | H46: =IFERROR(INDEX('Prospects'!$K$5:$K$504,MATCH(1,'Prospects'!$BV$5:$BV$504,0))&"","") | I46: =IFERROR(INDEX('Prospects'!$AN$5:$AN$504,MATCH(1,'Prospects'!$BV$5:$BV$504,0))&"","") | J46: =IFERROR(INDEX('Prospects'!$AP$5:$AP$504,MATCH(1,'Prospects'!$BV$5:$BV$504,0)),"")
B47: =IFERROR(INDEX('Prospects'!$C$5:$C$504,MATCH(2,'Prospects'!$BV$5:$BV$504,0))&"","") | C47: =IFERROR(INDEX('Prospects'!$F$5:$F$504,MATCH(2,'Prospects'!$BV$5:$BV$504,0))&"","") | E47: =IFERROR(INDEX('Prospects'!$D$5:$D$504,MATCH(2,'Prospects'!$BV$5:$BV$504,0))&"","") | F47: =IFERROR(INDEX('Prospects'!$R$5:$R$504,MATCH(2,'Prospects'!$BV$5:$BV$504,0)),"") | G47: =IFERROR(INDEX('Prospects'!$J$5:$J$504,MATCH(2,'Prospects'!$BV$5:$BV$504,0))&"","") | H47: =IFERROR(INDEX('Prospects'!$K$5:$K$504,MATCH(2,'Prospects'!$BV$5:$BV$504,0))&"","") | I47: =IFERROR(INDEX('Prospects'!$AN$5:$AN$504,MATCH(2,'Prospects'!$BV$5:$BV$504,0))&"","") | J47: =IFERROR(INDEX('Prospects'!$AP$5:$AP$504,MATCH(2,'Prospects'!$BV$5:$BV$504,0)),"")
B48: =IFERROR(INDEX('Prospects'!$C$5:$C$504,MATCH(3,'Prospects'!$BV$5:$BV$504,0))&"","") | C48: =IFERROR(INDEX('Prospects'!$F$5:$F$504,MATCH(3,'Prospects'!$BV$5:$BV$504,0))&"","") | E48: =IFERROR(INDEX('Prospects'!$D$5:$D$504,MATCH(3,'Prospects'!$BV$5:$BV$504,0))&"","") | F48: =IFERROR(INDEX('Prospects'!$R$5:$R$504,MATCH(3,'Prospects'!$BV$5:$BV$504,0)),"") | G48: =IFERROR(INDEX('Prospects'!$J$5:$J$504,MATCH(3,'Prospects'!$BV$5:$BV$504,0))&"","") | H48: =IFERROR(INDEX('Prospects'!$K$5:$K$504,MATCH(3,'Prospects'!$BV$5:$BV$504,0))&"","") | I48: =IFERROR(INDEX('Prospects'!$AN$5:$AN$504,MATCH(3,'Prospects'!$BV$5:$BV$504,0))&"","") | J48: =IFERROR(INDEX('Prospects'!$AP$5:$AP$504,MATCH(3,'Prospects'!$BV$5:$BV$504,0)),"")
B49: =IFERROR(INDEX('Prospects'!$C$5:$C$504,MATCH(4,'Prospects'!$BV$5:$BV$504,0))&"","") | C49: =IFERROR(INDEX('Prospects'!$F$5:$F$504,MATCH(4,'Prospects'!$BV$5:$BV$504,0))&"","") | E49: =IFERROR(INDEX('Prospects'!$D$5:$D$504,MATCH(4,'Prospects'!$BV$5:$BV$504,0))&"","") | F49: =IFERROR(INDEX('Prospects'!$R$5:$R$504,MATCH(4,'Prospects'!$BV$5:$BV$504,0)),"") | G49: =IFERROR(INDEX('Prospects'!$J$5:$J$504,MATCH(4,'Prospects'!$BV$5:$BV$504,0))&"","") | H49: =IFERROR(INDEX('Prospects'!$K$5:$K$504,MATCH(4,'Prospects'!$BV$5:$BV$504,0))&"","") | I49: =IFERROR(INDEX('Prospects'!$AN$5:$AN$504,MATCH(4,'Prospects'!$BV$5:$BV$504,0))&"","") | J49: =IFERROR(INDEX('Prospects'!$AP$5:$AP$504,MATCH(4,'Prospects'!$BV$5:$BV$504,0)),"")
B50: =IFERROR(INDEX('Prospects'!$C$5:$C$504,MATCH(5,'Prospects'!$BV$5:$BV$504,0))&"","") | C50: =IFERROR(INDEX('Prospects'!$F$5:$F$504,MATCH(5,'Prospects'!$BV$5:$BV$504,0))&"","") | E50: =IFERROR(INDEX('Prospects'!$D$5:$D$504,MATCH(5,'Prospects'!$BV$5:$BV$504,0))&"","") | F50: =IFERROR(INDEX('Prospects'!$R$5:$R$504,MATCH(5,'Prospects'!$BV$5:$BV$504,0)),"") | G50: =IFERROR(INDEX('Prospects'!$J$5:$J$504,MATCH(5,'Prospects'!$BV$5:$BV$504,0))&"","") | H50: =IFERROR(INDEX('Prospects'!$K$5:$K$504,MATCH(5,'Prospects'!$BV$5:$BV$504,0))&"","") | I50: =IFERROR(INDEX('Prospects'!$AN$5:$AN$504,MATCH(5,'Prospects'!$BV$5:$BV$504,0))&"","") | J50: =IFERROR(INDEX('Prospects'!$AP$5:$AP$504,MATCH(5,'Prospects'!$BV$5:$BV$504,0)),"")
B51: =IFERROR(INDEX('Prospects'!$C$5:$C$504,MATCH(6,'Prospects'!$BV$5:$BV$504,0))&"","") | C51: =IFERROR(INDEX('Prospects'!$F$5:$F$504,MATCH(6,'Prospects'!$BV$5:$BV$504,0))&"","") | E51: =IFERROR(INDEX('Prospects'!$D$5:$D$504,MATCH(6,'Prospects'!$BV$5:$BV$504,0))&"","") | F51: =IFERROR(INDEX('Prospects'!$R$5:$R$504,MATCH(6,'Prospects'!$BV$5:$BV$504,0)),"") | G51: =IFERROR(INDEX('Prospects'!$J$5:$J$504,MATCH(6,'Prospects'!$BV$5:$BV$504,0))&"","") | H51: =IFERROR(INDEX('Prospects'!$K$5:$K$504,MATCH(6,'Prospects'!$BV$5:$BV$504,0))&"","") | I51: =IFERROR(INDEX('Prospects'!$AN$5:$AN$504,MATCH(6,'Prospects'!$BV$5:$BV$504,0))&"","") | J51: =IFERROR(INDEX('Prospects'!$AP$5:$AP$504,MATCH(6,'Prospects'!$BV$5:$BV$504,0)),"")
B52: =IFERROR(INDEX('Prospects'!$C$5:$C$504,MATCH(7,'Prospects'!$BV$5:$BV$504,0))&"","") | C52: =IFERROR(INDEX('Prospects'!$F$5:$F$504,MATCH(7,'Prospects'!$BV$5:$BV$504,0))&"","") | E52: =IFERROR(INDEX('Prospects'!$D$5:$D$504,MATCH(7,'Prospects'!$BV$5:$BV$504,0))&"","") | F52: =IFERROR(INDEX('Prospects'!$R$5:$R$504,MATCH(7,'Prospects'!$BV$5:$BV$504,0)),"") | G52: =IFERROR(INDEX('Prospects'!$J$5:$J$504,MATCH(7,'Prospects'!$BV$5:$BV$504,0))&"","") | H52: =IFERROR(INDEX('Prospects'!$K$5:$K$504,MATCH(7,'Prospects'!$BV$5:$BV$504,0))&"","") | I52: =IFERROR(INDEX('Prospects'!$AN$5:$AN$504,MATCH(7,'Prospects'!$BV$5:$BV$504,0))&"","") | J52: =IFERROR(INDEX('Prospects'!$AP$5:$AP$504,MATCH(7,'Prospects'!$BV$5:$BV$504,0)),"")
B53: =IFERROR(INDEX('Prospects'!$C$5:$C$504,MATCH(8,'Prospects'!$BV$5:$BV$504,0))&"","") | C53: =IFERROR(INDEX('Prospects'!$F$5:$F$504,MATCH(8,'Prospects'!$BV$5:$BV$504,0))&"","") | E53: =IFERROR(INDEX('Prospects'!$D$5:$D$504,MATCH(8,'Prospects'!$BV$5:$BV$504,0))&"","") | F53: =IFERROR(INDEX('Prospects'!$R$5:$R$504,MATCH(8,'Prospects'!$BV$5:$BV$504,0)),"") | G53: =IFERROR(INDEX('Prospects'!$J$5:$J$504,MATCH(8,'Prospects'!$BV$5:$BV$504,0))&"","") | H53: =IFERROR(INDEX('Prospects'!$K$5:$K$504,MATCH(8,'Prospects'!$BV$5:$BV$504,0))&"","") | I53: =IFERROR(INDEX('Prospects'!$AN$5:$AN$504,MATCH(8,'Prospects'!$BV$5:$BV$504,0))&"","") | J53: =IFERROR(INDEX('Prospects'!$AP$5:$AP$504,MATCH(8,'Prospects'!$BV$5:$BV$504,0)),"")
B54: =IFERROR(INDEX('Prospects'!$C$5:$C$504,MATCH(9,'Prospects'!$BV$5:$BV$504,0))&"","") | C54: =IFERROR(INDEX('Prospects'!$F$5:$F$504,MATCH(9,'Prospects'!$BV$5:$BV$504,0))&"","") | E54: =IFERROR(INDEX('Prospects'!$D$5:$D$504,MATCH(9,'Prospects'!$BV$5:$BV$504,0))&"","") | F54: =IFERROR(INDEX('Prospects'!$R$5:$R$504,MATCH(9,'Prospects'!$BV$5:$BV$504,0)),"") | G54: =IFERROR(INDEX('Prospects'!$J$5:$J$504,MATCH(9,'Prospects'!$BV$5:$BV$504,0))&"","") | H54: =IFERROR(INDEX('Prospects'!$K$5:$K$504,MATCH(9,'Prospects'!$BV$5:$BV$504,0))&"","") | I54: =IFERROR(INDEX('Prospects'!$AN$5:$AN$504,MATCH(9,'Prospects'!$BV$5:$BV$504,0))&"","") | J54: =IFERROR(INDEX('Prospects'!$AP$5:$AP$504,MATCH(9,'Prospects'!$BV$5:$BV$504,0)),"")
B55: =IFERROR(INDEX('Prospects'!$C$5:$C$504,MATCH(10,'Prospects'!$BV$5:$BV$504,0))&"","") | C55: =IFERROR(INDEX('Prospects'!$F$5:$F$504,MATCH(10,'Prospects'!$BV$5:$BV$504,0))&"","") | E55: =IFERROR(INDEX('Prospects'!$D$5:$D$504,MATCH(10,'Prospects'!$BV$5:$BV$504,0))&"","") | F55: =IFERROR(INDEX('Prospects'!$R$5:$R$504,MATCH(10,'Prospects'!$BV$5:$BV$504,0)),"") | G55: =IFERROR(INDEX('Prospects'!$J$5:$J$504,MATCH(10,'Prospects'!$BV$5:$BV$504,0))&"","") | H55: =IFERROR(INDEX('Prospects'!$K$5:$K$504,MATCH(10,'Prospects'!$BV$5:$BV$504,0))&"","") | I55: =IFERROR(INDEX('Prospects'!$AN$5:$AN$504,MATCH(10,'Prospects'!$BV$5:$BV$504,0))&"","") | J55: =IFERROR(INDEX('Prospects'!$AP$5:$AP$504,MATCH(10,'Prospects'!$BV$5:$BV$504,0)),"")
B57: 🤝 CLIENTS À SURVEILLER
B58: Client | C58: Alerte | E58: Contact | F58: Téléphone | G58: Reste à encaisser | H58: Offre | I58: Renouvellement | J58: Onboarding
B59: =IFERROR(INDEX('Clients'!$B$5:$B$154,MATCH(1,'Clients'!$AD$5:$AD$154,0))&"","") | C59: =IFERROR(INDEX('Clients'!$D$5:$D$154,MATCH(1,'Clients'!$AD$5:$AD$154,0))&"","") | E59: =IFERROR(INDEX('Clients'!$E$5:$E$154,MATCH(1,'Clients'!$AD$5:$AD$154,0))&"","") | F59: =IFERROR(INDEX('Clients'!$F$5:$F$154,MATCH(1,'Clients'!$AD$5:$AD$154,0))&"","") | G59: =IFERROR(INDEX('Clients'!$Q$5:$Q$154,MATCH(1,'Clients'!$AD$5:$AD$154,0)),"") | H59: =IFERROR(INDEX('Clients'!$K$5:$K$154,MATCH(1,'Clients'!$AD$5:$AD$154,0))&"","") | I59: =IFERROR(INDEX('Clients'!$U$5:$U$154,MATCH(1,'Clients'!$AD$5:$AD$154,0)),"") | J59: =IFERROR(INDEX('Clients'!$Z$5:$Z$154,MATCH(1,'Clients'!$AD$5:$AD$154,0)),"")
B60: =IFERROR(INDEX('Clients'!$B$5:$B$154,MATCH(2,'Clients'!$AD$5:$AD$154,0))&"","") | C60: =IFERROR(INDEX('Clients'!$D$5:$D$154,MATCH(2,'Clients'!$AD$5:$AD$154,0))&"","") | E60: =IFERROR(INDEX('Clients'!$E$5:$E$154,MATCH(2,'Clients'!$AD$5:$AD$154,0))&"","") | F60: =IFERROR(INDEX('Clients'!$F$5:$F$154,MATCH(2,'Clients'!$AD$5:$AD$154,0))&"","") | G60: =IFERROR(INDEX('Clients'!$Q$5:$Q$154,MATCH(2,'Clients'!$AD$5:$AD$154,0)),"") | H60: =IFERROR(INDEX('Clients'!$K$5:$K$154,MATCH(2,'Clients'!$AD$5:$AD$154,0))&"","") | I60: =IFERROR(INDEX('Clients'!$U$5:$U$154,MATCH(2,'Clients'!$AD$5:$AD$154,0)),"") | J60: =IFERROR(INDEX('Clients'!$Z$5:$Z$154,MATCH(2,'Clients'!$AD$5:$AD$154,0)),"")
B61: =IFERROR(INDEX('Clients'!$B$5:$B$154,MATCH(3,'Clients'!$AD$5:$AD$154,0))&"","") | C61: =IFERROR(INDEX('Clients'!$D$5:$D$154,MATCH(3,'Clients'!$AD$5:$AD$154,0))&"","") | E61: =IFERROR(INDEX('Clients'!$E$5:$E$154,MATCH(3,'Clients'!$AD$5:$AD$154,0))&"","") | F61: =IFERROR(INDEX('Clients'!$F$5:$F$154,MATCH(3,'Clients'!$AD$5:$AD$154,0))&"","") | G61: =IFERROR(INDEX('Clients'!$Q$5:$Q$154,MATCH(3,'Clients'!$AD$5:$AD$154,0)),"") | H61: =IFERROR(INDEX('Clients'!$K$5:$K$154,MATCH(3,'Clients'!$AD$5:$AD$154,0))&"","") | I61: =IFERROR(INDEX('Clients'!$U$5:$U$154,MATCH(3,'Clients'!$AD$5:$AD$154,0)),"") | J61: =IFERROR(INDEX('Clients'!$Z$5:$Z$154,MATCH(3,'Clients'!$AD$5:$AD$154,0)),"")
B62: =IFERROR(INDEX('Clients'!$B$5:$B$154,MATCH(4,'Clients'!$AD$5:$AD$154,0))&"","") | C62: =IFERROR(INDEX('Clients'!$D$5:$D$154,MATCH(4,'Clients'!$AD$5:$AD$154,0))&"","") | E62: =IFERROR(INDEX('Clients'!$E$5:$E$154,MATCH(4,'Clients'!$AD$5:$AD$154,0))&"","") | F62: =IFERROR(INDEX('Clients'!$F$5:$F$154,MATCH(4,'Clients'!$AD$5:$AD$154,0))&"","") | G62: =IFERROR(INDEX('Clients'!$Q$5:$Q$154,MATCH(4,'Clients'!$AD$5:$AD$154,0)),"") | H62: =IFERROR(INDEX('Clients'!$K$5:$K$154,MATCH(4,'Clients'!$AD$5:$AD$154,0))&"","") | I62: =IFERROR(INDEX('Clients'!$U$5:$U$154,MATCH(4,'Clients'!$AD$5:$AD$154,0)),"") | J62: =IFERROR(INDEX('Clients'!$Z$5:$Z$154,MATCH(4,'Clients'!$AD$5:$AD$154,0)),"")
B63: =IFERROR(INDEX('Clients'!$B$5:$B$154,MATCH(5,'Clients'!$AD$5:$AD$154,0))&"","") | C63: =IFERROR(INDEX('Clients'!$D$5:$D$154,MATCH(5,'Clients'!$AD$5:$AD$154,0))&"","") | E63: =IFERROR(INDEX('Clients'!$E$5:$E$154,MATCH(5,'Clients'!$AD$5:$AD$154,0))&"","") | F63: =IFERROR(INDEX('Clients'!$F$5:$F$154,MATCH(5,'Clients'!$AD$5:$AD$154,0))&"","") | G63: =IFERROR(INDEX('Clients'!$Q$5:$Q$154,MATCH(5,'Clients'!$AD$5:$AD$154,0)),"") | H63: =IFERROR(INDEX('Clients'!$K$5:$K$154,MATCH(5,'Clients'!$AD$5:$AD$154,0))&"","") | I63: =IFERROR(INDEX('Clients'!$U$5:$U$154,MATCH(5,'Clients'!$AD$5:$AD$154,0)),"") | J63: =IFERROR(INDEX('Clients'!$Z$5:$Z$154,MATCH(5,'Clients'!$AD$5:$AD$154,0)),"")
B64: =IFERROR(INDEX('Clients'!$B$5:$B$154,MATCH(6,'Clients'!$AD$5:$AD$154,0))&"","") | C64: =IFERROR(INDEX('Clients'!$D$5:$D$154,MATCH(6,'Clients'!$AD$5:$AD$154,0))&"","") | E64: =IFERROR(INDEX('Clients'!$E$5:$E$154,MATCH(6,'Clients'!$AD$5:$AD$154,0))&"","") | F64: =IFERROR(INDEX('Clients'!$F$5:$F$154,MATCH(6,'Clients'!$AD$5:$AD$154,0))&"","") | G64: =IFERROR(INDEX('Clients'!$Q$5:$Q$154,MATCH(6,'Clients'!$AD$5:$AD$154,0)),"") | H64: =IFERROR(INDEX('Clients'!$K$5:$K$154,MATCH(6,'Clients'!$AD$5:$AD$154,0))&"","") | I64: =IFERROR(INDEX('Clients'!$U$5:$U$154,MATCH(6,'Clients'!$AD$5:$AD$154,0)),"") | J64: =IFERROR(INDEX('Clients'!$Z$5:$Z$154,MATCH(6,'Clients'!$AD$5:$AD$154,0)),"")
B65: =IFERROR(INDEX('Clients'!$B$5:$B$154,MATCH(7,'Clients'!$AD$5:$AD$154,0))&"","") | C65: =IFERROR(INDEX('Clients'!$D$5:$D$154,MATCH(7,'Clients'!$AD$5:$AD$154,0))&"","") | E65: =IFERROR(INDEX('Clients'!$E$5:$E$154,MATCH(7,'Clients'!$AD$5:$AD$154,0))&"","") | F65: =IFERROR(INDEX('Clients'!$F$5:$F$154,MATCH(7,'Clients'!$AD$5:$AD$154,0))&"","") | G65: =IFERROR(INDEX('Clients'!$Q$5:$Q$154,MATCH(7,'Clients'!$AD$5:$AD$154,0)),"") | H65: =IFERROR(INDEX('Clients'!$K$5:$K$154,MATCH(7,'Clients'!$AD$5:$AD$154,0))&"","") | I65: =IFERROR(INDEX('Clients'!$U$5:$U$154,MATCH(7,'Clients'!$AD$5:$AD$154,0)),"") | J65: =IFERROR(INDEX('Clients'!$Z$5:$Z$154,MATCH(7,'Clients'!$AD$5:$AD$154,0)),"")
B67: 📞 SCRIPT D'APPEL (version complète dans SOP)
B68: Accroche | C68: « Bonjour [prénom], [ton prénom] d'Agence Elite. J'ai vu votre publicité Instagram pour [offre], je vous appelle parce que j'ai remarqué un point qui vous fait sûrement perdre des clients. Vous avez 2 minutes ? »
B69: Question 1 | C69: « Aujourd'hui, la plupart de vos clients vous trouvent comment ? »
B70: Question 2 | C70: « Quand quelqu'un voit votre pub, il atterrit où ? Il peut réserver directement ? »
B71: Question 3 | C71: « Si on pouvait vous amener X clients de plus par mois, ce serait utile maintenant ? »
B72: Proposition | C72: « Je vous prépare un audit gratuit en vidéo de 5 minutes, avec une démo de ce que ça pourrait donner. On se cale 15 minutes [jour] pour le regarder ensemble ? »

Sheet Saisie
A1: =HYPERLINK("#'Ma journée'!A1","☀ Ma journée") | B1: ✎ SAISIE — le seul onglet à remplir
A2: Une ligne par action : appel, DM, relance, audit, RDV, proposition, signature, paiement… Nouveau prospect : tape son nom et remplis sa fiche (colonnes du milieu) sur cette première ligne. Ensuite, choisis-le dans la liste. Tout le reste du fichier se met à jour tout seul. Ajoute les lignes à la suite, dans l'ordre chronologique. Les lignes « EXEMPLE » sont à supprimer.
A3: ACTION (à chaque ligne) | R3: FICHE PROSPECT (1re ligne du prospect, puis seulement si ça change) | AN3: QUALIFICATION | AR3: AUTOMATIQUE (ne pas modifier)
A4: Date | B4: Heure | C4: Prospect (entreprise) | D4: Canal | E4: Action | F4: Résultat | G4: Montant (€) | H4: Durée (min) | I4: Prochaine action | J4: Date de relance (vide = auto) | K4: Heure de rappel | L4: Objection / motif de perte | M4: Modèle / accroche | N4: Note (audit /100, satisfaction /10) | O4: N° facture | P4: Remise (€) | Q4: Notes | R4: Secteur | S4: Ville | T4: Zone | U4: Nom du contact | V4: Fonction | W4: Téléphone | X4: WhatsApp (si différent) | Y4: Instagram | Z4: Site internet | AA4: Source | AB4: Recommandé par | AC4: Pub Insta active ? | AD4: Date de la pub | AE4: Budget pub | AF4: Présence Google | AG4: Note Google | AH4: Nb avis Google | AI4: Taille | AJ4: Concurrent en place | AK4: Personne au standard | AL4: Offre | AM4: Abonnement mensuel (€) | AN4: Budget OK ? | AO4: Décideur joint ? | AP4: Besoin confirmé ? | AQ4: Délai | AR4: Contrôle | AS4: N° ligne | AT4: Étape atteinte | AU4: Prospection ? | AV4: Réponse ? | AW4: Montant retenu | AX4: N° prospect | AY4: Heure (h) | AZ4: Jour (1 = lundi) | BA4: Canal du prospect | BB4: Rang fiche
A5: 46266 | E5: Dépense | G5: 49 | Q5: Abonnement Loom (EXEMPLE) | AR5: =IF(AND(C5="",E5=""),"",IF(A5="","⚠ Date manquante",IF(AND(C5="",E5<>"Dépense"),"⚠ Prospect manquant",IF(E5="","⚠ Action manquante",IF(AND(AU5=1,D5=""),"⚠ Canal manquant",IF(AND(W5<>"",COUNTIFS('Saisie'!$W$5:$W$2004,W5,'Saisie'!$C$5:$C$2004,"<>"&C5)>0),"⚠ Numéro déjà utilisé par un autre prospect",IF(AND(J5<>"",J5<A5),"⚠ Relance avant la date de l'action",IF(A5>TODAY(),"⚠ Date dans le futur","✓")))))))) | AS5: =IF(AND(A5="",C5="",E5=""),"",ROW()) | AT5: =IF(E5&F5="","",MAX(IFERROR(INDEX('Paramètres'!$J$6:$J$33,MATCH(E5,'Paramètres'!$I$6:$I$33,0)),0),IFERROR(INDEX('Paramètres'!$N$6:$N$17,MATCH(F5,'Paramètres'!$M$6:$M$17,0)),0))) | AU5: =IF(E5="","",IFERROR(IF(INDEX('Paramètres'!$K$6:$K$33,MATCH(E5,'Paramètres'!$I$6:$I$33,0))="Oui",1,0),0)) | AV5: =IF(F5="","",IFERROR(IF(INDEX('Paramètres'!$O$6:$O$17,MATCH(F5,'Paramètres'!$M$6:$M$17,0))="Oui",1,0),0)) | AW5: =IF(E5="","",IF(G5<>"",G5,IF(OR(E5="Proposition envoyée",E5="Signature"),MAX(0,N(IFERROR(INDEX('Paramètres'!$R$6:$R$15,MATCH(IF(AL5<>"",AL5,IFERROR(INDEX('Prospects'!$AN$5:$AN$504,MATCH(C5,'Prospects'!$C$5:$C$504,0)),"")),'Paramètres'!$Q$6:$Q$15,0)),0))-N(P5)),0))) | AX5: =IF(C5="","",IF(COUNTIF($C$5:C5,C5)=1,MAX($AX$4:AX4)+1,"")) | AY5: =IF(B5="","",HOUR(B5)) | AZ5: =IF(A5="","",MOD(A5-2,7)+1) | BA5: =IF(C5="","",IFERROR(INDEX('Prospects'!$N$5:$N$504,MATCH(C5,'Prospects'!$C$5:$C$504,0)),"")) | BB5: =IF(AND(C5<>"",C5='Fiche prospect'!$C$4),COUNTIF($C$5:C5,C5),"")
A6: 46275 | B6: 0.45833333 | C6: Studio Fit (EXEMPLE) | D6: Facebook | E6: Premier contact | F6: Pas intéressé | L6: J'ai déjà quelqu'un | M6: DM 2 - Audit gratuit | R6: Sport / Fitness | S6: Lyon | T6: Périphérie | U6: Léa Dubois | W6: 06 11 22 33 44 | Y6: @studiofit | Z6: studiofit.fr | AA6: Facebook | AC6: Non | AF6: Bonne | AI6: Moyenne | AR6: =IF(AND(C6="",E6=""),"",IF(A6="","⚠ Date manquante",IF(AND(C6="",E6<>"Dépense"),"⚠ Prospect manquant",IF(E6="","⚠ Action manquante",IF(AND(AU6=1,D6=""),"⚠ Canal manquant",IF(AND(W6<>"",COUNTIFS('Saisie'!$W$5:$W$2004,W6,'Saisie'!$C$5:$C$2004,"<>"&C6)>0),"⚠ Numéro déjà utilisé par un autre prospect",IF(AND(J6<>"",J6<A6),"⚠ Relance avant la date de l'action",IF(A6>TODAY(),"⚠ Date dans le futur","✓")))))))) | AS6: =IF(AND(A6="",C6="",E6=""),"",ROW()) | AT6: =IF(E6&F6="","",MAX(IFERROR(INDEX('Paramètres'!$J$6:$J$33,MATCH(E6,'Paramètres'!$I$6:$I$33,0)),0),IFERROR(INDEX('Paramètres'!$N$6:$N$17,MATCH(F6,'Paramètres'!$M$6:$M$17,0)),0))) | AU6: =IF(E6="","",IFERROR(IF(INDEX('Paramètres'!$K$6:$K$33,MATCH(E6,'Paramètres'!$I$6:$I$33,0))="Oui",1,0),0)) | AV6: =IF(F6="","",IFERROR(IF(INDEX('Paramètres'!$O$6:$O$17,MATCH(F6,'Paramètres'!$M$6:$M$17,0))="Oui",1,0),0)) | AW6: =IF(E6="","",IF(G6<>"",G6,IF(OR(E6="Proposition envoyée",E6="Signature"),MAX(0,N(IFERROR(INDEX('Paramètres'!$R$6:$R$15,MATCH(IF(AL6<>"",AL6,IFERROR(INDEX('Prospects'!$AN$5:$AN$504,MATCH(C6,'Prospects'!$C$5:$C$504,0)),"")),'Paramètres'!$Q$6:$Q$15,0)),0))-N(P6)),0))) | AX6: =IF(C6="","",IF(COUNTIF($C$5:C6,C6)=1,MAX($AX$4:AX5)+1,"")) | AY6: =IF(B6="","",HOUR(B6)) | AZ6: =IF(A6="","",MOD(A6-2,7)+1) | BA6: =IF(C6="","",IFERROR(INDEX('Prospects'!$N$5:$N$504,MATCH(C6,'Prospects'!$C$5:$C$504,0)),"")) | BB6: =IF(AND(C6<>"",C6='Fiche prospect'!$C$4),COUNTIF($C$5:C6,C6),"")
A7: 46277 | C7: Studio Fit (EXEMPLE) | E7: Perdu | L7: J'ai déjà quelqu'un | AR7: =IF(AND(C7="",E7=""),"",IF(A7="","⚠ Date manquante",IF(AND(C7="",E7<>"Dépense"),"⚠ Prospect manquant",IF(E7="","⚠ Action manquante",IF(AND(AU7=1,D7=""),"⚠ Canal manquant",IF(AND(W7<>"",COUNTIFS('Saisie'!$W$5:$W$2004,W7,'Saisie'!$C$5:$C$2004,"<>"&C7)>0),"⚠ Numéro déjà utilisé par un autre prospect",IF(AND(J7<>"",J7<A7),"⚠ Relance avant la date de l'action",IF(A7>TODAY(),"⚠ Date dans le futur","✓")))))))) | AS7: =IF(AND(A7="",C7="",E7=""),"",ROW()) | AT7: =IF(E7&F7="","",MAX(IFERROR(INDEX('Paramètres'!$J$6:$J$33,MATCH(E7,'Paramètres'!$I$6:$I$33,0)),0),IFERROR(INDEX('Paramètres'!$N$6:$N$17,MATCH(F7,'Paramètres'!$M$6:$M$17,0)),0))) | AU7: =IF(E7="","",IFERROR(IF(INDEX('Paramètres'!$K$6:$K$33,MATCH(E7,'Paramètres'!$I$6:$I$33,0))="Oui",1,0),0)) | AV7: =IF(F7="","",IFERROR(IF(INDEX('Paramètres'!$O$6:$O$17,MATCH(F7,'Paramètres'!$M$6:$M$17,0))="Oui",1,0),0)) | AW7: =IF(E7="","",IF(G7<>"",G7,IF(OR(E7="Proposition envoyée",E7="Signature"),MAX(0,N(IFERROR(INDEX('Paramètres'!$R$6:$R$15,MATCH(IF(AL7<>"",AL7,IFERROR(INDEX('Prospects'!$AN$5:$AN$504,MATCH(C7,'Prospects'!$C$5:$C$504,0)),"")),'Paramètres'!$Q$6:$Q$15,0)),0))-N(P7)),0))) | AX7: =IF(C7="","",IF(COUNTIF($C$5:C7,C7)=1,MAX($AX$4:AX6)+1,"")) | AY7: =IF(B7="","",HOUR(B7)) | AZ7: =IF(A7="","",MOD(A7-2,7)+1) | BA7: =IF(C7="","",IFERROR(INDEX('Prospects'!$N$5:$N$504,MATCH(C7,'Prospects'!$C$5:$C$504,0)),"")) | BB7: =IF(AND(C7<>"",C7='Fiche prospect'!$C$4),COUNTIF($C$5:C7,C7),"")
A8: 46280 | B8: 0.73611111 | C8: Pizzeria Da Marco (EXEMPLE) | D8: Appel | E8: Premier contact | F8: Messagerie - vocal laissé | H8: 1 | M8: Accroche A - Pub Insta | R8: Restaurant | S8: Lyon | T8: Centre-ville | U8: Marco Rossi | V8: Gérant | W8: 06 55 44 33 22 | Y8: @damarco | Z8: damarco.fr | AA8: Publicité Instagram | AC8: Oui | AD8: 46275 | AE8: Occasionnelle | AF8: Bonne | AG8: 4.6 | AH8: 210 | AI8: Petite | AR8: =IF(AND(C8="",E8=""),"",IF(A8="","⚠ Date manquante",IF(AND(C8="",E8<>"Dépense"),"⚠ Prospect manquant",IF(E8="","⚠ Action manquante",IF(AND(AU8=1,D8=""),"⚠ Canal manquant",IF(AND(W8<>"",COUNTIFS('Saisie'!$W$5:$W$2004,W8,'Saisie'!$C$5:$C$2004,"<>"&C8)>0),"⚠ Numéro déjà utilisé par un autre prospect",IF(AND(J8<>"",J8<A8),"⚠ Relance avant la date de l'action",IF(A8>TODAY(),"⚠ Date dans le futur","✓")))))))) | AS8: =IF(AND(A8="",C8="",E8=""),"",ROW()) | AT8: =IF(E8&F8="","",MAX(IFERROR(INDEX('Paramètres'!$J$6:$J$33,MATCH(E8,'Paramètres'!$I$6:$I$33,0)),0),IFERROR(INDEX('Paramètres'!$N$6:$N$17,MATCH(F8,'Paramètres'!$M$6:$M$17,0)),0))) | AU8: =IF(E8="","",IFERROR(IF(INDEX('Paramètres'!$K$6:$K$33,MATCH(E8,'Paramètres'!$I$6:$I$33,0))="Oui",1,0),0)) | AV8: =IF(F8="","",IFERROR(IF(INDEX('Paramètres'!$O$6:$O$17,MATCH(F8,'Paramètres'!$M$6:$M$17,0))="Oui",1,0),0)) | AW8: =IF(E8="","",IF(G8<>"",G8,IF(OR(E8="Proposition envoyée",E8="Signature"),MAX(0,N(IFERROR(INDEX('Paramètres'!$R$6:$R$15,MATCH(IF(AL8<>"",AL8,IFERROR(INDEX('Prospects'!$AN$5:$AN$504,MATCH(C8,'Prospects'!$C$5:$C$504,0)),"")),'Paramètres'!$Q$6:$Q$15,0)),0))-N(P8)),0))) | AX8: =IF(C8="","",IF(COUNTIF($C$5:C8,C8)=1,MAX($AX$4:AX7)+1,"")) | AY8: =IF(B8="","",HOUR(B8)) | AZ8: =IF(A8="","",MOD(A8-2,7)+1) | BA8: =IF(C8="","",IFERROR(INDEX('Prospects'!$N$5:$N$504,MATCH(C8,'Prospects'!$C$5:$C$504,0)),"")) | BB8: =IF(AND(C8<>"",C8='Fiche prospect'!$C$4),COUNTIF($C$5:C8,C8),"")
A9: 46281 | B9: 0.75694444 | C9: Pizzeria Da Marco (EXEMPLE) | D9: Appel | E9: Relance | F9: Intéressé | H9: 5 | I9: Rappeler pour fixer le RDV | J9: 46285 | K9: 0.45833333 | AN9: À voir | AO9: Oui | AP9: Oui | AR9: =IF(AND(C9="",E9=""),"",IF(A9="","⚠ Date manquante",IF(AND(C9="",E9<>"Dépense"),"⚠ Prospect manquant",IF(E9="","⚠ Action manquante",IF(AND(AU9=1,D9=""),"⚠ Canal manquant",IF(AND(W9<>"",COUNTIFS('Saisie'!$W$5:$W$2004,W9,'Saisie'!$C$5:$C$2004,"<>"&C9)>0),"⚠ Numéro déjà utilisé par un autre prospect",IF(AND(J9<>"",J9<A9),"⚠ Relance avant la date de l'action",IF(A9>TODAY(),"⚠ Date dans le futur","✓")))))))) | AS9: =IF(AND(A9="",C9="",E9=""),"",ROW()) | AT9: =IF(E9&F9="","",MAX(IFERROR(INDEX('Paramètres'!$J$6:$J$33,MATCH(E9,'Paramètres'!$I$6:$I$33,0)),0),IFERROR(INDEX('Paramètres'!$N$6:$N$17,MATCH(F9,'Paramètres'!$M$6:$M$17,0)),0))) | AU9: =IF(E9="","",IFERROR(IF(INDEX('Paramètres'!$K$6:$K$33,MATCH(E9,'Paramètres'!$I$6:$I$33,0))="Oui",1,0),0)) | AV9: =IF(F9="","",IFERROR(IF(INDEX('Paramètres'!$O$6:$O$17,MATCH(F9,'Paramètres'!$M$6:$M$17,0))="Oui",1,0),0)) | AW9: =IF(E9="","",IF(G9<>"",G9,IF(OR(E9="Proposition envoyée",E9="Signature"),MAX(0,N(IFERROR(INDEX('Paramètres'!$R$6:$R$15,MATCH(IF(AL9<>"",AL9,IFERROR(INDEX('Prospects'!$AN$5:$AN$504,MATCH(C9,'Prospects'!$C$5:$C$504,0)),"")),'Paramètres'!$Q$6:$Q$15,0)),0))-N(P9)),0))) | AX9: =IF(C9="","",IF(COUNTIF($C$5:C9,C9)=1,MAX($AX$4:AX8)+1,"")) | AY9: =IF(B9="","",HOUR(B9)) | AZ9: =IF(A9="","",MOD(A9-2,7)+1) | BA9: =IF(C9="","",IFERROR(INDEX('Prospects'!$N$5:$N$504,MATCH(C9,'Prospects'!$C$5:$C$504,0)),"")) | BB9: =IF(AND(C9<>"",C9='Fiche prospect'!$C$4),COUNTIF($C$5:C9,C9),"")
A10: 46286 | B10: 0.42708333 | C10: Institut Belle Peau (EXEMPLE) | D10: Appel | E10: Premier contact | F10: Intéressé | H10: 8 | I10: Envoyer audit + Loom | M10: Accroche A - Pub Insta | R10: Esthétique / Beauté | S10: Lyon | T10: Centre-ville | U10: Sarah Martin | V10: Gérante | W10: 06 12 34 56 78 | Y10: @bellepeau.lyon | Z10: bellepeau-lyon.fr | AA10: Publicité Instagram | AC10: Oui | AD10: 46283 | AE10: Régulière | AF10: Faible | AG10: 4.1 | AH10: 23 | AI10: Petite | AN10: Oui | AO10: Oui | AP10: Oui | AQ10: < 1 mois | AR10: =IF(AND(C10="",E10=""),"",IF(A10="","⚠ Date manquante",IF(AND(C10="",E10<>"Dépense"),"⚠ Prospect manquant",IF(E10="","⚠ Action manquante",IF(AND(AU10=1,D10=""),"⚠ Canal manquant",IF(AND(W10<>"",COUNTIFS('Saisie'!$W$5:$W$2004,W10,'Saisie'!$C$5:$C$2004,"<>"&C10)>0),"⚠ Numéro déjà utilisé par un autre prospect",IF(AND(J10<>"",J10<A10),"⚠ Relance avant la date de l'action",IF(A10>TODAY(),"⚠ Date dans le futur","✓")))))))) | AS10: =IF(AND(A10="",C10="",E10=""),"",ROW()) | AT10: =IF(E10&F10="","",MAX(IFERROR(INDEX('Paramètres'!$J$6:$J$33,MATCH(E10,'Paramètres'!$I$6:$I$33,0)),0),IFERROR(INDEX('Paramètres'!$N$6:$N$17,MATCH(F10,'Paramètres'!$M$6:$M$17,0)),0))) | AU10: =IF(E10="","",IFERROR(IF(INDEX('Paramètres'!$K$6:$K$33,MATCH(E10,'Paramètres'!$I$6:$I$33,0))="Oui",1,0),0)) | AV10: =IF(F10="","",IFERROR(IF(INDEX('Paramètres'!$O$6:$O$17,MATCH(F10,'Paramètres'!$M$6:$M$17,0))="Oui",1,0),0)) | AW10: =IF(E10="","",IF(G10<>"",G10,IF(OR(E10="Proposition envoyée",E10="Signature"),MAX(0,N(IFERROR(INDEX('Paramètres'!$R$6:$R$15,MATCH(IF(AL10<>"",AL10,IFERROR(INDEX('Prospects'!$AN$5:$AN$504,MATCH(C10,'Prospects'!$C$5:$C$504,0)),"")),'Paramètres'!$Q$6:$Q$15,0)),0))-N(P10)),0))) | AX10: =IF(C10="","",IF(COUNTIF($C$5:C10,C10)=1,MAX($AX$4:AX9)+1,"")) | AY10: =IF(B10="","",HOUR(B10)) | AZ10: =IF(A10="","",MOD(A10-2,7)+1) | BA10: =IF(C10="","",IFERROR(INDEX('Prospects'!$N$5:$N$504,MATCH(C10,'Prospects'!$C$5:$C$504,0)),"")) | BB10: =IF(AND(C10<>"",C10='Fiche prospect'!$C$4),COUNTIF($C$5:C10,C10),"")
A11: 46287 | C11: Institut Belle Peau (EXEMPLE) | E11: Audit réalisé | H11: 45 | N11: 38 | AR11: =IF(AND(C11="",E11=""),"",IF(A11="","⚠ Date manquante",IF(AND(C11="",E11<>"Dépense"),"⚠ Prospect manquant",IF(E11="","⚠ Action manquante",IF(AND(AU11=1,D11=""),"⚠ Canal manquant",IF(AND(W11<>"",COUNTIFS('Saisie'!$W$5:$W$2004,W11,'Saisie'!$C$5:$C$2004,"<>"&C11)>0),"⚠ Numéro déjà utilisé par un autre prospect",IF(AND(J11<>"",J11<A11),"⚠ Relance avant la date de l'action",IF(A11>TODAY(),"⚠ Date dans le futur","✓")))))))) | AS11: =IF(AND(A11="",C11="",E11=""),"",ROW()) | AT11: =IF(E11&F11="","",MAX(IFERROR(INDEX('Paramètres'!$J$6:$J$33,MATCH(E11,'Paramètres'!$I$6:$I$33,0)),0),IFERROR(INDEX('Paramètres'!$N$6:$N$17,MATCH(F11,'Paramètres'!$M$6:$M$17,0)),0))) | AU11: =IF(E11="","",IFERROR(IF(INDEX('Paramètres'!$K$6:$K$33,MATCH(E11,'Paramètres'!$I$6:$I$33,0))="Oui",1,0),0)) | AV11: =IF(F11="","",IFERROR(IF(INDEX('Paramètres'!$O$6:$O$17,MATCH(F11,'Paramètres'!$M$6:$M$17,0))="Oui",1,0),0)) | AW11: =IF(E11="","",IF(G11<>"",G11,IF(OR(E11="Proposition envoyée",E11="Signature"),MAX(0,N(IFERROR(INDEX('Paramètres'!$R$6:$R$15,MATCH(IF(AL11<>"",AL11,IFERROR(INDEX('Prospects'!$AN$5:$AN$504,MATCH(C11,'Prospects'!$C$5:$C$504,0)),"")),'Paramètres'!$Q$6:$Q$15,0)),0))-N(P11)),0))) | AX11: =IF(C11="","",IF(COUNTIF($C$5:C11,C11)=1,MAX($AX$4:AX10)+1,"")) | AY11: =IF(B11="","",HOUR(B11)) | AZ11: =IF(A11="","",MOD(A11-2,7)+1) | BA11: =IF(C11="","",IFERROR(INDEX('Prospects'!$N$5:$N$504,MATCH(C11,'Prospects'!$C$5:$C$504,0)),"")) | BB11: =IF(AND(C11<>"",C11='Fiche prospect'!$C$4),COUNTIF($C$5:C11,C11),"")
A12: 46287 | B12: 0.45833333 | C12: Garage Auto Rapide (EXEMPLE) | D12: DM | E12: Premier contact | F12: Pas de réponse | M12: DM 1 - Compliment + question | R12: Automobile | S12: Villeurbanne | T12: Périphérie | U12: Karim Benali | V12: Dirigeant | W12: 07 98 76 54 32 | Y12: @autorapide69 | AA12: Profil Instagram | AC12: Non | AF12: Absente | AI12: Moyenne | AR12: =IF(AND(C12="",E12=""),"",IF(A12="","⚠ Date manquante",IF(AND(C12="",E12<>"Dépense"),"⚠ Prospect manquant",IF(E12="","⚠ Action manquante",IF(AND(AU12=1,D12=""),"⚠ Canal manquant",IF(AND(W12<>"",COUNTIFS('Saisie'!$W$5:$W$2004,W12,'Saisie'!$C$5:$C$2004,"<>"&C12)>0),"⚠ Numéro déjà utilisé par un autre prospect",IF(AND(J12<>"",J12<A12),"⚠ Relance avant la date de l'action",IF(A12>TODAY(),"⚠ Date dans le futur","✓")))))))) | AS12: =IF(AND(A12="",C12="",E12=""),"",ROW()) | AT12: =IF(E12&F12="","",MAX(IFERROR(INDEX('Paramètres'!$J$6:$J$33,MATCH(E12,'Paramètres'!$I$6:$I$33,0)),0),IFERROR(INDEX('Paramètres'!$N$6:$N$17,MATCH(F12,'Paramètres'!$M$6:$M$17,0)),0))) | AU12: =IF(E12="","",IFERROR(IF(INDEX('Paramètres'!$K$6:$K$33,MATCH(E12,'Paramètres'!$I$6:$I$33,0))="Oui",1,0),0)) | AV12: =IF(F12="","",IFERROR(IF(INDEX('Paramètres'!$O$6:$O$17,MATCH(F12,'Paramètres'!$M$6:$M$17,0))="Oui",1,0),0)) | AW12: =IF(E12="","",IF(G12<>"",G12,IF(OR(E12="Proposition envoyée",E12="Signature"),MAX(0,N(IFERROR(INDEX('Paramètres'!$R$6:$R$15,MATCH(IF(AL12<>"",AL12,IFERROR(INDEX('Prospects'!$AN$5:$AN$504,MATCH(C12,'Prospects'!$C$5:$C$504,0)),"")),'Paramètres'!$Q$6:$Q$15,0)),0))-N(P12)),0))) | AX12: =IF(C12="","",IF(COUNTIF($C$5:C12,C12)=1,MAX($AX$4:AX11)+1,"")) | AY12: =IF(B12="","",HOUR(B12)) | AZ12: =IF(A12="","",MOD(A12-2,7)+1) | BA12: =IF(C12="","",IFERROR(INDEX('Prospects'!$N$5:$N$504,MATCH(C12,'Prospects'!$C$5:$C$504,0)),"")) | BB12: =IF(AND(C12<>"",C12='Fiche prospect'!$C$4),COUNTIF($C$5:C12,C12),"")
A13: 46287 | C13: Institut Belle Peau (EXEMPLE) | D13: WhatsApp | E13: Loom envoyé | F13: Loom vu | AR13: =IF(AND(C13="",E13=""),"",IF(A13="","⚠ Date manquante",IF(AND(C13="",E13<>"Dépense"),"⚠ Prospect manquant",IF(E13="","⚠ Action manquante",IF(AND(AU13=1,D13=""),"⚠ Canal manquant",IF(AND(W13<>"",COUNTIFS('Saisie'!$W$5:$W$2004,W13,'Saisie'!$C$5:$C$2004,"<>"&C13)>0),"⚠ Numéro déjà utilisé par un autre prospect",IF(AND(J13<>"",J13<A13),"⚠ Relance avant la date de l'action",IF(A13>TODAY(),"⚠ Date dans le futur","✓")))))))) | AS13: =IF(AND(A13="",C13="",E13=""),"",ROW()) | AT13: =IF(E13&F13="","",MAX(IFERROR(INDEX('Paramètres'!$J$6:$J$33,MATCH(E13,'Paramètres'!$I$6:$I$33,0)),0),IFERROR(INDEX('Paramètres'!$N$6:$N$17,MATCH(F13,'Paramètres'!$M$6:$M$17,0)),0))) | AU13: =IF(E13="","",IFERROR(IF(INDEX('Paramètres'!$K$6:$K$33,MATCH(E13,'Paramètres'!$I$6:$I$33,0))="Oui",1,0),0)) | AV13: =IF(F13="","",IFERROR(IF(INDEX('Paramètres'!$O$6:$O$17,MATCH(F13,'Paramètres'!$M$6:$M$17,0))="Oui",1,0),0)) | AW13: =IF(E13="","",IF(G13<>"",G13,IF(OR(E13="Proposition envoyée",E13="Signature"),MAX(0,N(IFERROR(INDEX('Paramètres'!$R$6:$R$15,MATCH(IF(AL13<>"",AL13,IFERROR(INDEX('Prospects'!$AN$5:$AN$504,MATCH(C13,'Prospects'!$C$5:$C$504,0)),"")),'Paramètres'!$Q$6:$Q$15,0)),0))-N(P13)),0))) | AX13: =IF(C13="","",IF(COUNTIF($C$5:C13,C13)=1,MAX($AX$4:AX12)+1,"")) | AY13: =IF(B13="","",HOUR(B13)) | AZ13: =IF(A13="","",MOD(A13-2,7)+1) | BA13: =IF(C13="","",IFERROR(INDEX('Prospects'!$N$5:$N$504,MATCH(C13,'Prospects'!$C$5:$C$504,0)),"")) | BB13: =IF(AND(C13<>"",C13='Fiche prospect'!$C$4),COUNTIF($C$5:C13,C13),"")
A14: 46288 | B14: 0.60416667 | C14: Institut Belle Peau (EXEMPLE) | D14: Appel | E14: Échange / suivi | F14: RDV pris | H14: 6 | AR14: =IF(AND(C14="",E14=""),"",IF(A14="","⚠ Date manquante",IF(AND(C14="",E14<>"Dépense"),"⚠ Prospect manquant",IF(E14="","⚠ Action manquante",IF(AND(AU14=1,D14=""),"⚠ Canal manquant",IF(AND(W14<>"",COUNTIFS('Saisie'!$W$5:$W$2004,W14,'Saisie'!$C$5:$C$2004,"<>"&C14)>0),"⚠ Numéro déjà utilisé par un autre prospect",IF(AND(J14<>"",J14<A14),"⚠ Relance avant la date de l'action",IF(A14>TODAY(),"⚠ Date dans le futur","✓")))))))) | AS14: =IF(AND(A14="",C14="",E14=""),"",ROW()) | AT14: =IF(E14&F14="","",MAX(IFERROR(INDEX('Paramètres'!$J$6:$J$33,MATCH(E14,'Paramètres'!$I$6:$I$33,0)),0),IFERROR(INDEX('Paramètres'!$N$6:$N$17,MATCH(F14,'Paramètres'!$M$6:$M$17,0)),0))) | AU14: =IF(E14="","",IFERROR(IF(INDEX('Paramètres'!$K$6:$K$33,MATCH(E14,'Paramètres'!$I$6:$I$33,0))="Oui",1,0),0)) | AV14: =IF(F14="","",IFERROR(IF(INDEX('Paramètres'!$O$6:$O$17,MATCH(F14,'Paramètres'!$M$6:$M$17,0))="Oui",1,0),0)) | AW14: =IF(E14="","",IF(G14<>"",G14,IF(OR(E14="Proposition envoyée",E14="Signature"),MAX(0,N(IFERROR(INDEX('Paramètres'!$R$6:$R$15,MATCH(IF(AL14<>"",AL14,IFERROR(INDEX('Prospects'!$AN$5:$AN$504,MATCH(C14,'Prospects'!$C$5:$C$504,0)),"")),'Paramètres'!$Q$6:$Q$15,0)),0))-N(P14)),0))) | AX14: =IF(C14="","",IF(COUNTIF($C$5:C14,C14)=1,MAX($AX$4:AX13)+1,"")) | AY14: =IF(B14="","",HOUR(B14)) | AZ14: =IF(A14="","",MOD(A14-2,7)+1) | BA14: =IF(C14="","",IFERROR(INDEX('Prospects'!$N$5:$N$504,MATCH(C14,'Prospects'!$C$5:$C$504,0)),"")) | BB14: =IF(AND(C14<>"",C14='Fiche prospect'!$C$4),COUNTIF($C$5:C14,C14),"")
A15: 46289 | B15: 0.39583333 | C15: Garage Auto Rapide (EXEMPLE) | D15: DM | E15: Relance | F15: Pas de réponse | M15: DM 2 - Audit gratuit | AR15: =IF(AND(C15="",E15=""),"",IF(A15="","⚠ Date manquante",IF(AND(C15="",E15<>"Dépense"),"⚠ Prospect manquant",IF(E15="","⚠ Action manquante",IF(AND(AU15=1,D15=""),"⚠ Canal manquant",IF(AND(W15<>"",COUNTIFS('Saisie'!$W$5:$W$2004,W15,'Saisie'!$C$5:$C$2004,"<>"&C15)>0),"⚠ Numéro déjà utilisé par un autre prospect",IF(AND(J15<>"",J15<A15),"⚠ Relance avant la date de l'action",IF(A15>TODAY(),"⚠ Date dans le futur","✓")))))))) | AS15: =IF(AND(A15="",C15="",E15=""),"",ROW()) | AT15: =IF(E15&F15="","",MAX(IFERROR(INDEX('Paramètres'!$J$6:$J$33,MATCH(E15,'Paramètres'!$I$6:$I$33,0)),0),IFERROR(INDEX('Paramètres'!$N$6:$N$17,MATCH(F15,'Paramètres'!$M$6:$M$17,0)),0))) | AU15: =IF(E15="","",IFERROR(IF(INDEX('Paramètres'!$K$6:$K$33,MATCH(E15,'Paramètres'!$I$6:$I$33,0))="Oui",1,0),0)) | AV15: =IF(F15="","",IFERROR(IF(INDEX('Paramètres'!$O$6:$O$17,MATCH(F15,'Paramètres'!$M$6:$M$17,0))="Oui",1,0),0)) | AW15: =IF(E15="","",IF(G15<>"",G15,IF(OR(E15="Proposition envoyée",E15="Signature"),MAX(0,N(IFERROR(INDEX('Paramètres'!$R$6:$R$15,MATCH(IF(AL15<>"",AL15,IFERROR(INDEX('Prospects'!$AN$5:$AN$504,MATCH(C15,'Prospects'!$C$5:$C$504,0)),"")),'Paramètres'!$Q$6:$Q$15,0)),0))-N(P15)),0))) | AX15: =IF(C15="","",IF(COUNTIF($C$5:C15,C15)=1,MAX($AX$4:AX14)+1,"")) | AY15: =IF(B15="","",HOUR(B15)) | AZ15: =IF(A15="","",MOD(A15-2,7)+1) | BA15: =IF(C15="","",IFERROR(INDEX('Prospects'!$N$5:$N$504,MATCH(C15,'Prospects'!$C$5:$C$504,0)),"")) | BB15: =IF(AND(C15<>"",C15='Fiche prospect'!$C$4),COUNTIF($C$5:C15,C15),"")
A16: 46289 | C16: Institut Belle Peau (EXEMPLE) | E16: RDV | F16: Intéressé | H16: 40 | I16: Envoyer la proposition | AR16: =IF(AND(C16="",E16=""),"",IF(A16="","⚠ Date manquante",IF(AND(C16="",E16<>"Dépense"),"⚠ Prospect manquant",IF(E16="","⚠ Action manquante",IF(AND(AU16=1,D16=""),"⚠ Canal manquant",IF(AND(W16<>"",COUNTIFS('Saisie'!$W$5:$W$2004,W16,'Saisie'!$C$5:$C$2004,"<>"&C16)>0),"⚠ Numéro déjà utilisé par un autre prospect",IF(AND(J16<>"",J16<A16),"⚠ Relance avant la date de l'action",IF(A16>TODAY(),"⚠ Date dans le futur","✓")))))))) | AS16: =IF(AND(A16="",C16="",E16=""),"",ROW()) | AT16: =IF(E16&F16="","",MAX(IFERROR(INDEX('Paramètres'!$J$6:$J$33,MATCH(E16,'Paramètres'!$I$6:$I$33,0)),0),IFERROR(INDEX('Paramètres'!$N$6:$N$17,MATCH(F16,'Paramètres'!$M$6:$M$17,0)),0))) | AU16: =IF(E16="","",IFERROR(IF(INDEX('Paramètres'!$K$6:$K$33,MATCH(E16,'Paramètres'!$I$6:$I$33,0))="Oui",1,0),0)) | AV16: =IF(F16="","",IFERROR(IF(INDEX('Paramètres'!$O$6:$O$17,MATCH(F16,'Paramètres'!$M$6:$M$17,0))="Oui",1,0),0)) | AW16: =IF(E16="","",IF(G16<>"",G16,IF(OR(E16="Proposition envoyée",E16="Signature"),MAX(0,N(IFERROR(INDEX('Paramètres'!$R$6:$R$15,MATCH(IF(AL16<>"",AL16,IFERROR(INDEX('Prospects'!$AN$5:$AN$504,MATCH(C16,'Prospects'!$C$5:$C$504,0)),"")),'Paramètres'!$Q$6:$Q$15,0)),0))-N(P16)),0))) | AX16: =IF(C16="","",IF(COUNTIF($C$5:C16,C16)=1,MAX($AX$4:AX15)+1,"")) | AY16: =IF(B16="","",HOUR(B16)) | AZ16: =IF(A16="","",MOD(A16-2,7)+1) | BA16: =IF(C16="","",IFERROR(INDEX('Prospects'!$N$5:$N$504,MATCH(C16,'Prospects'!$C$5:$C$504,0)),"")) | BB16: =IF(AND(C16<>"",C16='Fiche prospect'!$C$4),COUNTIF($C$5:C16,C16),"")
A17: 46289 | C17: Institut Belle Peau (EXEMPLE) | E17: Proposition envoyée | AL17: Site + réservation | AM17: 90 | AR17: =IF(AND(C17="",E17=""),"",IF(A17="","⚠ Date manquante",IF(AND(C17="",E17<>"Dépense"),"⚠ Prospect manquant",IF(E17="","⚠ Action manquante",IF(AND(AU17=1,D17=""),"⚠ Canal manquant",IF(AND(W17<>"",COUNTIFS('Saisie'!$W$5:$W$2004,W17,'Saisie'!$C$5:$C$2004,"<>"&C17)>0),"⚠ Numéro déjà utilisé par un autre prospect",IF(AND(J17<>"",J17<A17),"⚠ Relance avant la date de l'action",IF(A17>TODAY(),"⚠ Date dans le futur","✓")))))))) | AS17: =IF(AND(A17="",C17="",E17=""),"",ROW()) | AT17: =IF(E17&F17="","",MAX(IFERROR(INDEX('Paramètres'!$J$6:$J$33,MATCH(E17,'Paramètres'!$I$6:$I$33,0)),0),IFERROR(INDEX('Paramètres'!$N$6:$N$17,MATCH(F17,'Paramètres'!$M$6:$M$17,0)),0))) | AU17: =IF(E17="","",IFERROR(IF(INDEX('Paramètres'!$K$6:$K$33,MATCH(E17,'Paramètres'!$I$6:$I$33,0))="Oui",1,0),0)) | AV17: =IF(F17="","",IFERROR(IF(INDEX('Paramètres'!$O$6:$O$17,MATCH(F17,'Paramètres'!$M$6:$M$17,0))="Oui",1,0),0)) | AW17: =IF(E17="","",IF(G17<>"",G17,IF(OR(E17="Proposition envoyée",E17="Signature"),MAX(0,N(IFERROR(INDEX('Paramètres'!$R$6:$R$15,MATCH(IF(AL17<>"",AL17,IFERROR(INDEX('Prospects'!$AN$5:$AN$504,MATCH(C17,'Prospects'!$C$5:$C$504,0)),"")),'Paramètres'!$Q$6:$Q$15,0)),0))-N(P17)),0))) | AX17: =IF(C17="","",IF(COUNTIF($C$5:C17,C17)=1,MAX($AX$4:AX16)+1,"")) | AY17: =IF(B17="","",HOUR(B17)) | AZ17: =IF(A17="","",MOD(A17-2,7)+1) | BA17: =IF(C17="","",IFERROR(INDEX('Prospects'!$N$5:$N$504,MATCH(C17,'Prospects'!$C$5:$C$504,0)),"")) | BB17: =IF(AND(C17<>"",C17='Fiche prospect'!$C$4),COUNTIF($C$5:C17,C17),"")
A18: 46290 | C18: Institut Belle Peau (EXEMPLE) | E18: Signature | AR18: =IF(AND(C18="",E18=""),"",IF(A18="","⚠ Date manquante",IF(AND(C18="",E18<>"Dépense"),"⚠ Prospect manquant",IF(E18="","⚠ Action manquante",IF(AND(AU18=1,D18=""),"⚠ Canal manquant",IF(AND(W18<>"",COUNTIFS('Saisie'!$W$5:$W$2004,W18,'Saisie'!$C$5:$C$2004,"<>"&C18)>0),"⚠ Numéro déjà utilisé par un autre prospect",IF(AND(J18<>"",J18<A18),"⚠ Relance avant la date de l'action",IF(A18>TODAY(),"⚠ Date dans le futur","✓")))))))) | AS18: =IF(AND(A18="",C18="",E18=""),"",ROW()) | AT18: =IF(E18&F18="","",MAX(IFERROR(INDEX('Paramètres'!$J$6:$J$33,MATCH(E18,'Paramètres'!$I$6:$I$33,0)),0),IFERROR(INDEX('Paramètres'!$N$6:$N$17,MATCH(F18,'Paramètres'!$M$6:$M$17,0)),0))) | AU18: =IF(E18="","",IFERROR(IF(INDEX('Paramètres'!$K$6:$K$33,MATCH(E18,'Paramètres'!$I$6:$I$33,0))="Oui",1,0),0)) | AV18: =IF(F18="","",IFERROR(IF(INDEX('Paramètres'!$O$6:$O$17,MATCH(F18,'Paramètres'!$M$6:$M$17,0))="Oui",1,0),0)) | AW18: =IF(E18="","",IF(G18<>"",G18,IF(OR(E18="Proposition envoyée",E18="Signature"),MAX(0,N(IFERROR(INDEX('Paramètres'!$R$6:$R$15,MATCH(IF(AL18<>"",AL18,IFERROR(INDEX('Prospects'!$AN$5:$AN$504,MATCH(C18,'Prospects'!$C$5:$C$504,0)),"")),'Paramètres'!$Q$6:$Q$15,0)),0))-N(P18)),0))) | AX18: =IF(C18="","",IF(COUNTIF($C$5:C18,C18)=1,MAX($AX$4:AX17)+1,"")) | AY18: =IF(B18="","",HOUR(B18)) | AZ18: =IF(A18="","",MOD(A18-2,7)+1) | BA18: =IF(C18="","",IFERROR(INDEX('Prospects'!$N$5:$N$504,MATCH(C18,'Prospects'!$C$5:$C$504,0)),"")) | BB18: =IF(AND(C18<>"",C18='Fiche prospect'!$C$4),COUNTIF($C$5:C18,C18),"")
A19: 46290 | C19: Institut Belle Peau (EXEMPLE) | E19: Paiement reçu | G19: 900 | O19: F-2026-001 | Q19: Acompte 50 % | AR19: =IF(AND(C19="",E19=""),"",IF(A19="","⚠ Date manquante",IF(AND(C19="",E19<>"Dépense"),"⚠ Prospect manquant",IF(E19="","⚠ Action manquante",IF(AND(AU19=1,D19=""),"⚠ Canal manquant",IF(AND(W19<>"",COUNTIFS('Saisie'!$W$5:$W$2004,W19,'Saisie'!$C$5:$C$2004,"<>"&C19)>0),"⚠ Numéro déjà utilisé par un autre prospect",IF(AND(J19<>"",J19<A19),"⚠ Relance avant la date de l'action",IF(A19>TODAY(),"⚠ Date dans le futur","✓")))))))) | AS19: =IF(AND(A19="",C19="",E19=""),"",ROW()) | AT19: =IF(E19&F19="","",MAX(IFERROR(INDEX('Paramètres'!$J$6:$J$33,MATCH(E19,'Paramètres'!$I$6:$I$33,0)),0),IFERROR(INDEX('Paramètres'!$N$6:$N$17,MATCH(F19,'Paramètres'!$M$6:$M$17,0)),0))) | AU19: =IF(E19="","",IFERROR(IF(INDEX('Paramètres'!$K$6:$K$33,MATCH(E19,'Paramètres'!$I$6:$I$33,0))="Oui",1,0),0)) | AV19: =IF(F19="","",IFERROR(IF(INDEX('Paramètres'!$O$6:$O$17,MATCH(F19,'Paramètres'!$M$6:$M$17,0))="Oui",1,0),0)) | AW19: =IF(E19="","",IF(G19<>"",G19,IF(OR(E19="Proposition envoyée",E19="Signature"),MAX(0,N(IFERROR(INDEX('Paramètres'!$R$6:$R$15,MATCH(IF(AL19<>"",AL19,IFERROR(INDEX('Prospects'!$AN$5:$AN$504,MATCH(C19,'Prospects'!$C$5:$C$504,0)),"")),'Paramètres'!$Q$6:$Q$15,0)),0))-N(P19)),0))) | AX19: =IF(C19="","",IF(COUNTIF($C$5:C19,C19)=1,MAX($AX$4:AX18)+1,"")) | AY19: =IF(B19="","",HOUR(B19)) | AZ19: =IF(A19="","",MOD(A19-2,7)+1) | BA19: =IF(C19="","",IFERROR(INDEX('Prospects'!$N$5:$N$504,MATCH(C19,'Prospects'!$C$5:$C$504,0)),"")) | BB19: =IF(AND(C19<>"",C19='Fiche prospect'!$C$4),COUNTIF($C$5:C19,C19),"")
A20: 46290 | C20: Salon Coiff'Style (EXEMPLE) | D20: Appel | E20: Ajout prospect | R20: Coiffure | S20: Lyon | T20: Centre-ville | U20: Julie Petit | W20: 06 77 88 99 00 | Y20: @coiffstyle | AA20: Recommandation | AB20: Institut Belle Peau (EXEMPLE) | AC20: Oui | AD20: 46289 | AE20: Régulière | AF20: Absente | AI20: Petite | AR20: =IF(AND(C20="",E20=""),"",IF(A20="","⚠ Date manquante",IF(AND(C20="",E20<>"Dépense"),"⚠ Prospect manquant",IF(E20="","⚠ Action manquante",IF(AND(AU20=1,D20=""),"⚠ Canal manquant",IF(AND(W20<>"",COUNTIFS('Saisie'!$W$5:$W$2004,W20,'Saisie'!$C$5:$C$2004,"<>"&C20)>0),"⚠ Numéro déjà utilisé par un autre prospect",IF(AND(J20<>"",J20<A20),"⚠ Relance avant la date de l'action",IF(A20>TODAY(),"⚠ Date dans le futur","✓")))))))) | AS20: =IF(AND(A20="",C20="",E20=""),"",ROW()) | AT20: =IF(E20&F20="","",MAX(IFERROR(INDEX('Paramètres'!$J$6:$J$33,MATCH(E20,'Paramètres'!$I$6:$I$33,0)),0),IFERROR(INDEX('Paramètres'!$N$6:$N$17,MATCH(F20,'Paramètres'!$M$6:$M$17,0)),0))) | AU20: =IF(E20="","",IFERROR(IF(INDEX('Paramètres'!$K$6:$K$33,MATCH(E20,'Paramètres'!$I$6:$I$33,0))="Oui",1,0),0)) | AV20: =IF(F20="","",IFERROR(IF(INDEX('Paramètres'!$O$6:$O$17,MATCH(F20,'Paramètres'!$M$6:$M$17,0))="Oui",1,0),0)) | AW20: =IF(E20="","",IF(G20<>"",G20,IF(OR(E20="Proposition envoyée",E20="Signature"),MAX(0,N(IFERROR(INDEX('Paramètres'!$R$6:$R$15,MATCH(IF(AL20<>"",AL20,IFERROR(INDEX('Prospects'!$AN$5:$AN$504,MATCH(C20,'Prospects'!$C$5:$C$504,0)),"")),'Paramètres'!$Q$6:$Q$15,0)),0))-N(P20)),0))) | AX20: =IF(C20="","",IF(COUNTIF($C$5:C20,C20)=1,MAX($AX$4:AX19)+1,"")) | AY20: =IF(B20="","",HOUR(B20)) | AZ20: =IF(A20="","",MOD(A20-2,7)+1) | BA20: =IF(C20="","",IFERROR(INDEX('Prospects'!$N$5:$N$504,MATCH(C20,'Prospects'!$C$5:$C$504,0)),"")) | BB20: =IF(AND(C20<>"",C20='Fiche prospect'!$C$4),COUNTIF($C$5:C20,C20),"")
A21: 46291 | C21: Institut Belle Peau (EXEMPLE) | E21: Onboarding - Contrat | AR21: =IF(AND(C21="",E21=""),"",IF(A21="","⚠ Date manquante",IF(AND(C21="",E21<>"Dépense"),"⚠ Prospect manquant",IF(E21="","⚠ Action manquante",IF(AND(AU21=1,D21=""),"⚠ Canal manquant",IF(AND(W21<>"",COUNTIFS('Saisie'!$W$5:$W$2004,W21,'Saisie'!$C$5:$C$2004,"<>"&C21)>0),"⚠ Numéro déjà utilisé par un autre prospect",IF(AND(J21<>"",J21<A21),"⚠ Relance avant la date de l'action",IF(A21>TODAY(),"⚠ Date dans le futur","✓")))))))) | AS21: =IF(AND(A21="",C21="",E21=""),"",ROW()) | AT21: =IF(E21&F21="","",MAX(IFERROR(INDEX('Paramètres'!$J$6:$J$33,MATCH(E21,'Paramètres'!$I$6:$I$33,0)),0),IFERROR(INDEX('Paramètres'!$N$6:$N$17,MATCH(F21,'Paramètres'!$M$6:$M$17,0)),0))) | AU21: =IF(E21="","",IFERROR(IF(INDEX('Paramètres'!$K$6:$K$33,MATCH(E21,'Paramètres'!$I$6:$I$33,0))="Oui",1,0),0)) | AV21: =IF(F21="","",IFERROR(IF(INDEX('Paramètres'!$O$6:$O$17,MATCH(F21,'Paramètres'!$M$6:$M$17,0))="Oui",1,0),0)) | AW21: =IF(E21="","",IF(G21<>"",G21,IF(OR(E21="Proposition envoyée",E21="Signature"),MAX(0,N(IFERROR(INDEX('Paramètres'!$R$6:$R$15,MATCH(IF(AL21<>"",AL21,IFERROR(INDEX('Prospects'!$AN$5:$AN$504,MATCH(C21,'Prospects'!$C$5:$C$504,0)),"")),'Paramètres'!$Q$6:$Q$15,0)),0))-N(P21)),0))) | AX21: =IF(C21="","",IF(COUNTIF($C$5:C21,C21)=1,MAX($AX$4:AX20)+1,"")) | AY21: =IF(B21="","",HOUR(B21)) | AZ21: =IF(A21="","",MOD(A21-2,7)+1) | BA21: =IF(C21="","",IFERROR(INDEX('Prospects'!$N$5:$N$504,MATCH(C21,'Prospects'!$C$5:$C$504,0)),"")) | BB21: =IF(AND(C21<>"",C21='Fiche prospect'!$C$4),COUNTIF($C$5:C21,C21),"")
AR22: =IF(AND(C22="",E22=""),"",IF(A22="","⚠ Date manquante",IF(AND(C22="",E22<>"Dépense"),"⚠ Prospect manquant",IF(E22="","⚠ Action manquante",IF(AND(AU22=1,D22=""),"⚠ Canal manquant",IF(AND(W22<>"",COUNTIFS('Saisie'!$W$5:$W$2004,W22,'Saisie'!$C$5:$C$2004,"<>"&C22)>0),"⚠ Numéro déjà utilisé par un autre prospect",IF(AND(J22<>"",J22<A22),"⚠ Relance avant la date de l'action",IF(A22>TODAY(),"⚠ Date dans le futur","✓")))))))) | AS22: =IF(AND(A22="",C22="",E22=""),"",ROW()) | AT22: =IF(E22&F22="","",MAX(IFERROR(INDEX('Paramètres'!$J$6:$J$33,MATCH(E22,'Paramètres'!$I$6:$I$33,0)),0),IFERROR(INDEX('Paramètres'!$N$6:$N$17,MATCH(F22,'Paramètres'!$M$6:$M$17,0)),0))) | AU22: =IF(E22="","",IFERROR(IF(INDEX('Paramètres'!$K$6:$K$33,MATCH(E22,'Paramètres'!$I$6:$I$33,0))="Oui",1,0),0)) | AV22: =IF(F22="","",IFERROR(IF(INDEX('Paramètres'!$O$6:$O$17,MATCH(F22,'Paramètres'!$M$6:$M$17,0))="Oui",1,0),0)) | AW22: =IF(E22="","",IF(G22<>"",G22,IF(OR(E22="Proposition envoyée",E22="Signature"),MAX(0,N(IFERROR(INDEX('Paramètres'!$R$6:$R$15,MATCH(IF(AL22<>"",AL22,IFERROR(INDEX('Prospects'!$AN$5:$AN$504,MATCH(C22,'Prospects'!$C$5:$C$504,0)),"")),'Paramètres'!$Q$6:$Q$15,0)),0))-N(P22)),0))) | AX22: =IF(C22="","",IF(COUNTIF($C$5:C22,C22)=1,MAX($AX$4:AX21)+1,"")) | AY22: =IF(B22="","",HOUR(B22)) | AZ22: =IF(A22="","",MOD(A22-2,7)+1) | BA22: =IF(C22="","",IFERROR(INDEX('Prospects'!$N$5:$N$504,MATCH(C22,'Prospects'!$C$5:$C$504,0)),"")) | BB22: =IF(AND(C22<>"",C22='Fiche prospect'!$C$4),COUNTIF($C$5:C22,C22),"")
AR23: =IF(AND(C23="",E23=""),"",IF(A23="","⚠ Date manquante",IF(AND(C23="",E23<>"Dépense"),"⚠ Prospect manquant",IF(E23="","⚠ Action manquante",IF(AND(AU23=1,D23=""),"⚠ Canal manquant",IF(AND(W23<>"",COUNTIFS('Saisie'!$W$5:$W$2004,W23,'Saisie'!$C$5:$C$2004,"<>"&C23)>0),"⚠ Numéro déjà utilisé par un autre prospect",IF(AND(J23<>"",J23<A23),"⚠ Relance avant la date de l'action",IF(A23>TODAY(),"⚠ Date dans le futur","✓")))))))) | AS23: =IF(AND(A23="",C23="",E23=""),"",ROW()) | AT23: =IF(E23&F23="","",MAX(IFERROR(INDEX('Paramètres'!$J$6:$J$33,MATCH(E23,'Paramètres'!$I$6:$I$33,0)),0),IFERROR(INDEX('Paramètres'!$N$6:$N$17,MATCH(F23,'Paramètres'!$M$6:$M$17,0)),0))) | AU23: =IF(E23="","",IFERROR(IF(INDEX('Paramètres'!$K$6:$K$33,MATCH(E23,'Paramètres'!$I$6:$I$33,0))="Oui",1,0),0)) | AV23: =IF(F23="","",IFERROR(IF(INDEX('Paramètres'!$O$6:$O$17,MATCH(F23,'Paramètres'!$M$6:$M$17,0))="Oui",1,0),0)) | AW23: =IF(E23="","",IF(G23<>"",G23,IF(OR(E23="Proposition envoyée",E23="Signature"),MAX(0,N(IFERROR(INDEX('Paramètres'!$R$6:$R$15,MATCH(IF(AL23<>"",AL23,IFERROR(INDEX('Prospects'!$AN$5:$AN$504,MATCH(C23,'Prospects'!$C$5:$C$504,0)),"")),'Paramètres'!$Q$6:$Q$15,0)),0))-N(P23)),0))) | AX23: =IF(C23="","",IF(COUNTIF($C$5:C23,C23)=1,MAX($AX$4:AX22)+1,"")) | AY23: =IF(B23="","",HOUR(B23)) | AZ23: =IF(A23="","",MOD(A23-2,7)+1) | BA23: =IF(C23="","",IFERROR(INDEX('Prospects'!$N$5:$N$504,MATCH(C23,'Prospects'!$C$5:$C$504,0)),"")) | BB23: =IF(AND(C23<>"",C23='Fiche prospect'!$C$4),COUNTIF($C$5:C23,C23),"")
AR24: =IF(AND(C24="",E24=""),"",IF(A24="","⚠ Date manquante",IF(AND(C24="",E24<>"Dépense"),"⚠ Prospect manquant",IF(E24="","⚠ Action manquante",IF(AND(AU24=1,D24=""),"⚠ Canal manquant",IF(AND(W24<>"",COUNTIFS('Saisie'!$W$5:$W$2004,W24,'Saisie'!$C$5:$C$2004,"<>"&C24)>0),"⚠ Numéro déjà utilisé par un autre prospect",IF(AND(J24<>"",J24<A24),"⚠ Relance avant la date de l'action",IF(A24>TODAY(),"⚠ Date dans le futur","✓")))))))) | AS24: =IF(AND(A24="",C24="",E24=""),"",ROW()) | AT24: =IF(E24&F24="","",MAX(IFERROR(INDEX('Paramètres'!$J$6:$J$33,MATCH(E24,'Paramètres'!$I$6:$I$33,0)),0),IFERROR(INDEX('Paramètres'!$N$6:$N$17,MATCH(F24,'Paramètres'!$M$6:$M$17,0)),0))) | AU24: =IF(E24="","",IFERROR(IF(INDEX('Paramètres'!$K$6:$K$33,MATCH(E24,'Paramètres'!$I$6:$I$33,0))="Oui",1,0),0)) | AV24: =IF(F24="","",IFERROR(IF(INDEX('Paramètres'!$O$6:$O$17,MATCH(F24,'Paramètres'!$M$6:$M$17,0))="Oui",1,0),0)) | AW24: =IF(E24="","",IF(G24<>"",G24,IF(OR(E24="Proposition envoyée",E24="Signature"),MAX(0,N(IFERROR(INDEX('Paramètres'!$R$6:$R$15,MATCH(IF(AL24<>"",AL24,IFERROR(INDEX('Prospects'!$AN$5:$AN$504,MATCH(C24,'Prospects'!$C$5:$C$504,0)),"")),'Paramètres'!$Q$6:$Q$15,0)),0))-N(P24)),0))) | AX24: =IF(C24="","",IF(COUNTIF($C$5:C24,C24)=1,MAX($AX$4:AX23)+1,"")) | AY24: =IF(B24="","",HOUR(B24)) | AZ24: =IF(A24="","",MOD(A24-2,7)+1) | BA24: =IF(C24="","",IFERROR(INDEX('Prospects'!$N$5:$N$504,MATCH(C24,'Prospects'!$C$5:$C$504,0)),"")) | BB24: =IF(AND(C24<>"",C24='Fiche prospect'!$C$4),COUNTIF($C$5:C24,C24),"")
AR25: =IF(AND(C25="",E25=""),"",IF(A25="","⚠ Date manquante",IF(AND(C25="",E25<>"Dépense"),"⚠ Prospect manquant",IF(E25="","⚠ Action manquante",IF(AND(AU25=1,D25=""),"⚠ Canal manquant",IF(AND(W25<>"",COUNTIFS('Saisie'!$W$5:$W$2004,W25,'Saisie'!$C$5:$C$2004,"<>"&C25)>0),"⚠ Numéro déjà utilisé par un autre prospect",IF(AND(J25<>"",J25<A25),"⚠ Relance avant la date de l'action",IF(A25>TODAY(),"⚠ Date dans le futur","✓")))))))) | AS25: =IF(AND(A25="",C25="",E25=""),"",ROW()) | AT25: =IF(E25&F25="","",MAX(IFERROR(INDEX('Paramètres'!$J$6:$J$33,MATCH(E25,'Paramètres'!$I$6:$I$33,0)),0),IFERROR(INDEX('Paramètres'!$N$6:$N$17,MATCH(F25,'Paramètres'!$M$6:$M$17,0)),0))) | AU25: =IF(E25="","",IFERROR(IF(INDEX('Paramètres'!$K$6:$K$33,MATCH(E25,'Paramètres'!$I$6:$I$33,0))="Oui",1,0),0)) | AV25: =IF(F25="","",IFERROR(IF(INDEX('Paramètres'!$O$6:$O$17,MATCH(F25,'Paramètres'!$M$6:$M$17,0))="Oui",1,0),0)) | AW25: =IF(E25="","",IF(G25<>"",G25,IF(OR(E25="Proposition envoyée",E25="Signature"),MAX(0,N(IFERROR(INDEX('Paramètres'!$R$6:$R$15,MATCH(IF(AL25<>"",AL25,IFERROR(INDEX('Prospects'!$AN$5:$AN$504,MATCH(C25,'Prospects'!$C$5:$C$504,0)),"")),'Paramètres'!$Q$6:$Q$15,0)),0))-N(P25)),0))) | AX25: =IF(C25="","",IF(COUNTIF($C$5:C25,C25)=1,MAX($AX$4:AX24)+1,"")) | AY25: =IF(B25="","",HOUR(B25)) | AZ25: =IF(A25="","",MOD(A25-2,7)+1) | BA25: =IF(C25="","",IFERROR(INDEX('Prospects'!$N$5:$N$504,MATCH(C25,'Prospects'!$C$5:$C$504,0)),"")) | BB25: =IF(AND(C25<>"",C25='Fiche prospect'!$C$4),COUNTIF($C$5:C25,C25),"")
AR26: =IF(AND(C26="",E26=""),"",IF(A26="","⚠ Date manquante",IF(AND(C26="",E26<>"Dépense"),"⚠ Prospect manquant",IF(E26="","⚠ Action manquante",IF(AND(AU26=1,D26=""),"⚠ Canal manquant",IF(AND(W26<>"",COUNTIFS('Saisie'!$W$5:$W$2004,W26,'Saisie'!$C$5:$C$2004,"<>"&C26)>0),"⚠ Numéro déjà utilisé par un autre prospect",IF(AND(J26<>"",J26<A26),"⚠ Relance avant la date de l'action",IF(A26>TODAY(),"⚠ Date dans le futur","✓")))))))) | AS26: =IF(AND(A26="",C26="",E26=""),"",ROW()) | AT26: =IF(E26&F26="","",MAX(IFERROR(INDEX('Paramètres'!$J$6:$J$33,MATCH(E26,'Paramètres'!$I$6:$I$33,0)),0),IFERROR(INDEX('Paramètres'!$N$6:$N$17,MATCH(F26,'Paramètres'!$M$6:$M$17,0)),0))) | AU26: =IF(E26="","",IFERROR(IF(INDEX('Paramètres'!$K$6:$K$33,MATCH(E26,'Paramètres'!$I$6:$I$33,0))="Oui",1,0),0)) | AV26: =IF(F26="","",IFERROR(IF(INDEX('Paramètres'!$O$6:$O$17,MATCH(F26,'Paramètres'!$M$6:$M$17,0))="Oui",1,0),0)) | AW26: =IF(E26="","",IF(G26<>"",G26,IF(OR(E26="Proposition envoyée",E26="Signature"),MAX(0,N(IFERROR(INDEX('Paramètres'!$R$6:$R$15,MATCH(IF(AL26<>"",AL26,IFERROR(INDEX('Prospects'!$AN$5:$AN$504,MATCH(C26,'Prospects'!$C$5:$C$504,0)),"")),'Paramètres'!$Q$6:$Q$15,0)),0))-N(P26)),0))) | AX26: =IF(C26="","",IF(COUNTIF($C$5:C26,C26)=1,MAX($AX$4:AX25)+1,"")) | AY26: =IF(B26="","",HOUR(B26)) | AZ26: =IF(A26="","",MOD(A26-2,7)+1) | BA26: =IF(C26="","",IFERROR(INDEX('Prospects'!$N$5:$N$504,MATCH(C26,'Prospects'!$C$5:$C$504,0)),"")) | BB26: =IF(AND(C26<>"",C26='Fiche prospect'!$C$4),COUNTIF($C$5:C26,C26),"")
AR27: =IF(AND(C27="",E27=""),"",IF(A27="","⚠ Date manquante",IF(AND(C27="",E27<>"Dépense"),"⚠ Prospect manquant",IF(E27="","⚠ Action manquante",IF(AND(AU27=1,D27=""),"⚠ Canal manquant",IF(AND(W27<>"",COUNTIFS('Saisie'!$W$5:$W$2004,W27,'Saisie'!$C$5:$C$2004,"<>"&C27)>0),"⚠ Numéro déjà utilisé par un autre prospect",IF(AND(J27<>"",J27<A27),"⚠ Relance avant la date de l'action",IF(A27>TODAY(),"⚠ Date dans le futur","✓")))))))) | AS27: =IF(AND(A27="",C27="",E27=""),"",ROW()) | AT27: =IF(E27&F27="","",MAX(IFERROR(INDEX('Paramètres'!$J$6:$J$33,MATCH(E27,'Paramètres'!$I$6:$I$33,0)),0),IFERROR(INDEX('Paramètres'!$N$6:$N$17,MATCH(F27,'Paramètres'!$M$6:$M$17,0)),0))) | AU27: =IF(E27="","",IFERROR(IF(INDEX('Paramètres'!$K$6:$K$33,MATCH(E27,'Paramètres'!$I$6:$I$33,0))="Oui",1,0),0)) | AV27: =IF(F27="","",IFERROR(IF(INDEX('Paramètres'!$O$6:$O$17,MATCH(F27,'Paramètres'!$M$6:$M$17,0))="Oui",1,0),0)) | AW27: =IF(E27="","",IF(G27<>"",G27,IF(OR(E27="Proposition envoyée",E27="Signature"),MAX(0,N(IFERROR(INDEX('Paramètres'!$R$6:$R$15,MATCH(IF(AL27<>"",AL27,IFERROR(INDEX('Prospects'!$AN$5:$AN$504,MATCH(C27,'Prospects'!$C$5:$C$504,0)),"")),'Paramètres'!$Q$6:$Q$15,0)),0))-N(P27)),0))) | AX27: =IF(C27="","",IF(COUNTIF($C$5:C27,C27)=1,MAX($AX$4:AX26)+1,"")) | AY27: =IF(B27="","",HOUR(B27)) | AZ27: =IF(A27="","",MOD(A27-2,7)+1) | BA27: =IF(C27="","",IFERROR(INDEX('Prospects'!$N$5:$N$504,MATCH(C27,'Prospects'!$C$5:$C$504,0)),"")) | BB27: =IF(AND(C27<>"",C27='Fiche prospect'!$C$4),COUNTIF($C$5:C27,C27),"")
AR28: =IF(AND(C28="",E28=""),"",IF(A28="","⚠ Date manquante",IF(AND(C28="",E28<>"Dépense"),"⚠ Prospect manquant",IF(E28="","⚠ Action manquante",IF(AND(AU28=1,D28=""),"⚠ Canal manquant",IF(AND(W28<>"",COUNTIFS('Saisie'!$W$5:$W$2004,W28,'Saisie'!$C$5:$C$2004,"<>"&C28)>0),"⚠ Numéro déjà utilisé par un autre prospect",IF(AND(J28<>"",J28<A28),"⚠ Relance avant la date de l'action",IF(A28>TODAY(),"⚠ Date dans le futur","✓")))))))) | AS28: =IF(AND(A28="",C28="",E28=""),"",ROW()) | AT28: =IF(E28&F28="","",MAX(IFERROR(INDEX('Paramètres'!$J$6:$J$33,MATCH(E28,'Paramètres'!$I$6:$I$33,0)),0),IFERROR(INDEX('Paramètres'!$N$6:$N$17,MATCH(F28,'Paramètres'!$M$6:$M$17,0)),0))) | AU28: =IF(E28="","",IFERROR(IF(INDEX('Paramètres'!$K$6:$K$33,MATCH(E28,'Paramètres'!$I$6:$I$33,0))="Oui",1,0),0)) | AV28: =IF(F28="","",IFERROR(IF(INDEX('Paramètres'!$O$6:$O$17,MATCH(F28,'Paramètres'!$M$6:$M$17,0))="Oui",1,0),0)) | AW28: =IF(E28="","",IF(G28<>"",G28,IF(OR(E28="Proposition envoyée",E28="Signature"),MAX(0,N(IFERROR(INDEX('Paramètres'!$R$6:$R$15,MATCH(IF(AL28<>"",AL28,IFERROR(INDEX('Prospects'!$AN$5:$AN$504,MATCH(C28,'Prospects'!$C$5:$C$504,0)),"")),'Paramètres'!$Q$6:$Q$15,0)),0))-N(P28)),0))) | AX28: =IF(C28="","",IF(COUNTIF($C$5:C28,C28)=1,MAX($AX$4:AX27)+1,"")) | AY28: =IF(B28="","",HOUR(B28)) | AZ28: =IF(A28="","",MOD(A28-2,7)+1) | BA28: =IF(C28="","",IFERROR(INDEX('Prospects'!$N$5:$N$504,MATCH(C28,'Prospects'!$C$5:$C$504,0)),"")) | BB28: =IF(AND(C28<>"",C28='Fiche prospect'!$C$4),COUNTIF($C$5:C28,C28),"")
AR29: =IF(AND(C29="",E29=""),"",IF(A29="","⚠ Date manquante",IF(AND(C29="",E29<>"Dépense"),"⚠ Prospect manquant",IF(E29="","⚠ Action manquante",IF(AND(AU29=1,D29=""),"⚠ Canal manquant",IF(AND(W29<>"",COUNTIFS('Saisie'!$W$5:$W$2004,W29,'Saisie'!$C$5:$C$2004,"<>"&C29)>0),"⚠ Numéro déjà utilisé par un autre prospect",IF(AND(J29<>"",J29<A29),"⚠ Relance avant la date de l'action",IF(A29>TODAY(),"⚠ Date dans le futur","✓")))))))) | AS29: =IF(AND(A29="",C29="",E29=""),"",ROW()) | AT29: =IF(E29&F29="","",MAX(IFERROR(INDEX('Paramètres'!$J$6:$J$33,MATCH(E29,'Paramètres'!$I$6:$I$33,0)),0),IFERROR(INDEX('Paramètres'!$N$6:$N$17,MATCH(F29,'Paramètres'!$M$6:$M$17,0)),0))) | AU29: =IF(E29="","",IFERROR(IF(INDEX('Paramètres'!$K$6:$K$33,MATCH(E29,'Paramètres'!$I$6:$I$33,0))="Oui",1,0),0)) | AV29: =IF(F29="","",IFERROR(IF(INDEX('Paramètres'!$O$6:$O$17,MATCH(F29,'Paramètres'!$M$6:$M$17,0))="Oui",1,0),0)) | AW29: =IF(E29="","",IF(G29<>"",G29,IF(OR(E29="Proposition envoyée",E29="Signature"),MAX(0,N(IFERROR(INDEX('Paramètres'!$R$6:$R$15,MATCH(IF(AL29<>"",AL29,IFERROR(INDEX('Prospects'!$AN$5:$AN$504,MATCH(C29,'Prospects'!$C$5:$C$504,0)),"")),'Paramètres'!$Q$6:$Q$15,0)),0))-N(P29)),0))) | AX29: =IF(C29="","",IF(COUNTIF($C$5:C29,C29)=1,MAX($AX$4:AX28)+1,"")) | AY29: =IF(B29="","",HOUR(B29)) | AZ29: =IF(A29="","",MOD(A29-2,7)+1) | BA29: =IF(C29="","",IFERROR(INDEX('Prospects'!$N$5:$N$504,MATCH(C29,'Prospects'!$C$5:$C$504,0)),"")) | BB29: =IF(AND(C29<>"",C29='Fiche prospect'!$C$4),COUNTIF($C$5:C29,C29),"")
AR30: =IF(AND(C30="",E30=""),"",IF(A30="","⚠ Date manquante",IF(AND(C30="",E30<>"Dépense"),"⚠ Prospect manquant",IF(E30="","⚠ Action manquante",IF(AND(AU30=1,D30=""),"⚠ Canal manquant",IF(AND(W30<>"",COUNTIFS('Saisie'!$W$5:$W$2004,W30,'Saisie'!$C$5:$C$2004,"<>"&C30)>0),"⚠ Numéro déjà utilisé par un autre prospect",IF(AND(J30<>"",J30<A30),"⚠ Relance avant la date de l'action",IF(A30>TODAY(),"⚠ Date dans le futur","✓")))))))) | AS30: =IF(AND(A30="",C30="",E30=""),"",ROW()) | AT30: =IF(E30&F30="","",MAX(IFERROR(INDEX('Paramètres'!$J$6:$J$33,MATCH(E30,'Paramètres'!$I$6:$I$33,0)),0),IFERROR(INDEX('Paramètres'!$N$6:$N$17,MATCH(F30,'Paramètres'!$M$6:$M$17,0)),0))) | AU30: =IF(E30="","",IFERROR(IF(INDEX('Paramètres'!$K$6:$K$33,MATCH(E30,'Paramètres'!$I$6:$I$33,0))="Oui",1,0),0)) | AV30: =IF(F30="","",IFERROR(IF(INDEX('Paramètres'!$O$6:$O$17,MATCH(F30,'Paramètres'!$M$6:$M$17,0))="Oui",1,0),0)) | AW30: =IF(E30="","",IF(G30<>"",G30,IF(OR(E30="Proposition envoyée",E30="Signature"),MAX(0,N(IFERROR(INDEX('Paramètres'!$R$6:$R$15,MATCH(IF(AL30<>"",AL30,IFERROR(INDEX('Prospects'!$AN$5:$AN$504,MATCH(C30,'Prospects'!$C$5:$C$504,0)),"")),'Paramètres'!$Q$6:$Q$15,0)),0))-N(P30)),0))) | AX30: =IF(C30="","",IF(COUNTIF($C$5:C30,C30)=1,MAX($AX$4:AX29)+1,"")) | AY30: =IF(B30="","",HOUR(B30)) | AZ30: =IF(A30="","",MOD(A30-2,7)+1) | BA30: =IF(C30="","",IFERROR(INDEX('Prospects'!$N$5:$N$504,MATCH(C30,'Prospects'!$C$5:$C$504,0)),"")) | BB30: =IF(AND(C30<>"",C30='Fiche prospect'!$C$4),COUNTIF($C$5:C30,C30),"")
AR31: =IF(AND(C31="",E31=""),"",IF(A31="","⚠ Date manquante",IF(AND(C31="",E31<>"Dépense"),"⚠ Prospect manquant",IF(E31="","⚠ Action manquante",IF(AND(AU31=1,D31=""),"⚠ Canal manquant",IF(AND(W31<>"",COUNTIFS('Saisie'!$W$5:$W$2004,W31,'Saisie'!$C$5:$C$2004,"<>"&C31)>0),"⚠ Numéro déjà utilisé par un autre prospect",IF(AND(J31<>"",J31<A31),"⚠ Relance avant la date de l'action",IF(A31>TODAY(),"⚠ Date dans le futur","✓")))))))) | AS31: =IF(AND(A31="",C31="",E31=""),"",ROW()) | AT31: =IF(E31&F31="","",MAX(IFERROR(INDEX('Paramètres'!$J$6:$J$33,MATCH(E31,'Paramètres'!$I$6:$I$33,0)),0),IFERROR(INDEX('Paramètres'!$N$6:$N$17,MATCH(F31,'Paramètres'!$M$6:$M$17,0)),0))) | AU31: =IF(E31="","",IFERROR(IF(INDEX('Paramètres'!$K$6:$K$33,MATCH(E31,'Paramètres'!$I$6:$I$33,0))="Oui",1,0),0)) | AV31: =IF(F31="","",IFERROR(IF(INDEX('Paramètres'!$O$6:$O$17,MATCH(F31,'Paramètres'!$M$6:$M$17,0))="Oui",1,0),0)) | AW31: =IF(E31="","",IF(G31<>"",G31,IF(OR(E31="Proposition envoyée",E31="Signature"),MAX(0,N(IFERROR(INDEX('Paramètres'!$R$6:$R$15,MATCH(IF(AL31<>"",AL31,IFERROR(INDEX('Prospects'!$AN$5:$AN$504,MATCH(C31,'Prospects'!$C$5:$C$504,0)),"")),'Paramètres'!$Q$6:$Q$15,0)),0))-N(P31)),0))) | AX31: =IF(C31="","",IF(COUNTIF($C$5:C31,C31)=1,MAX($AX$4:AX30)+1,"")) | AY31: =IF(B31="","",HOUR(B31)) | AZ31: =IF(A31="","",MOD(A31-2,7)+1) | BA31: =IF(C31="","",IFERROR(INDEX('Prospects'!$N$5:$N$504,MATCH(C31,'Prospects'!$C$5:$C$504,0)),"")) | BB31: =IF(AND(C31<>"",C31='Fiche prospect'!$C$4),COUNTIF($C$5:C31,C31),"")
AR32: =IF(AND(C32="",E32=""),"",IF(A32="","⚠ Date manquante",IF(AND(C32="",E32<>"Dépense"),"⚠ Prospect manquant",IF(E32="","⚠ Action manquante",IF(AND(AU32=1,D32=""),"⚠ Canal manquant",IF(AND(W32<>"",COUNTIFS('Saisie'!$W$5:$W$2004,W32,'Saisie'!$C$5:$C$2004,"<>"&C32)>0),"⚠ Numéro déjà utilisé par un autre prospect",IF(AND(J32<>"",J32<A32),"⚠ Relance avant la date de l'action",IF(A32>TODAY(),"⚠ Date dans le futur","✓")))))))) | AS32: =IF(AND(A32="",C32="",E32=""),"",ROW()) | AT32: =IF(E32&F32="","",MAX(IFERROR(INDEX('Paramètres'!$J$6:$J$33,MATCH(E32,'Paramètres'!$I$6:$I$33,0)),0),IFERROR(INDEX('Paramètres'!$N$6:$N$17,MATCH(F32,'Paramètres'!$M$6:$M$17,0)),0))) | AU32: =IF(E32="","",IFERROR(IF(INDEX('Paramètres'!$K$6:$K$33,MATCH(E32,'Paramètres'!$I$6:$I$33,0))="Oui",1,0),0)) | AV32: =IF(F32="","",IFERROR(IF(INDEX('Paramètres'!$O$6:$O$17,MATCH(F32,'Paramètres'!$M$6:$M$17,0))="Oui",1,0),0)) | AW32: =IF(E32="","",IF(G32<>"",G32,IF(OR(E32="Proposition envoyée",E32="Signature"),MAX(0,N(IFERROR(INDEX('Paramètres'!$R$6:$R$15,MATCH(IF(AL32<>"",AL32,IFERROR(INDEX('Prospects'!$AN$5:$AN$504,MATCH(C32,'Prospects'!$C$5:$C$504,0)),"")),'Paramètres'!$Q$6:$Q$15,0)),0))-N(P32)),0))) | AX32: =IF(C32="","",IF(COUNTIF($C$5:C32,C32)=1,MAX($AX$4:AX31)+1,"")) | AY32: =IF(B32="","",HOUR(B32)) | AZ32: =IF(A32="","",MOD(A32-2,7)+1) | BA32: =IF(C32="","",IFERROR(INDEX('Prospects'!$N$5:$N$504,MATCH(C32,'Prospects'!$C$5:$C$504,0)),"")) | BB32: =IF(AND(C32<>"",C32='Fiche prospect'!$C$4),COUNTIF($C$5:C32,C32),"")
AR33: =IF(AND(C33="",E33=""),"",IF(A33="","⚠ Date manquante",IF(AND(C33="",E33<>"Dépense"),"⚠ Prospect manquant",IF(E33="","⚠ Action manquante",IF(AND(AU33=1,D33=""),"⚠ Canal manquant",IF(AND(W33<>"",COUNTIFS('Saisie'!$W$5:$W$2004,W33,'Saisie'!$C$5:$C$2004,"<>"&C33)>0),"⚠ Numéro déjà utilisé par un autre prospect",IF(AND(J33<>"",J33<A33),"⚠ Relance avant la date de l'action",IF(A33>TODAY(),"⚠ Date dans le futur","✓")))))))) | AS33: =IF(AND(A33="",C33="",E33=""),"",ROW()) | AT33: =IF(E33&F33="","",MAX(IFERROR(INDEX('Paramètres'!$J$6:$J$33,MATCH(E33,'Paramètres'!$I$6:$I$33,0)),0),IFERROR(INDEX('Paramètres'!$N$6:$N$17,MATCH(F33,'Paramètres'!$M$6:$M$17,0)),0))) | AU33: =IF(E33="","",IFERROR(IF(INDEX('Paramètres'!$K$6:$K$33,MATCH(E33,'Paramètres'!$I$6:$I$33,0))="Oui",1,0),0)) | AV33: =IF(F33="","",IFERROR(IF(INDEX('Paramètres'!$O$6:$O$17,MATCH(F33,'Paramètres'!$M$6:$M$17,0))="Oui",1,0),0)) | AW33: =IF(E33="","",IF(G33<>"",G33,IF(OR(E33="Proposition envoyée",E33="Signature"),MAX(0,N(IFERROR(INDEX('Paramètres'!$R$6:$R$15,MATCH(IF(AL33<>"",AL33,IFERROR(INDEX('Prospects'!$AN$5:$AN$504,MATCH(C33,'Prospects'!$C$5:$C$504,0)),"")),'Paramètres'!$Q$6:$Q$15,0)),0))-N(P33)),0))) | AX33: =IF(C33="","",IF(COUNTIF($C$5:C33,C33)=1,MAX($AX$4:AX32)+1,"")) | AY33: =IF(B33="","",HOUR(B33)) | AZ33: =IF(A33="","",MOD(A33-2,7)+1) | BA33: =IF(C33="","",IFERROR(INDEX('Prospects'!$N$5:$N$504,MATCH(C33,'Prospects'!$C$5:$C$504,0)),"")) | BB33: =IF(AND(C33<>"",C33='Fiche prospect'!$C$4),COUNTIF($C$5:C33,C33),"")
... AR2004: =IF(AND(C2004="",E2004=""),"",IF(A2004="","⚠ Date manquante",IF(AND(C2004="",E2004<>"Dépense"),"⚠ Prospect manquant",IF(E2004="","⚠ Action manquante",IF(AND(AU2004=1,D2004=""),"⚠ Canal manquant",IF(AND(W2004<>"",COUNTIFS('Saisie'!$W$5:$W$2004,W2004,'Saisie'!$C$5:$C$2004,"<>"&C2004)>0),"⚠ Numéro déjà utilisé par un autre prospect",IF(AND(J2004<>"",J2004<A2004),"⚠ Relance avant la date de l'action",IF(A2004>TODAY(),"⚠ Date dans le futur","✓")))))))) | AS2004: =IF(AND(A2004="",C2004="",E2004=""),"",ROW()) | AT2004: =IF(E2004&F2004="","",MAX(IFERROR(INDEX('Paramètres'!$J$6:$J$33,MATCH(E2004,'Paramètres'!$I$6:$I$33,0)),0),IFERROR(INDEX('Paramètres'!$N$6:$N$17,MATCH(F2004,'Paramètres'!$M$6:$M$17,0)),0))) | AU2004: =IF(E2004="","",IFERROR(IF(INDEX('Paramètres'!$K$6:$K$33,MATCH(E2004,'Paramètres'!$I$6:$I$33,0))="Oui",1,0),0)) | AV2004: =IF(F2004="","",IFERROR(IF(INDEX('Paramètres'!$O$6:$O$17,MATCH(F2004,'Paramètres'!$M$6:$M$17,0))="Oui",1,0),0)) | AW2004: =IF(E2004="","",IF(G2004<>"",G2004,IF(OR(E2004="Proposition envoyée",E2004="Signature"),MAX(0,N(IFERROR(INDEX('Paramètres'!$R$6:$R$15,MATCH(IF(AL2004<>"",AL2004,IFERROR(INDEX('Prospects'!$AN$5:$AN$504,MATCH(C2004,'Prospects'!$C$5:$C$504,0)),"")),'Paramètres'!$Q$6:$Q$15,0)),0))-N(P2004)),0))) | AX2004: =IF(C2004="","",IF(COUNTIF($C$5:C2004,C2004)=1,MAX($AX$4:AX2003)+1,"")) | AY2004: =IF(B2004="","",HOUR(B2004)) | AZ2004: =IF(A2004="","",MOD(A2004-2,7)+1) | BA2004: =IF(C2004="","",IFERROR(INDEX('Prospects'!$N$5:$N$504,MATCH(C2004,'Prospects'!$C$5:$C$504,0)),"")) | BB2004: =IF(AND(C2004<>"",C2004='Fiche prospect'!$C$4),COUNTIF($C$5:C2004,C2004),"")

Sheet Tableau de bord
A1: 📊 TABLEAU DE BORD — AGENCE ELITE
A2: Rien à saisir : tout vient de l'onglet Saisie. Choisis le mois et le canal dans les cases jaunes, tout se recalcule. Les flèches comparent avec le mois précédent.
A3: =HYPERLINK("#'Saisie'!A1","↩ Saisie") | C3: =HYPERLINK("#'Ma journée'!A1","☀ Ma journée") | Q3: Calculs période → | R3: Début | S3: Fin | T3: Début M-1 | U3: Fin M-1
B4: Mois | C4: Mois en cours | F4: Canal | G4: Tous | I4: =IF($C$4="Tous","Tout l'historique",IF($C$4="Mois en cours","Mois en cours","Mois "&$C$4))&IF($G$4="Tous",", tous canaux",", canal "&$G$4) | R4: =IF($C$4="Tous",DATE(2000,1,1),IF($C$4="Mois en cours",DATE(YEAR(TODAY()),MONTH(TODAY()),1),DATE(VALUE(LEFT($C$4,4)),VALUE(RIGHT($C$4,2)),1))) | S4: =IF($C$4="Tous",DATE(2100,12,31),EOMONTH($R$4,0)) | T4: =IF($C$4="Tous",DATE(1999,1,1),EDATE($R$4,-1)) | U4: =IF($C$4="Tous",DATE(1999,1,31),EOMONTH($T$4,0))
B6: Prospects ajoutés | D6: Appels passés | F6: DM envoyés | H6: Réponses | J6: RDV obtenus | L6: Propositions
B7: =COUNTIFS('Prospects'!$B$5:$B$504,">="&$R$4,'Prospects'!$B$5:$B$504,"<="&$S$4,'Prospects'!$N$5:$N$504,IF('Tableau de bord'!$G$4="Tous","<>§",'Tableau de bord'!$G$4)) | D7: =COUNTIFS('Saisie'!$A$5:$A$2004,">="&$R$4,'Saisie'!$A$5:$A$2004,"<="&$S$4,'Saisie'!$D$5:$D$2004,"Appel",'Saisie'!$D$5:$D$2004,IF('Tableau de bord'!$G$4="Tous","<>§",'Tableau de bord'!$G$4),'Saisie'!$AU$5:$AU$2004,1) | F7: =COUNTIFS('Saisie'!$A$5:$A$2004,">="&$R$4,'Saisie'!$A$5:$A$2004,"<="&$S$4,'Saisie'!$D$5:$D$2004,"DM",'Saisie'!$D$5:$D$2004,IF('Tableau de bord'!$G$4="Tous","<>§",'Tableau de bord'!$G$4),'Saisie'!$AU$5:$AU$2004,1) | H7: =COUNTIFS('Saisie'!$A$5:$A$2004,">="&$R$4,'Saisie'!$A$5:$A$2004,"<="&$S$4,'Saisie'!$D$5:$D$2004,IF('Tableau de bord'!$G$4="Tous","<>§",'Tableau de bord'!$G$4),'Saisie'!$AV$5:$AV$2004,1) | J7: =COUNTIFS('Prospects'!$BG$5:$BG$504,">="&$R$4,'Prospects'!$BG$5:$BG$504,"<="&$S$4,'Prospects'!$N$5:$N$504,IF('Tableau de bord'!$G$4="Tous","<>§",'Tableau de bord'!$G$4)) | L7: =COUNTIFS('Saisie'!$A$5:$A$2004,">="&$R$4,'Saisie'!$A$5:$A$2004,"<="&$S$4,'Saisie'!$E$5:$E$2004,"Proposition envoyée",'Saisie'!$BA$5:$BA$2004,IF('Tableau de bord'!$G$4="Tous","<>§",'Tableau de bord'!$G$4))
B8: =IF(C8="","",IF(C8>0,"▲",IF(C8<0,"▼","="))) | C8: =IF($C$4="Tous","",COUNTIFS('Prospects'!$B$5:$B$504,">="&$R$4,'Prospects'!$B$5:$B$504,"<="&$S$4,'Prospects'!$N$5:$N$504,IF('Tableau de bord'!$G$4="Tous","<>§",'Tableau de bord'!$G$4))-COUNTIFS('Prospects'!$B$5:$B$504,">="&$T$4,'Prospects'!$B$5:$B$504,"<="&$U$4,'Prospects'!$N$5:$N$504,IF('Tableau de bord'!$G$4="Tous","<>§",'Tableau de bord'!$G$4))) | D8: =IF(E8="","",IF(E8>0,"▲",IF(E8<0,"▼","="))) | E8: =IF($C$4="Tous","",COUNTIFS('Saisie'!$A$5:$A$2004,">="&$R$4,'Saisie'!$A$5:$A$2004,"<="&$S$4,'Saisie'!$D$5:$D$2004,"Appel",'Saisie'!$D$5:$D$2004,IF('Tableau de bord'!$G$4="Tous","<>§",'Tableau de bord'!$G$4),'Saisie'!$AU$5:$AU$2004,1)-COUNTIFS('Saisie'!$A$5:$A$2004,">="&$T$4,'Saisie'!$A$5:$A$2004,"<="&$U$4,'Saisie'!$D$5:$D$2004,"Appel",'Saisie'!$D$5:$D$2004,IF('Tableau de bord'!$G$4="Tous","<>§",'Tableau de bord'!$G$4),'Saisie'!$AU$5:$AU$2004,1)) | F8: =IF(G8="","",IF(G8>0,"▲",IF(G8<0,"▼","="))) | G8: =IF($C$4="Tous","",COUNTIFS('Saisie'!$A$5:$A$2004,">="&$R$4,'Saisie'!$A$5:$A$2004,"<="&$S$4,'Saisie'!$D$5:$D$2004,"DM",'Saisie'!$D$5:$D$2004,IF('Tableau de bord'!$G$4="Tous","<>§",'Tableau de bord'!$G$4),'Saisie'!$AU$5:$AU$2004,1)-COUNTIFS('Saisie'!$A$5:$A$2004,">="&$T$4,'Saisie'!$A$5:$A$2004,"<="&$U$4,'Saisie'!$D$5:$D$2004,"DM",'Saisie'!$D$5:$D$2004,IF('Tableau de bord'!$G$4="Tous","<>§",'Tableau de bord'!$G$4),'Saisie'!$AU$5:$AU$2004,1)) | H8: =IF(I8="","",IF(I8>0,"▲",IF(I8<0,"▼","="))) | I8: =IF($C$4="Tous","",COUNTIFS('Saisie'!$A$5:$A$2004,">="&$R$4,'Saisie'!$A$5:$A$2004,"<="&$S$4,'Saisie'!$D$5:$D$2004,IF('Tableau de bord'!$G$4="Tous","<>§",'Tableau de bord'!$G$4),'Saisie'!$AV$5:$AV$2004,1)-COUNTIFS('Saisie'!$A$5:$A$2004,">="&$T$4,'Saisie'!$A$5:$A$2004,"<="&$U$4,'Saisie'!$D$5:$D$2004,IF('Tableau de bord'!$G$4="Tous","<>§",'Tableau de bord'!$G$4),'Saisie'!$AV$5:$AV$2004,1)) | J8: =IF(K8="","",IF(K8>0,"▲",IF(K8<0,"▼","="))) | K8: =IF($C$4="Tous","",COUNTIFS('Prospects'!$BG$5:$BG$504,">="&$R$4,'Prospects'!$BG$5:$BG$504,"<="&$S$4,'Prospects'!$N$5:$N$504,IF('Tableau de bord'!$G$4="Tous","<>§",'Tableau de bord'!$G$4))-COUNTIFS('Prospects'!$BG$5:$BG$504,">="&$T$4,'Prospects'!$BG$5:$BG$504,"<="&$U$4,'Prospects'!$N$5:$N$504,IF('Tableau de bord'!$G$4="Tous","<>§",'Tableau de bord'!$G$4))) | L8: =IF(M8="","",IF(M8>0,"▲",IF(M8<0,"▼","="))) | M8: =IF($C$4="Tous","",COUNTIFS('Saisie'!$A$5:$A$2004,">="&$R$4,'Saisie'!$A$5:$A$2004,"<="&$S$4,'Saisie'!$E$5:$E$2004,"Proposition envoyée",'Saisie'!$BA$5:$BA$2004,IF('Tableau de bord'!$G$4="Tous","<>§",'Tableau de bord'!$G$4))-COUNTIFS('Saisie'!$A$5:$A$2004,">="&$T$4,'Saisie'!$A$5:$A$2004,"<="&$U$4,'Saisie'!$E$5:$E$2004,"Proposition envoyée",'Saisie'!$BA$5:$BA$2004,IF('Tableau de bord'!$G$4="Tous","<>§",'Tableau de bord'!$G$4)))
B10: Clients signés | D10: Taux de closing | F10: CA signé | H10: CA encaissé | J10: Bénéfice net | L10: Revenu récurrent (MRR)
B11: =COUNTIFS('Prospects'!$BI$5:$BI$504,">="&$R$4,'Prospects'!$BI$5:$BI$504,"<="&$S$4,'Prospects'!$N$5:$N$504,IF('Tableau de bord'!$G$4="Tous","<>§",'Tableau de bord'!$G$4)) | D11: =IFERROR(COUNTIFS('Prospects'!$BI$5:$BI$504,">="&$R$4,'Prospects'!$BI$5:$BI$504,"<="&$S$4,'Prospects'!$N$5:$N$504,IF('Tableau de bord'!$G$4="Tous","<>§",'Tableau de bord'!$G$4))/COUNTIFS('Saisie'!$A$5:$A$2004,">="&$R$4,'Saisie'!$A$5:$A$2004,"<="&$S$4,'Saisie'!$E$5:$E$2004,"Proposition envoyée",'Saisie'!$BA$5:$BA$2004,IF('Tableau de bord'!$G$4="Tous","<>§",'Tableau de bord'!$G$4)),0) | F11: =SUMIFS('Saisie'!$AW$5:$AW$2004,'Saisie'!$A$5:$A$2004,">="&$R$4,'Saisie'!$A$5:$A$2004,"<="&$S$4,'Saisie'!$E$5:$E$2004,"Signature",'Saisie'!$BA$5:$BA$2004,IF('Tableau de bord'!$G$4="Tous","<>§",'Tableau de bord'!$G$4))+SUMIFS('Saisie'!$AW$5:$AW$2004,'Saisie'!$A$5:$A$2004,">="&$R$4,'Saisie'!$A$5:$A$2004,"<="&$S$4,'Saisie'!$E$5:$E$2004,"Vente additionnelle",'Saisie'!$BA$5:$BA$2004,IF('Tableau de bord'!$G$4="Tous","<>§",'Tableau de bord'!$G$4)) | H11: =SUMIFS('Saisie'!$AW$5:$AW$2004,'Saisie'!$A$5:$A$2004,">="&$R$4,'Saisie'!$A$5:$A$2004,"<="&$S$4,'Saisie'!$E$5:$E$2004,"Paiement reçu",'Saisie'!$BA$5:$BA$2004,IF('Tableau de bord'!$G$4="Tous","<>§",'Tableau de bord'!$G$4)) | J11: =(SUMIFS('Saisie'!$AW$5:$AW$2004,'Saisie'!$A$5:$A$2004,">="&$R$4,'Saisie'!$A$5:$A$2004,"<="&$S$4,'Saisie'!$E$5:$E$2004,"Paiement reçu",'Saisie'!$BA$5:$BA$2004,IF('Tableau de bord'!$G$4="Tous","<>§",'Tableau de bord'!$G$4))-(SUMIFS('Saisie'!$AW$5:$AW$2004,'Saisie'!$A$5:$A$2004,">="&$R$4,'Saisie'!$A$5:$A$2004,"<="&$S$4,'Saisie'!$E$5:$E$2004,"Dépense")+IF($C$4="Tous",0,SUM('Paramètres'!$AH$6:$AH$12)))) | L11: =SUMIFS('Clients'!$T$5:$T$154,'Clients'!$C$5:$C$154,"Actif",'Clients'!$G$5:$G$154,IF('Tableau de bord'!$G$4="Tous","<>§",'Tableau de bord'!$G$4))
B12: =IF(C12="","",IF(C12>0,"▲",IF(C12<0,"▼","="))) | C12: =IF($C$4="Tous","",COUNTIFS('Prospects'!$BI$5:$BI$504,">="&$R$4,'Prospects'!$BI$5:$BI$504,"<="&$S$4,'Prospects'!$N$5:$N$504,IF('Tableau de bord'!$G$4="Tous","<>§",'Tableau de bord'!$G$4))-COUNTIFS('Prospects'!$BI$5:$BI$504,">="&$T$4,'Prospects'!$BI$5:$BI$504,"<="&$U$4,'Prospects'!$N$5:$N$504,IF('Tableau de bord'!$G$4="Tous","<>§",'Tableau de bord'!$G$4))) | D12: =IF(E12="","",IF(E12>0,"▲",IF(E12<0,"▼","="))) | E12: =IF($C$4="Tous","",IFERROR(COUNTIFS('Prospects'!$BI$5:$BI$504,">="&$R$4,'Prospects'!$BI$5:$BI$504,"<="&$S$4,'Prospects'!$N$5:$N$504,IF('Tableau de bord'!$G$4="Tous","<>§",'Tableau de bord'!$G$4))/COUNTIFS('Saisie'!$A$5:$A$2004,">="&$R$4,'Saisie'!$A$5:$A$2004,"<="&$S$4,'Saisie'!$E$5:$E$2004,"Proposition envoyée",'Saisie'!$BA$5:$BA$2004,IF('Tableau de bord'!$G$4="Tous","<>§",'Tableau de bord'!$G$4)),0)-IFERROR(COUNTIFS('Prospects'!$BI$5:$BI$504,">="&$T$4,'Prospects'!$BI$5:$BI$504,"<="&$U$4,'Prospects'!$N$5:$N$504,IF('Tableau de bord'!$G$4="Tous","<>§",'Tableau de bord'!$G$4))/COUNTIFS('Saisie'!$A$5:$A$2004,">="&$T$4,'Saisie'!$A$5:$A$2004,"<="&$U$4,'Saisie'!$E$5:$E$2004,"Proposition envoyée",'Saisie'!$BA$5:$BA$2004,IF('Tableau de bord'!$G$4="Tous","<>§",'Tableau de bord'!$G$4)),0)) | F12: =IF(G12="","",IF(G12>0,"▲",IF(G12<0,"▼","="))) | G12: =IF($C$4="Tous","",SUMIFS('Saisie'!$AW$5:$AW$2004,'Saisie'!$A$5:$A$2004,">="&$R$4,'Saisie'!$A$5:$A$2004,"<="&$S$4,'Saisie'!$E$5:$E$2004,"Signature",'Saisie'!$BA$5:$BA$2004,IF('Tableau de bord'!$G$4="Tous","<>§",'Tableau de bord'!$G$4))+SUMIFS('Saisie'!$AW$5:$AW$2004,'Saisie'!$A$5:$A$2004,">="&$R$4,'Saisie'!$A$5:$A$2004,"<="&$S$4,'Saisie'!$E$5:$E$2004,"Vente additionnelle",'Saisie'!$BA$5:$BA$2004,IF('Tableau de bord'!$G$4="Tous","<>§",'Tableau de bord'!$G$4))-SUMIFS('Saisie'!$AW$5:$AW$2004,'Saisie'!$A$5:$A$2004,">="&$T$4,'Saisie'!$A$5:$A$2004,"<="&$U$4,'Saisie'!$E$5:$E$2004,"Signature",'Saisie'!$BA$5:$BA$2004,IF('Tableau de bord'!$G$4="Tous","<>§",'Tableau de bord'!$G$4))+SUMIFS('Saisie'!$AW$5:$AW$2004,'Saisie'!$A$5:$A$2004,">="&$T$4,'Saisie'!$A$5:$A$2004,"<="&$U$4,'Saisie'!$E$5:$E$2004,"Vente additionnelle",'Saisie'!$BA$5:$BA$2004,IF('Tableau de bord'!$G$4="Tous","<>§",'Tableau de bord'!$G$4))) | H12: =IF(I12="","",IF(I12>0,"▲",IF(I12<0,"▼","="))) | I12: =IF($C$4="Tous","",SUMIFS('Saisie'!$AW$5:$AW$2004,'Saisie'!$A$5:$A$2004,">="&$R$4,'Saisie'!$A$5:$A$2004,"<="&$S$4,'Saisie'!$E$5:$E$2004,"Paiement reçu",'Saisie'!$BA$5:$BA$2004,IF('Tableau de bord'!$G$4="Tous","<>§",'Tableau de bord'!$G$4))-SUMIFS('Saisie'!$AW$5:$AW$2004,'Saisie'!$A$5:$A$2004,">="&$T$4,'Saisie'!$A$5:$A$2004,"<="&$U$4,'Saisie'!$E$5:$E$2004,"Paiement reçu",'Saisie'!$BA$5:$BA$2004,IF('Tableau de bord'!$G$4="Tous","<>§",'Tableau de bord'!$G$4))) | J12: =IF(K12="","",IF(K12>0,"▲",IF(K12<0,"▼","="))) | K12: =IF($C$4="Tous","",(SUMIFS('Saisie'!$AW$5:$AW$2004,'Saisie'!$A$5:$A$2004,">="&$R$4,'Saisie'!$A$5:$A$2004,"<="&$S$4,'Saisie'!$E$5:$E$2004,"Paiement reçu",'Saisie'!$BA$5:$BA$2004,IF('Tableau de bord'!$G$4="Tous","<>§",'Tableau de bord'!$G$4))-(SUMIFS('Saisie'!$AW$5:$AW$2004,'Saisie'!$A$5:$A$2004,">="&$R$4,'Saisie'!$A$5:$A$2004,"<="&$S$4,'Saisie'!$E$5:$E$2004,"Dépense")+IF($C$4="Tous",0,SUM('Paramètres'!$AH$6:$AH$12))))-(SUMIFS('Saisie'!$AW$5:$AW$2004,'Saisie'!$A$5:$A$2004,">="&$T$4,'Saisie'!$A$5:$A$2004,"<="&$U$4,'Saisie'!$E$5:$E$2004,"Paiement reçu",'Saisie'!$BA$5:$BA$2004,IF('Tableau de bord'!$G$4="Tous","<>§",'Tableau de bord'!$G$4))-(SUMIFS('Saisie'!$AW$5:$AW$2004,'Saisie'!$A$5:$A$2004,">="&$T$4,'Saisie'!$A$5:$A$2004,"<="&$U$4,'Saisie'!$E$5:$E$2004,"Dépense")+IF($C$4="Tous",0,SUM('Paramètres'!$AH$6:$AH$12))))) | L12: =IF(M12="","",IF(M12>0,"▲",IF(M12<0,"▼","="))) | M12: =""
B13: ▲▼ = évolution par rapport au mois précédent (même canal).
B15: 🎯 OBJECTIFS DU MOIS EN COURS
B16: Objectif | D16: Réalisé | E16: Cible | F16: % atteint | G16: Progression | J16: Projection fin de mois | L16: Statut
B17: Appels | D17: =COUNTIFS('Saisie'!$A$5:$A$2004,">="&DATE(YEAR(TODAY()),MONTH(TODAY()),1),'Saisie'!$A$5:$A$2004,"<="&EOMONTH(TODAY(),0),'Saisie'!$D$5:$D$2004,"Appel",'Saisie'!$D$5:$D$2004,"<>§",'Saisie'!$AU$5:$AU$2004,1) | E17: ='Paramètres'!$B$11 | F17: =IFERROR(D17/E17,0) | G17: =REPT("█",ROUND(MIN(1,F17)*20,0))&REPT("░",20-ROUND(MIN(1,F17)*20,0)) | J17: =IFERROR(D17/DAY(TODAY())*DAY(EOMONTH(TODAY(),0)),0) | L17: =IF(J17>=E17,"✔ En avance","✖ En retard")
B18: DM | D18: =COUNTIFS('Saisie'!$A$5:$A$2004,">="&DATE(YEAR(TODAY()),MONTH(TODAY()),1),'Saisie'!$A$5:$A$2004,"<="&EOMONTH(TODAY(),0),'Saisie'!$D$5:$D$2004,"DM",'Saisie'!$D$5:$D$2004,"<>§",'Saisie'!$AU$5:$AU$2004,1) | E18: ='Paramètres'!$B$12 | F18: =IFERROR(D18/E18,0) | G18: =REPT("█",ROUND(MIN(1,F18)*20,0))&REPT("░",20-ROUND(MIN(1,F18)*20,0)) | J18: =IFERROR(D18/DAY(TODAY())*DAY(EOMONTH(TODAY(),0)),0) | L18: =IF(J18>=E18,"✔ En avance","✖ En retard")
B19: RDV | D19: =COUNTIFS('Prospects'!$BG$5:$BG$504,">="&DATE(YEAR(TODAY()),MONTH(TODAY()),1),'Prospects'!$BG$5:$BG$504,"<="&EOMONTH(TODAY(),0),'Prospects'!$N$5:$N$504,"<>§") | E19: ='Paramètres'!$B$13 | F19: =IFERROR(D19/E19,0) | G19: =REPT("█",ROUND(MIN(1,F19)*20,0))&REPT("░",20-ROUND(MIN(1,F19)*20,0)) | J19: =IFERROR(D19/DAY(TODAY())*DAY(EOMONTH(TODAY(),0)),0) | L19: =IF(J19>=E19,"✔ En avance","✖ En retard")
B20: Clients signés | D20: =COUNTIFS('Prospects'!$BI$5:$BI$504,">="&DATE(YEAR(TODAY()),MONTH(TODAY()),1),'Prospects'!$BI$5:$BI$504,"<="&EOMONTH(TODAY(),0),'Prospects'!$N$5:$N$504,"<>§") | E20: ='Paramètres'!$B$14 | F20: =IFERROR(D20/E20,0) | G20: =REPT("█",ROUND(MIN(1,F20)*20,0))&REPT("░",20-ROUND(MIN(1,F20)*20,0)) | J20: =IFERROR(D20/DAY(TODAY())*DAY(EOMONTH(TODAY(),0)),0) | L20: =IF(J20>=E20,"✔ En avance","✖ En retard")
B21: CA signé | D21: =SUMIFS('Saisie'!$AW$5:$AW$2004,'Saisie'!$A$5:$A$2004,">="&DATE(YEAR(TODAY()),MONTH(TODAY()),1),'Saisie'!$A$5:$A$2004,"<="&EOMONTH(TODAY(),0),'Saisie'!$E$5:$E$2004,"Signature",'Saisie'!$BA$5:$BA$2004,"<>§")+SUMIFS('Saisie'!$AW$5:$AW$2004,'Saisie'!$A$5:$A$2004,">="&DATE(YEAR(TODAY()),MONTH(TODAY()),1),'Saisie'!$A$5:$A$2004,"<="&EOMONTH(TODAY(),0),'Saisie'!$E$5:$E$2004,"Vente additionnelle",'Saisie'!$BA$5:$BA$2004,"<>§") | E21: ='Paramètres'!$B$15 | F21: =IFERROR(D21/E21,0) | G21: =REPT("█",ROUND(MIN(1,F21)*20,0))&REPT("░",20-ROUND(MIN(1,F21)*20,0)) | J21: =IFERROR(D21/DAY(TODAY())*DAY(EOMONTH(TODAY(),0)),0) | L21: =IF(J21>=E21,"✔ En avance","✖ En retard")
B23: 💶 PIPELINE, TRÉSORERIE ET PRÉVISIONS
B24: Pipeline pondéré (montant × probabilité) | F24: =SUMIFS('Prospects'!$AS$5:$AS$504,'Prospects'!$N$5:$N$504,IF('Tableau de bord'!$G$4="Tous","<>§",'Tableau de bord'!$G$4)) | H24: Prévision | I24: Encaissements attendus | K24: Dépenses fixes | L24: Solde
B25: Propositions en attente (montant) | F25: =SUMIFS('Prospects'!$AP$5:$AP$504,'Prospects'!$D$5:$D$504,"Proposition",'Prospects'!$N$5:$N$504,IF('Tableau de bord'!$G$4="Tous","<>§",'Tableau de bord'!$G$4)) | H25: =EDATE(DATE(YEAR(TODAY()),MONTH(TODAY()),1),1) | I25: =SUMIFS('Clients'!$T$5:$T$154,'Clients'!$C$5:$C$154,"Actif")+SUM('Clients'!$Q$5:$Q$154) | K25: =SUM('Paramètres'!$AH$6:$AH$12) | L25: =I25-K25
B26: Reste à encaisser (clients) | F26: =SUMIFS('Clients'!$Q$5:$Q$154,'Clients'!$G$5:$G$154,IF('Tableau de bord'!$G$4="Tous","<>§",'Tableau de bord'!$G$4)) | H26: =EDATE(DATE(YEAR(TODAY()),MONTH(TODAY()),1),2) | I26: =SUMIFS('Clients'!$T$5:$T$154,'Clients'!$C$5:$C$154,"Actif") | K26: =SUM('Paramètres'!$AH$6:$AH$12) | L26: =I26-K26
B27: Dépenses de la période | F27: =(SUMIFS('Saisie'!$AW$5:$AW$2004,'Saisie'!$A$5:$A$2004,">="&$R$4,'Saisie'!$A$5:$A$2004,"<="&$S$4,'Saisie'!$E$5:$E$2004,"Dépense")+IF($C$4="Tous",0,SUM('Paramètres'!$AH$6:$AH$12))) | H27: =EDATE(DATE(YEAR(TODAY()),MONTH(TODAY()),1),3) | I27: =SUMIFS('Clients'!$T$5:$T$154,'Clients'!$C$5:$C$154,"Actif") | K27: =SUM('Paramètres'!$AH$6:$AH$12) | L27: =I27-K27
B28: Valeur vie client moyenne | F28: =IFERROR(AVERAGEIFS('Clients'!$X$5:$X$154,'Clients'!$B$5:$B$154,"?*"),0) | H28: M+1 inclut le reste à encaisser. Le pipeline pondéré est un potentiel, non compté.
B29: Taux de résiliation (période) | F29: =IFERROR(COUNTIFS('Clients'!$AC$5:$AC$154,">="&$R$4,'Clients'!$AC$5:$AC$154,"<="&$S$4)/COUNTIFS('Clients'!$L$5:$L$154,"<"&$R$4,'Clients'!$B$5:$B$154,"?*"),0)
B31: 🔻 ENTONNOIR DU PIPELINE (prospects ajoutés sur la période)
B32: Étape | D32: Prospects | E32: Conversion
B33: Nouveau | D33: =COUNTIFS('Prospects'!$BW$5:$BW$504,1,'Prospects'!$BA$5:$BA$504,">=1")
B34: Contacté | D34: =COUNTIFS('Prospects'!$BW$5:$BW$504,1,'Prospects'!$BA$5:$BA$504,">=2") | E34: =IFERROR(D34/D33,0)
B35: Qualifié | D35: =COUNTIFS('Prospects'!$BW$5:$BW$504,1,'Prospects'!$BA$5:$BA$504,">=3") | E35: =IFERROR(D35/D34,0)
B36: Audit/Démo | D36: =COUNTIFS('Prospects'!$BW$5:$BW$504,1,'Prospects'!$BA$5:$BA$504,">=4") | E36: =IFERROR(D36/D35,0)
B37: RDV | D37: =COUNTIFS('Prospects'!$BW$5:$BW$504,1,'Prospects'!$BA$5:$BA$504,">=5") | E37: =IFERROR(D37/D36,0)
B38: Proposition | D38: =COUNTIFS('Prospects'!$BW$5:$BW$504,1,'Prospects'!$BA$5:$BA$504,">=6") | E38: =IFERROR(D38/D37,0)
B39: Gagné | D39: =COUNTIFS('Prospects'!$BW$5:$BW$504,1,'Prospects'!$BA$5:$BA$504,">=7") | E39: =IFERROR(D39/D38,0)
B40: Perdus | D40: =COUNTIFS('Prospects'!$BW$5:$BW$504,1,'Prospects'!$D$5:$D$504,"Perdu")
B42: 📡 CE QUE PRODUIT CHAQUE CANAL (période choisie)
B43: Canal | C43: Actions | D43: Réponses | E43: Taux de réponse | F43: Temps (h) | G43: RDV | H43: Clients | I43: CA signé | J43: CA / heure | K43: Heures / client | L43: Appels / heure
B44: DM | C44: =COUNTIFS('Saisie'!$A$5:$A$2004,">="&$R$4,'Saisie'!$A$5:$A$2004,"<="&$S$4,'Saisie'!$D$5:$D$2004,"DM",'Saisie'!$AU$5:$AU$2004,1) | D44: =COUNTIFS('Saisie'!$A$5:$A$2004,">="&$R$4,'Saisie'!$A$5:$A$2004,"<="&$S$4,'Saisie'!$D$5:$D$2004,"DM",'Saisie'!$AV$5:$AV$2004,1) | E44: =IFERROR(D44/C44,0) | F44: =SUMIFS('Saisie'!$H$5:$H$2004,'Saisie'!$A$5:$A$2004,">="&$R$4,'Saisie'!$A$5:$A$2004,"<="&$S$4,'Saisie'!$D$5:$D$2004,"DM")/60 | G44: =COUNTIFS('Prospects'!$BG$5:$BG$504,">="&$R$4,'Prospects'!$BG$5:$BG$504,"<="&$S$4,'Prospects'!$N$5:$N$504,"DM") | H44: =COUNTIFS('Prospects'!$BI$5:$BI$504,">="&$R$4,'Prospects'!$BI$5:$BI$504,"<="&$S$4,'Prospects'!$N$5:$N$504,"DM") | I44: =SUMIFS('Saisie'!$AW$5:$AW$2004,'Saisie'!$A$5:$A$2004,">="&$R$4,'Saisie'!$A$5:$A$2004,"<="&$S$4,'Saisie'!$E$5:$E$2004,"Signature",'Saisie'!$BA$5:$BA$2004,"DM")+SUMIFS('Saisie'!$AW$5:$AW$2004,'Saisie'!$A$5:$A$2004,">="&$R$4,'Saisie'!$A$5:$A$2004,"<="&$S$4,'Saisie'!$E$5:$E$2004,"Vente additionnelle",'Saisie'!$BA$5:$BA$2004,"DM") | J44: =IFERROR(I44/F44,0) | K44: =IFERROR(F44/H44,0) | L44: =IFERROR(C44/(SUMIFS('Saisie'!$H$5:$H$2004,'Saisie'!$A$5:$A$2004,">="&$R$4,'Saisie'!$A$5:$A$2004,"<="&$S$4,'Saisie'!$D$5:$D$2004,"DM",'Saisie'!$AU$5:$AU$2004,1)/60),0)
B45: Appel | C45: =COUNTIFS('Saisie'!$A$5:$A$2004,">="&$R$4,'Saisie'!$A$5:$A$2004,"<="&$S$4,'Saisie'!$D$5:$D$2004,"Appel",'Saisie'!$AU$5:$AU$2004,1) | D45: =COUNTIFS('Saisie'!$A$5:$A$2004,">="&$R$4,'Saisie'!$A$5:$A$2004,"<="&$S$4,'Saisie'!$D$5:$D$2004,"Appel",'Saisie'!$AV$5:$AV$2004,1) | E45: =IFERROR(D45/C45,0) | F45: =SUMIFS('Saisie'!$H$5:$H$2004,'Saisie'!$A$5:$A$2004,">="&$R$4,'Saisie'!$A$5:$A$2004,"<="&$S$4,'Saisie'!$D$5:$D$2004,"Appel")/60 | G45: =COUNTIFS('Prospects'!$BG$5:$BG$504,">="&$R$4,'Prospects'!$BG$5:$BG$504,"<="&$S$4,'Prospects'!$N$5:$N$504,"Appel") | H45: =COUNTIFS('Prospects'!$BI$5:$BI$504,">="&$R$4,'Prospects'!$BI$5:$BI$504,"<="&$S$4,'Prospects'!$N$5:$N$504,"Appel") | I45: =SUMIFS('Saisie'!$AW$5:$AW$2004,'Saisie'!$A$5:$A$2004,">="&$R$4,'Saisie'!$A$5:$A$2004,"<="&$S$4,'Saisie'!$E$5:$E$2004,"Signature",'Saisie'!$BA$5:$BA$2004,"Appel")+SUMIFS('Saisie'!$AW$5:$AW$2004,'Saisie'!$A$5:$A$2004,">="&$R$4,'Saisie'!$A$5:$A$2004,"<="&$S$4,'Saisie'!$E$5:$E$2004,"Vente additionnelle",'Saisie'!$BA$5:$BA$2004,"Appel") | J45: =IFERROR(I45/F45,0) | K45: =IFERROR(F45/H45,0) | L45: =IFERROR(C45/(SUMIFS('Saisie'!$H$5:$H$2004,'Saisie'!$A$5:$A$2004,">="&$R$4,'Saisie'!$A$5:$A$2004,"<="&$S$4,'Saisie'!$D$5:$D$2004,"Appel",'Saisie'!$AU$5:$AU$2004,1)/60),0)
B46: WhatsApp | C46: =COUNTIFS('Saisie'!$A$5:$A$2004,">="&$R$4,'Saisie'!$A$5:$A$2004,"<="&$S$4,'Saisie'!$D$5:$D$2004,"WhatsApp",'Saisie'!$AU$5:$AU$2004,1) | D46: =COUNTIFS('Saisie'!$A$5:$A$2004,">="&$R$4,'Saisie'!$A$5:$A$2004,"<="&$S$4,'Saisie'!$D$5:$D$2004,"WhatsApp",'Saisie'!$AV$5:$AV$2004,1) | E46: =IFERROR(D46/C46,0) | F46: =SUMIFS('Saisie'!$H$5:$H$2004,'Saisie'!$A$5:$A$2004,">="&$R$4,'Saisie'!$A$5:$A$2004,"<="&$S$4,'Saisie'!$D$5:$D$2004,"WhatsApp")/60 | G46: =COUNTIFS('Prospects'!$BG$5:$BG$504,">="&$R$4,'Prospects'!$BG$5:$BG$504,"<="&$S$4,'Prospects'!$N$5:$N$504,"WhatsApp") | H46: =COUNTIFS('Prospects'!$BI$5:$BI$504,">="&$R$4,'Prospects'!$BI$5:$BI$504,"<="&$S$4,'Prospects'!$N$5:$N$504,"WhatsApp") | I46: =SUMIFS('Saisie'!$AW$5:$AW$2004,'Saisie'!$A$5:$A$2004,">="&$R$4,'Saisie'!$A$5:$A$2004,"<="&$S$4,'Saisie'!$E$5:$E$2004,"Signature",'Saisie'!$BA$5:$BA$2004,"WhatsApp")+SUMIFS('Saisie'!$AW$5:$AW$2004,'Saisie'!$A$5:$A$2004,">="&$R$4,'Saisie'!$A$5:$A$2004,"<="&$S$4,'Saisie'!$E$5:$E$2004,"Vente additionnelle",'Saisie'!$BA$5:$BA$2004,"WhatsApp") | J46: =IFERROR(I46/F46,0) | K46: =IFERROR(F46/H46,0) | L46: =IFERROR(C46/(SUMIFS('Saisie'!$H$5:$H$2004,'Saisie'!$A$5:$A$2004,">="&$R$4,'Saisie'!$A$5:$A$2004,"<="&$S$4,'Saisie'!$D$5:$D$2004,"WhatsApp",'Saisie'!$AU$5:$AU$2004,1)/60),0)
B47: Facebook | C47: =COUNTIFS('Saisie'!$A$5:$A$2004,">="&$R$4,'Saisie'!$A$5:$A$2004,"<="&$S$4,'Saisie'!$D$5:$D$2004,"Facebook",'Saisie'!$AU$5:$AU$2004,1) | D47: =COUNTIFS('Saisie'!$A$5:$A$2004,">="&$R$4,'Saisie'!$A$5:$A$2004,"<="&$S$4,'Saisie'!$D$5:$D$2004,"Facebook",'Saisie'!$AV$5:$AV$2004,1) | E47: =IFERROR(D47/C47,0) | F47: =SUMIFS('Saisie'!$H$5:$H$2004,'Saisie'!$A$5:$A$2004,">="&$R$4,'Saisie'!$A$5:$A$2004,"<="&$S$4,'Saisie'!$D$5:$D$2004,"Facebook")/60 | G47: =COUNTIFS('Prospects'!$BG$5:$BG$504,">="&$R$4,'Prospects'!$BG$5:$BG$504,"<="&$S$4,'Prospects'!$N$5:$N$504,"Facebook") | H47: =COUNTIFS('Prospects'!$BI$5:$BI$504,">="&$R$4,'Prospects'!$BI$5:$BI$504,"<="&$S$4,'Prospects'!$N$5:$N$504,"Facebook") | I47: =SUMIFS('Saisie'!$AW$5:$AW$2004,'Saisie'!$A$5:$A$2004,">="&$R$4,'Saisie'!$A$5:$A$2004,"<="&$S$4,'Saisie'!$E$5:$E$2004,"Signature",'Saisie'!$BA$5:$BA$2004,"Facebook")+SUMIFS('Saisie'!$AW$5:$AW$2004,'Saisie'!$A$5:$A$2004,">="&$R$4,'Saisie'!$A$5:$A$2004,"<="&$S$4,'Saisie'!$E$5:$E$2004,"Vente additionnelle",'Saisie'!$BA$5:$BA$2004,"Facebook") | J47: =IFERROR(I47/F47,0) | K47: =IFERROR(F47/H47,0) | L47: =IFERROR(C47/(SUMIFS('Saisie'!$H$5:$H$2004,'Saisie'!$A$5:$A$2004,">="&$R$4,'Saisie'!$A$5:$A$2004,"<="&$S$4,'Saisie'!$D$5:$D$2004,"Facebook",'Saisie'!$AU$5:$AU$2004,1)/60),0)
B48: Autre | C48: =COUNTIFS('Saisie'!$A$5:$A$2004,">="&$R$4,'Saisie'!$A$5:$A$2004,"<="&$S$4,'Saisie'!$D$5:$D$2004,"Autre",'Saisie'!$AU$5:$AU$2004,1) | D48: =COUNTIFS('Saisie'!$A$5:$A$2004,">="&$R$4,'Saisie'!$A$5:$A$2004,"<="&$S$4,'Saisie'!$D$5:$D$2004,"Autre",'Saisie'!$AV$5:$AV$2004,1) | E48: =IFERROR(D48/C48,0) | F48: =SUMIFS('Saisie'!$H$5:$H$2004,'Saisie'!$A$5:$A$2004,">="&$R$4,'Saisie'!$A$5:$A$2004,"<="&$S$4,'Saisie'!$D$5:$D$2004,"Autre")/60 | G48: =COUNTIFS('Prospects'!$BG$5:$BG$504,">="&$R$4,'Prospects'!$BG$5:$BG$504,"<="&$S$4,'Prospects'!$N$5:$N$504,"Autre") | H48: =COUNTIFS('Prospects'!$BI$5:$BI$504,">="&$R$4,'Prospects'!$BI$5:$BI$504,"<="&$S$4,'Prospects'!$N$5:$N$504,"Autre") | I48: =SUMIFS('Saisie'!$AW$5:$AW$2004,'Saisie'!$A$5:$A$2004,">="&$R$4,'Saisie'!$A$5:$A$2004,"<="&$S$4,'Saisie'!$E$5:$E$2004,"Signature",'Saisie'!$BA$5:$BA$2004,"Autre")+SUMIFS('Saisie'!$AW$5:$AW$2004,'Saisie'!$A$5:$A$2004,">="&$R$4,'Saisie'!$A$5:$A$2004,"<="&$S$4,'Saisie'!$E$5:$E$2004,"Vente additionnelle",'Saisie'!$BA$5:$BA$2004,"Autre") | J48: =IFERROR(I48/F48,0) | K48: =IFERROR(F48/H48,0) | L48: =IFERROR(C48/(SUMIFS('Saisie'!$H$5:$H$2004,'Saisie'!$A$5:$A$2004,">="&$R$4,'Saisie'!$A$5:$A$2004,"<="&$S$4,'Saisie'!$D$5:$D$2004,"Autre",'Saisie'!$AU$5:$AU$2004,1)/60),0)
B49: Total | C49: =SUM(C44:C48) | D49: =SUM(D44:D48) | E49: =IFERROR(D49/C49,0) | F49: =SUM(F44:F48) | G49: =SUM(G44:G48) | H49: =SUM(H44:H48) | I49: =SUM(I44:I48) | J49: =IFERROR(I49/F49,0) | K49: =IFERROR(F49/H49,0)
B64: 📈 ÉVOLUTION MOIS PAR MOIS (année du mois choisi, canal choisi)
B65: Mois | C65: Prospects | D65: Appels | E65: DM | F65: RDV | G65: Clients | H65: CA signé | I65: CA encaissé | J65: Dépenses | K65: Bénéfice
B66: =DATE(YEAR(IF($C$4="Tous",TODAY(),$R$4)),1,1) | C66: =COUNTIFS('Prospects'!$B$5:$B$504,">="&$B66,'Prospects'!$B$5:$B$504,"<="&EOMONTH($B66,0),'Prospects'!$N$5:$N$504,IF('Tableau de bord'!$G$4="Tous","<>§",'Tableau de bord'!$G$4)) | D66: =COUNTIFS('Saisie'!$A$5:$A$2004,">="&$B66,'Saisie'!$A$5:$A$2004,"<="&EOMONTH($B66,0),'Saisie'!$D$5:$D$2004,"Appel",'Saisie'!$D$5:$D$2004,IF('Tableau de bord'!$G$4="Tous","<>§",'Tableau de bord'!$G$4),'Saisie'!$AU$5:$AU$2004,1) | E66: =COUNTIFS('Saisie'!$A$5:$A$2004,">="&$B66,'Saisie'!$A$5:$A$2004,"<="&EOMONTH($B66,0),'Saisie'!$D$5:$D$2004,"DM",'Saisie'!$D$5:$D$2004,IF('Tableau de bord'!$G$4="Tous","<>§",'Tableau de bord'!$G$4),'Saisie'!$AU$5:$AU$2004,1) | F66: =COUNTIFS('Prospects'!$BG$5:$BG$504,">="&$B66,'Prospects'!$BG$5:$BG$504,"<="&EOMONTH($B66,0),'Prospects'!$N$5:$N$504,IF('Tableau de bord'!$G$4="Tous","<>§",'Tableau de bord'!$G$4)) | G66: =COUNTIFS('Prospects'!$BI$5:$BI$504,">="&$B66,'Prospects'!$BI$5:$BI$504,"<="&EOMONTH($B66,0),'Prospects'!$N$5:$N$504,IF('Tableau de bord'!$G$4="Tous","<>§",'Tableau de bord'!$G$4)) | H66: =SUMIFS('Saisie'!$AW$5:$AW$2004,'Saisie'!$A$5:$A$2004,">="&$B66,'Saisie'!$A$5:$A$2004,"<="&EOMONTH($B66,0),'Saisie'!$E$5:$E$2004,"Signature",'Saisie'!$BA$5:$BA$2004,IF('Tableau de bord'!$G$4="Tous","<>§",'Tableau de bord'!$G$4))+SUMIFS('Saisie'!$AW$5:$AW$2004,'Saisie'!$A$5:$A$2004,">="&$B66,'Saisie'!$A$5:$A$2004,"<="&EOMONTH($B66,0),'Saisie'!$E$5:$E$2004,"Vente additionnelle",'Saisie'!$BA$5:$BA$2004,IF('Tableau de bord'!$G$4="Tous","<>§",'Tableau de bord'!$G$4)) | I66: =SUMIFS('Saisie'!$AW$5:$AW$2004,'Saisie'!$A$5:$A$2004,">="&$B66,'Saisie'!$A$5:$A$2004,"<="&EOMONTH($B66,0),'Saisie'!$E$5:$E$2004,"Paiement reçu",'Saisie'!$BA$5:$BA$2004,IF('Tableau de bord'!$G$4="Tous","<>§",'Tableau de bord'!$G$4)) | J66: =SUMIFS('Saisie'!$AW$5:$AW$2004,'Saisie'!$A$5:$A$2004,">="&$B66,'Saisie'!$A$5:$A$2004,"<="&EOMONTH($B66,0),'Saisie'!$E$5:$E$2004,"Dépense")+SUM('Paramètres'!$AH$6:$AH$12) | K66: =I66-J66
B67: =DATE(YEAR(IF($C$4="Tous",TODAY(),$R$4)),2,1) | C67: =COUNTIFS('Prospects'!$B$5:$B$504,">="&$B67,'Prospects'!$B$5:$B$504,"<="&EOMONTH($B67,0),'Prospects'!$N$5:$N$504,IF('Tableau de bord'!$G$4="Tous","<>§",'Tableau de bord'!$G$4)) | D67: =COUNTIFS('Saisie'!$A$5:$A$2004,">="&$B67,'Saisie'!$A$5:$A$2004,"<="&EOMONTH($B67,0),'Saisie'!$D$5:$D$2004,"Appel",'Saisie'!$D$5:$D$2004,IF('Tableau de bord'!$G$4="Tous","<>§",'Tableau de bord'!$G$4),'Saisie'!$AU$5:$AU$2004,1) | E67: =COUNTIFS('Saisie'!$A$5:$A$2004,">="&$B67,'Saisie'!$A$5:$A$2004,"<="&EOMONTH($B67,0),'Saisie'!$D$5:$D$2004,"DM",'Saisie'!$D$5:$D$2004,IF('Tableau de bord'!$G$4="Tous","<>§",'Tableau de bord'!$G$4),'Saisie'!$AU$5:$AU$2004,1) | F67: =COUNTIFS('Prospects'!$BG$5:$BG$504,">="&$B67,'Prospects'!$BG$5:$BG$504,"<="&EOMONTH($B67,0),'Prospects'!$N$5:$N$504,IF('Tableau de bord'!$G$4="Tous","<>§",'Tableau de bord'!$G$4)) | G67: =COUNTIFS('Prospects'!$BI$5:$BI$504,">="&$B67,'Prospects'!$BI$5:$BI$504,"<="&EOMONTH($B67,0),'Prospects'!$N$5:$N$504,IF('Tableau de bord'!$G$4="Tous","<>§",'Tableau de bord'!$G$4)) | H67: =SUMIFS('Saisie'!$AW$5:$AW$2004,'Saisie'!$A$5:$A$2004,">="&$B67,'Saisie'!$A$5:$A$2004,"<="&EOMONTH($B67,0),'Saisie'!$E$5:$E$2004,"Signature",'Saisie'!$BA$5:$BA$2004,IF('Tableau de bord'!$G$4="Tous","<>§",'Tableau de bord'!$G$4))+SUMIFS('Saisie'!$AW$5:$AW$2004,'Saisie'!$A$5:$A$2004,">="&$B67,'Saisie'!$A$5:$A$2004,"<="&EOMONTH($B67,0),'Saisie'!$E$5:$E$2004,"Vente additionnelle",'Saisie'!$BA$5:$BA$2004,IF('Tableau de bord'!$G$4="Tous","<>§",'Tableau de bord'!$G$4)) | I67: =SUMIFS('Saisie'!$AW$5:$AW$2004,'Saisie'!$A$5:$A$2004,">="&$B67,'Saisie'!$A$5:$A$2004,"<="&EOMONTH($B67,0),'Saisie'!$E$5:$E$2004,"Paiement reçu",'Saisie'!$BA$5:$BA$2004,IF('Tableau de bord'!$G$4="Tous","<>§",'Tableau de bord'!$G$4)) | J67: =SUMIFS('Saisie'!$AW$5:$AW$2004,'Saisie'!$A$5:$A$2004,">="&$B67,'Saisie'!$A$5:$A$2004,"<="&EOMONTH($B67,0),'Saisie'!$E$5:$E$2004,"Dépense")+SUM('Paramètres'!$AH$6:$AH$12) | K67: =I67-J67
B68: =DATE(YEAR(IF($C$4="Tous",TODAY(),$R$4)),3,1) | C68: =COUNTIFS('Prospects'!$B$5:$B$504,">="&$B68,'Prospects'!$B$5:$B$504,"<="&EOMONTH($B68,0),'Prospects'!$N$5:$N$504,IF('Tableau de bord'!$G$4="Tous","<>§",'Tableau de bord'!$G$4)) | D68: =COUNTIFS('Saisie'!$A$5:$A$2004,">="&$B68,'Saisie'!$A$5:$A$2004,"<="&EOMONTH($B68,0),'Saisie'!$D$5:$D$2004,"Appel",'Saisie'!$D$5:$D$2004,IF('Tableau de bord'!$G$4="Tous","<>§",'Tableau de bord'!$G$4),'Saisie'!$AU$5:$AU$2004,1) | E68: =COUNTIFS('Saisie'!$A$5:$A$2004,">="&$B68,'Saisie'!$A$5:$A$2004,"<="&EOMONTH($B68,0),'Saisie'!$D$5:$D$2004,"DM",'Saisie'!$D$5:$D$2004,IF('Tableau de bord'!$G$4="Tous","<>§",'Tableau de bord'!$G$4),'Saisie'!$AU$5:$AU$2004,1) | F68: =COUNTIFS('Prospects'!$BG$5:$BG$504,">="&$B68,'Prospects'!$BG$5:$BG$504,"<="&EOMONTH($B68,0),'Prospects'!$N$5:$N$504,IF('Tableau de bord'!$G$4="Tous","<>§",'Tableau de bord'!$G$4)) | G68: =COUNTIFS('Prospects'!$BI$5:$BI$504,">="&$B68,'Prospects'!$BI$5:$BI$504,"<="&EOMONTH($B68,0),'Prospects'!$N$5:$N$504,IF('Tableau de bord'!$G$4="Tous","<>§",'Tableau de bord'!$G$4)) | H68: =SUMIFS('Saisie'!$AW$5:$AW$2004,'Saisie'!$A$5:$A$2004,">="&$B68,'Saisie'!$A$5:$A$2004,"<="&EOMONTH($B68,0),'Saisie'!$E$5:$E$2004,"Signature",'Saisie'!$BA$5:$BA$2004,IF('Tableau de bord'!$G$4="Tous","<>§",'Tableau de bord'!$G$4))+SUMIFS('Saisie'!$AW$5:$AW$2004,'Saisie'!$A$5:$A$2004,">="&$B68,'Saisie'!$A$5:$A$2004,"<="&EOMONTH($B68,0),'Saisie'!$E$5:$E$2004,"Vente additionnelle",'Saisie'!$BA$5:$BA$2004,IF('Tableau de bord'!$G$4="Tous","<>§",'Tableau de bord'!$G$4)) | I68: =SUMIFS('Saisie'!$AW$5:$AW$2004,'Saisie'!$A$5:$A$2004,">="&$B68,'Saisie'!$A$5:$A$2004,"<="&EOMONTH($B68,0),'Saisie'!$E$5:$E$2004,"Paiement reçu",'Saisie'!$BA$5:$BA$2004,IF('Tableau de bord'!$G$4="Tous","<>§",'Tableau de bord'!$G$4)) | J68: =SUMIFS('Saisie'!$AW$5:$AW$2004,'Saisie'!$A$5:$A$2004,">="&$B68,'Saisie'!$A$5:$A$2004,"<="&EOMONTH($B68,0),'Saisie'!$E$5:$E$2004,"Dépense")+SUM('Paramètres'!$AH$6:$AH$12) | K68: =I68-J68
B69: =DATE(YEAR(IF($C$4="Tous",TODAY(),$R$4)),4,1) | C69: =COUNTIFS('Prospects'!$B$5:$B$504,">="&$B69,'Prospects'!$B$5:$B$504,"<="&EOMONTH($B69,0),'Prospects'!$N$5:$N$504,IF('Tableau de bord'!$G$4="Tous","<>§",'Tableau de bord'!$G$4)) | D69: =COUNTIFS('Saisie'!$A$5:$A$2004,">="&$B69,'Saisie'!$A$5:$A$2004,"<="&EOMONTH($B69,0),'Saisie'!$D$5:$D$2004,"Appel",'Saisie'!$D$5:$D$2004,IF('Tableau de bord'!$G$4="Tous","<>§",'Tableau de bord'!$G$4),'Saisie'!$AU$5:$AU$2004,1) | E69: =COUNTIFS('Saisie'!$A$5:$A$2004,">="&$B69,'Saisie'!$A$5:$A$2004,"<="&EOMONTH($B69,0),'Saisie'!$D$5:$D$2004,"DM",'Saisie'!$D$5:$D$2004,IF('Tableau de bord'!$G$4="Tous","<>§",'Tableau de bord'!$G$4),'Saisie'!$AU$5:$AU$2004,1) | F69: =COUNTIFS('Prospects'!$BG$5:$BG$504,">="&$B69,'Prospects'!$BG$5:$BG$504,"<="&EOMONTH($B69,0),'Prospects'!$N$5:$N$504,IF('Tableau de bord'!$G$4="Tous","<>§",'Tableau de bord'!$G$4)) | G69: =COUNTIFS('Prospects'!$BI$5:$BI$504,">="&$B69,'Prospects'!$BI$5:$BI$504,"<="&EOMONTH($B69,0),'Prospects'!$N$5:$N$504,IF('Tableau de bord'!$G$4="Tous","<>§",'Tableau de bord'!$G$4)) | H69: =SUMIFS('Saisie'!$AW$5:$AW$2004,'Saisie'!$A$5:$A$2004,">="&$B69,'Saisie'!$A$5:$A$2004,"<="&EOMONTH($B69,0),'Saisie'!$E$5:$E$2004,"Signature",'Saisie'!$BA$5:$BA$2004,IF('Tableau de bord'!$G$4="Tous","<>§",'Tableau de bord'!$G$4))+SUMIFS('Saisie'!$AW$5:$AW$2004,'Saisie'!$A$5:$A$2004,">="&$B69,'Saisie'!$A$5:$A$2004,"<="&EOMONTH($B69,0),'Saisie'!$E$5:$E$2004,"Vente additionnelle",'Saisie'!$BA$5:$BA$2004,IF('Tableau de bord'!$G$4="Tous","<>§",'Tableau de bord'!$G$4)) | I69: =SUMIFS('Saisie'!$AW$5:$AW$2004,'Saisie'!$A$5:$A$2004,">="&$B69,'Saisie'!$A$5:$A$2004,"<="&EOMONTH($B69,0),'Saisie'!$E$5:$E$2004,"Paiement reçu",'Saisie'!$BA$5:$BA$2004,IF('Tableau de bord'!$G$4="Tous","<>§",'Tableau de bord'!$G$4)) | J69: =SUMIFS('Saisie'!$AW$5:$AW$2004,'Saisie'!$A$5:$A$2004,">="&$B69,'Saisie'!$A$5:$A$2004,"<="&EOMONTH($B69,0),'Saisie'!$E$5:$E$2004,"Dépense")+SUM('Paramètres'!$AH$6:$AH$12) | K69: =I69-J69
B70: =DATE(YEAR(IF($C$4="Tous",TODAY(),$R$4)),5,1) | C70: =COUNTIFS('Prospects'!$B$5:$B$504,">="&$B70,'Prospects'!$B$5:$B$504,"<="&EOMONTH($B70,0),'Prospects'!$N$5:$N$504,IF('Tableau de bord'!$G$4="Tous","<>§",'Tableau de bord'!$G$4)) | D70: =COUNTIFS('Saisie'!$A$5:$A$2004,">="&$B70,'Saisie'!$A$5:$A$2004,"<="&EOMONTH($B70,0),'Saisie'!$D$5:$D$2004,"Appel",'Saisie'!$D$5:$D$2004,IF('Tableau de bord'!$G$4="Tous","<>§",'Tableau de bord'!$G$4),'Saisie'!$AU$5:$AU$2004,1) | E70: =COUNTIFS('Saisie'!$A$5:$A$2004,">="&$B70,'Saisie'!$A$5:$A$2004,"<="&EOMONTH($B70,0),'Saisie'!$D$5:$D$2004,"DM",'Saisie'!$D$5:$D$2004,IF('Tableau de bord'!$G$4="Tous","<>§",'Tableau de bord'!$G$4),'Saisie'!$AU$5:$AU$2004,1) | F70: =COUNTIFS('Prospects'!$BG$5:$BG$504,">="&$B70,'Prospects'!$BG$5:$BG$504,"<="&EOMONTH($B70,0),'Prospects'!$N$5:$N$504,IF('Tableau de bord'!$G$4="Tous","<>§",'Tableau de bord'!$G$4)) | G70: =COUNTIFS('Prospects'!$BI$5:$BI$504,">="&$B70,'Prospects'!$BI$5:$BI$504,"<="&EOMONTH($B70,0),'Prospects'!$N$5:$N$504,IF('Tableau de bord'!$G$4="Tous","<>§",'Tableau de bord'!$G$4)) | H70: =SUMIFS('Saisie'!$AW$5:$AW$2004,'Saisie'!$A$5:$A$2004,">="&$B70,'Saisie'!$A$5:$A$2004,"<="&EOMONTH($B70,0),'Saisie'!$E$5:$E$2004,"Signature",'Saisie'!$BA$5:$BA$2004,IF('Tableau de bord'!$G$4="Tous","<>§",'Tableau de bord'!$G$4))+SUMIFS('Saisie'!$AW$5:$AW$2004,'Saisie'!$A$5:$A$2004,">="&$B70,'Saisie'!$A$5:$A$2004,"<="&EOMONTH($B70,0),'Saisie'!$E$5:$E$2004,"Vente additionnelle",'Saisie'!$BA$5:$BA$2004,IF('Tableau de bord'!$G$4="Tous","<>§",'Tableau de bord'!$G$4)) | I70: =SUMIFS('Saisie'!$AW$5:$AW$2004,'Saisie'!$A$5:$A$2004,">="&$B70,'Saisie'!$A$5:$A$2004,"<="&EOMONTH($B70,0),'Saisie'!$E$5:$E$2004,"Paiement reçu",'Saisie'!$BA$5:$BA$2004,IF('Tableau de bord'!$G$4="Tous","<>§",'Tableau de bord'!$G$4)) | J70: =SUMIFS('Saisie'!$AW$5:$AW$2004,'Saisie'!$A$5:$A$2004,">="&$B70,'Saisie'!$A$5:$A$2004,"<="&EOMONTH($B70,0),'Saisie'!$E$5:$E$2004,"Dépense")+SUM('Paramètres'!$AH$6:$AH$12) | K70: =I70-J70
B71: =DATE(YEAR(IF($C$4="Tous",TODAY(),$R$4)),6,1) | C71: =COUNTIFS('Prospects'!$B$5:$B$504,">="&$B71,'Prospects'!$B$5:$B$504,"<="&EOMONTH($B71,0),'Prospects'!$N$5:$N$504,IF('Tableau de bord'!$G$4="Tous","<>§",'Tableau de bord'!$G$4)) | D71: =COUNTIFS('Saisie'!$A$5:$A$2004,">="&$B71,'Saisie'!$A$5:$A$2004,"<="&EOMONTH($B71,0),'Saisie'!$D$5:$D$2004,"Appel",'Saisie'!$D$5:$D$2004,IF('Tableau de bord'!$G$4="Tous","<>§",'Tableau de bord'!$G$4),'Saisie'!$AU$5:$AU$2004,1) | E71: =COUNTIFS('Saisie'!$A$5:$A$2004,">="&$B71,'Saisie'!$A$5:$A$2004,"<="&EOMONTH($B71,0),'Saisie'!$D$5:$D$2004,"DM",'Saisie'!$D$5:$D$2004,IF('Tableau de bord'!$G$4="Tous","<>§",'Tableau de bord'!$G$4),'Saisie'!$AU$5:$AU$2004,1) | F71: =COUNTIFS('Prospects'!$BG$5:$BG$504,">="&$B71,'Prospects'!$BG$5:$BG$504,"<="&EOMONTH($B71,0),'Prospects'!$N$5:$N$504,IF('Tableau de bord'!$G$4="Tous","<>§",'Tableau de bord'!$G$4)) | G71: =COUNTIFS('Prospects'!$BI$5:$BI$504,">="&$B71,'Prospects'!$BI$5:$BI$504,"<="&EOMONTH($B71,0),'Prospects'!$N$5:$N$504,IF('Tableau de bord'!$G$4="Tous","<>§",'Tableau de bord'!$G$4)) | H71: =SUMIFS('Saisie'!$AW$5:$AW$2004,'Saisie'!$A$5:$A$2004,">="&$B71,'Saisie'!$A$5:$A$2004,"<="&EOMONTH($B71,0),'Saisie'!$E$5:$E$2004,"Signature",'Saisie'!$BA$5:$BA$2004,IF('Tableau de bord'!$G$4="Tous","<>§",'Tableau de bord'!$G$4))+SUMIFS('Saisie'!$AW$5:$AW$2004,'Saisie'!$A$5:$A$2004,">="&$B71,'Saisie'!$A$5:$A$2004,"<="&EOMONTH($B71,0),'Saisie'!$E$5:$E$2004,"Vente additionnelle",'Saisie'!$BA$5:$BA$2004,IF('Tableau de bord'!$G$4="Tous","<>§",'Tableau de bord'!$G$4)) | I71: =SUMIFS('Saisie'!$AW$5:$AW$2004,'Saisie'!$A$5:$A$2004,">="&$B71,'Saisie'!$A$5:$A$2004,"<="&EOMONTH($B71,0),'Saisie'!$E$5:$E$2004,"Paiement reçu",'Saisie'!$BA$5:$BA$2004,IF('Tableau de bord'!$G$4="Tous","<>§",'Tableau de bord'!$G$4)) | J71: =SUMIFS('Saisie'!$AW$5:$AW$2004,'Saisie'!$A$5:$A$2004,">="&$B71,'Saisie'!$A$5:$A$2004,"<="&EOMONTH($B71,0),'Saisie'!$E$5:$E$2004,"Dépense")+SUM('Paramètres'!$AH$6:$AH$12) | K71: =I71-J71
B72: =DATE(YEAR(IF($C$4="Tous",TODAY(),$R$4)),7,1) | C72: =COUNTIFS('Prospects'!$B$5:$B$504,">="&$B72,'Prospects'!$B$5:$B$504,"<="&EOMONTH($B72,0),'Prospects'!$N$5:$N$504,IF('Tableau de bord'!$G$4="Tous","<>§",'Tableau de bord'!$G$4)) | D72: =COUNTIFS('Saisie'!$A$5:$A$2004,">="&$B72,'Saisie'!$A$5:$A$2004,"<="&EOMONTH($B72,0),'Saisie'!$D$5:$D$2004,"Appel",'Saisie'!$D$5:$D$2004,IF('Tableau de bord'!$G$4="Tous","<>§",'Tableau de bord'!$G$4),'Saisie'!$AU$5:$AU$2004,1) | E72: =COUNTIFS('Saisie'!$A$5:$A$2004,">="&$B72,'Saisie'!$A$5:$A$2004,"<="&EOMONTH($B72,0),'Saisie'!$D$5:$D$2004,"DM",'Saisie'!$D$5:$D$2004,IF('Tableau de bord'!$G$4="Tous","<>§",'Tableau de bord'!$G$4),'Saisie'!$AU$5:$AU$2004,1) | F72: =COUNTIFS('Prospects'!$BG$5:$BG$504,">="&$B72,'Prospects'!$BG$5:$BG$504,"<="&EOMONTH($B72,0),'Prospects'!$N$5:$N$504,IF('Tableau de bord'!$G$4="Tous","<>§",'Tableau de bord'!$G$4)) | G72: =COUNTIFS('Prospects'!$BI$5:$BI$504,">="&$B72,'Prospects'!$BI$5:$BI$504,"<="&EOMONTH($B72,0),'Prospects'!$N$5:$N$504,IF('Tableau de bord'!$G$4="Tous","<>§",'Tableau de bord'!$G$4)) | H72: =SUMIFS('Saisie'!$AW$5:$AW$2004,'Saisie'!$A$5:$A$2004,">="&$B72,'Saisie'!$A$5:$A$2004,"<="&EOMONTH($B72,0),'Saisie'!$E$5:$E$2004,"Signature",'Saisie'!$BA$5:$BA$2004,IF('Tableau de bord'!$G$4="Tous","<>§",'Tableau de bord'!$G$4))+SUMIFS('Saisie'!$AW$5:$AW$2004,'Saisie'!$A$5:$A$2004,">="&$B72,'Saisie'!$A$5:$A$2004,"<="&EOMONTH($B72,0),'Saisie'!$E$5:$E$2004,"Vente additionnelle",'Saisie'!$BA$5:$BA$2004,IF('Tableau de bord'!$G$4="Tous","<>§",'Tableau de bord'!$G$4)) | I72: =SUMIFS('Saisie'!$AW$5:$AW$2004,'Saisie'!$A$5:$A$2004,">="&$B72,'Saisie'!$A$5:$A$2004,"<="&EOMONTH($B72,0),'Saisie'!$E$5:$E$2004,"Paiement reçu",'Saisie'!$BA$5:$BA$2004,IF('Tableau de bord'!$G$4="Tous","<>§",'Tableau de bord'!$G$4)) | J72: =SUMIFS('Saisie'!$AW$5:$AW$2004,'Saisie'!$A$5:$A$2004,">="&$B72,'Saisie'!$A$5:$A$2004,"<="&EOMONTH($B72,0),'Saisie'!$E$5:$E$2004,"Dépense")+SUM('Paramètres'!$AH$6:$AH$12) | K72: =I72-J72
B73: =DATE(YEAR(IF($C$4="Tous",TODAY(),$R$4)),8,1) | C73: =COUNTIFS('Prospects'!$B$5:$B$504,">="&$B73,'Prospects'!$B$5:$B$504,"<="&EOMONTH($B73,0),'Prospects'!$N$5:$N$504,IF('Tableau de bord'!$G$4="Tous","<>§",'Tableau de bord'!$G$4)) | D73: =COUNTIFS('Saisie'!$A$5:$A$2004,">="&$B73,'Saisie'!$A$5:$A$2004,"<="&EOMONTH($B73,0),'Saisie'!$D$5:$D$2004,"Appel",'Saisie'!$D$5:$D$2004,IF('Tableau de bord'!$G$4="Tous","<>§",'Tableau de bord'!$G$4),'Saisie'!$AU$5:$AU$2004,1) | E73: =COUNTIFS('Saisie'!$A$5:$A$2004,">="&$B73,'Saisie'!$A$5:$A$2004,"<="&EOMONTH($B73,0),'Saisie'!$D$5:$D$2004,"DM",'Saisie'!$D$5:$D$2004,IF('Tableau de bord'!$G$4="Tous","<>§",'Tableau de bord'!$G$4),'Saisie'!$AU$5:$AU$2004,1) | F73: =COUNTIFS('Prospects'!$BG$5:$BG$504,">="&$B73,'Prospects'!$BG$5:$BG$504,"<="&EOMONTH($B73,0),'Prospects'!$N$5:$N$504,IF('Tableau de bord'!$G$4="Tous","<>§",'Tableau de bord'!$G$4)) | G73: =COUNTIFS('Prospects'!$BI$5:$BI$504,">="&$B73,'Prospects'!$BI$5:$BI$504,"<="&EOMONTH($B73,0),'Prospects'!$N$5:$N$504,IF('Tableau de bord'!$G$4="Tous","<>§",'Tableau de bord'!$G$4)) | H73: =SUMIFS('Saisie'!$AW$5:$AW$2004,'Saisie'!$A$5:$A$2004,">="&$B73,'Saisie'!$A$5:$A$2004,"<="&EOMONTH($B73,0),'Saisie'!$E$5:$E$2004,"Signature",'Saisie'!$BA$5:$BA$2004,IF('Tableau de bord'!$G$4="Tous","<>§",'Tableau de bord'!$G$4))+SUMIFS('Saisie'!$AW$5:$AW$2004,'Saisie'!$A$5:$A$2004,">="&$B73,'Saisie'!$A$5:$A$2004,"<="&EOMONTH($B73,0),'Saisie'!$E$5:$E$2004,"Vente additionnelle",'Saisie'!$BA$5:$BA$2004,IF('Tableau de bord'!$G$4="Tous","<>§",'Tableau de bord'!$G$4)) | I73: =SUMIFS('Saisie'!$AW$5:$AW$2004,'Saisie'!$A$5:$A$2004,">="&$B73,'Saisie'!$A$5:$A$2004,"<="&EOMONTH($B73,0),'Saisie'!$E$5:$E$2004,"Paiement reçu",'Saisie'!$BA$5:$BA$2004,IF('Tableau de bord'!$G$4="Tous","<>§",'Tableau de bord'!$G$4)) | J73: =SUMIFS('Saisie'!$AW$5:$AW$2004,'Saisie'!$A$5:$A$2004,">="&$B73,'Saisie'!$A$5:$A$2004,"<="&EOMONTH($B73,0),'Saisie'!$E$5:$E$2004,"Dépense")+SUM('Paramètres'!$AH$6:$AH$12) | K73: =I73-J73
B74: =DATE(YEAR(IF($C$4="Tous",TODAY(),$R$4)),9,1) | C74: =COUNTIFS('Prospects'!$B$5:$B$504,">="&$B74,'Prospects'!$B$5:$B$504,"<="&EOMONTH($B74,0),'Prospects'!$N$5:$N$504,IF('Tableau de bord'!$G$4="Tous","<>§",'Tableau de bord'!$G$4)) | D74: =COUNTIFS('Saisie'!$A$5:$A$2004,">="&$B74,'Saisie'!$A$5:$A$2004,"<="&EOMONTH($B74,0),'Saisie'!$D$5:$D$2004,"Appel",'Saisie'!$D$5:$D$2004,IF('Tableau de bord'!$G$4="Tous","<>§",'Tableau de bord'!$G$4),'Saisie'!$AU$5:$AU$2004,1) | E74: =COUNTIFS('Saisie'!$A$5:$A$2004,">="&$B74,'Saisie'!$A$5:$A$2004,"<="&EOMONTH($B74,0),'Saisie'!$D$5:$D$2004,"DM",'Saisie'!$D$5:$D$2004,IF('Tableau de bord'!$G$4="Tous","<>§",'Tableau de bord'!$G$4),'Saisie'!$AU$5:$AU$2004,1) | F74: =COUNTIFS('Prospects'!$BG$5:$BG$504,">="&$B74,'Prospects'!$BG$5:$BG$504,"<="&EOMONTH($B74,0),'Prospects'!$N$5:$N$504,IF('Tableau de bord'!$G$4="Tous","<>§",'Tableau de bord'!$G$4)) | G74: =COUNTIFS('Prospects'!$BI$5:$BI$504,">="&$B74,'Prospects'!$BI$5:$BI$504,"<="&EOMONTH($B74,0),'Prospects'!$N$5:$N$504,IF('Tableau de bord'!$G$4="Tous","<>§",'Tableau de bord'!$G$4)) | H74: =SUMIFS('Saisie'!$AW$5:$AW$2004,'Saisie'!$A$5:$A$2004,">="&$B74,'Saisie'!$A$5:$A$2004,"<="&EOMONTH($B74,0),'Saisie'!$E$5:$E$2004,"Signature",'Saisie'!$BA$5:$BA$2004,IF('Tableau de bord'!$G$4="Tous","<>§",'Tableau de bord'!$G$4))+SUMIFS('Saisie'!$AW$5:$AW$2004,'Saisie'!$A$5:$A$2004,">="&$B74,'Saisie'!$A$5:$A$2004,"<="&EOMONTH($B74,0),'Saisie'!$E$5:$E$2004,"Vente additionnelle",'Saisie'!$BA$5:$BA$2004,IF('Tableau de bord'!$G$4="Tous","<>§",'Tableau de bord'!$G$4)) | I74: =SUMIFS('Saisie'!$AW$5:$AW$2004,'Saisie'!$A$5:$A$2004,">="&$B74,'Saisie'!$A$5:$A$2004,"<="&EOMONTH($B74,0),'Saisie'!$E$5:$E$2004,"Paiement reçu",'Saisie'!$BA$5:$BA$2004,IF('Tableau de bord'!$G$4="Tous","<>§",'Tableau de bord'!$G$4)) | J74: =SUMIFS('Saisie'!$AW$5:$AW$2004,'Saisie'!$A$5:$A$2004,">="&$B74,'Saisie'!$A$5:$A$2004,"<="&EOMONTH($B74,0),'Saisie'!$E$5:$E$2004,"Dépense")+SUM('Paramètres'!$AH$6:$AH$12) | K74: =I74-J74
B75: =DATE(YEAR(IF($C$4="Tous",TODAY(),$R$4)),10,1) | C75: =COUNTIFS('Prospects'!$B$5:$B$504,">="&$B75,'Prospects'!$B$5:$B$504,"<="&EOMONTH($B75,0),'Prospects'!$N$5:$N$504,IF('Tableau de bord'!$G$4="Tous","<>§",'Tableau de bord'!$G$4)) | D75: =COUNTIFS('Saisie'!$A$5:$A$2004,">="&$B75,'Saisie'!$A$5:$A$2004,"<="&EOMONTH($B75,0),'Saisie'!$D$5:$D$2004,"Appel",'Saisie'!$D$5:$D$2004,IF('Tableau de bord'!$G$4="Tous","<>§",'Tableau de bord'!$G$4),'Saisie'!$AU$5:$AU$2004,1) | E75: =COUNTIFS('Saisie'!$A$5:$A$2004,">="&$B75,'Saisie'!$A$5:$A$2004,"<="&EOMONTH($B75,0),'Saisie'!$D$5:$D$2004,"DM",'Saisie'!$D$5:$D$2004,IF('Tableau de bord'!$G$4="Tous","<>§",'Tableau de bord'!$G$4),'Saisie'!$AU$5:$AU$2004,1) | F75: =COUNTIFS('Prospects'!$BG$5:$BG$504,">="&$B75,'Prospects'!$BG$5:$BG$504,"<="&EOMONTH($B75,0),'Prospects'!$N$5:$N$504,IF('Tableau de bord'!$G$4="Tous","<>§",'Tableau de bord'!$G$4)) | G75: =COUNTIFS('Prospects'!$BI$5:$BI$504,">="&$B75,'Prospects'!$BI$5:$BI$504,"<="&EOMONTH($B75,0),'Prospects'!$N$5:$N$504,IF('Tableau de bord'!$G$4="Tous","<>§",'Tableau de bord'!$G$4)) | H75: =SUMIFS('Saisie'!$AW$5:$AW$2004,'Saisie'!$A$5:$A$2004,">="&$B75,'Saisie'!$A$5:$A$2004,"<="&EOMONTH($B75,0),'Saisie'!$E$5:$E$2004,"Signature",'Saisie'!$BA$5:$BA$2004,IF('Tableau de bord'!$G$4="Tous","<>§",'Tableau de bord'!$G$4))+SUMIFS('Saisie'!$AW$5:$AW$2004,'Saisie'!$A$5:$A$2004,">="&$B75,'Saisie'!$A$5:$A$2004,"<="&EOMONTH($B75,0),'Saisie'!$E$5:$E$2004,"Vente additionnelle",'Saisie'!$BA$5:$BA$2004,IF('Tableau de bord'!$G$4="Tous","<>§",'Tableau de bord'!$G$4)) | I75: =SUMIFS('Saisie'!$AW$5:$AW$2004,'Saisie'!$A$5:$A$2004,">="&$B75,'Saisie'!$A$5:$A$2004,"<="&EOMONTH($B75,0),'Saisie'!$E$5:$E$2004,"Paiement reçu",'Saisie'!$BA$5:$BA$2004,IF('Tableau de bord'!$G$4="Tous","<>§",'Tableau de bord'!$G$4)) | J75: =SUMIFS('Saisie'!$AW$5:$AW$2004,'Saisie'!$A$5:$A$2004,">="&$B75,'Saisie'!$A$5:$A$2004,"<="&EOMONTH($B75,0),'Saisie'!$E$5:$E$2004,"Dépense")+SUM('Paramètres'!$AH$6:$AH$12) | K75: =I75-J75
B76: =DATE(YEAR(IF($C$4="Tous",TODAY(),$R$4)),11,1) | C76: =COUNTIFS('Prospects'!$B$5:$B$504,">="&$B76,'Prospects'!$B$5:$B$504,"<="&EOMONTH($B76,0),'Prospects'!$N$5:$N$504,IF('Tableau de bord'!$G$4="Tous","<>§",'Tableau de bord'!$G$4)) | D76: =COUNTIFS('Saisie'!$A$5:$A$2004,">="&$B76,'Saisie'!$A$5:$A$2004,"<="&EOMONTH($B76,0),'Saisie'!$D$5:$D$2004,"Appel",'Saisie'!$D$5:$D$2004,IF('Tableau de bord'!$G$4="Tous","<>§",'Tableau de bord'!$G$4),'Saisie'!$AU$5:$AU$2004,1) | E76: =COUNTIFS('Saisie'!$A$5:$A$2004,">="&$B76,'Saisie'!$A$5:$A$2004,"<="&EOMONTH($B76,0),'Saisie'!$D$5:$D$2004,"DM",'Saisie'!$D$5:$D$2004,IF('Tableau de bord'!$G$4="Tous","<>§",'Tableau de bord'!$G$4),'Saisie'!$AU$5:$AU$2004,1) | F76: =COUNTIFS('Prospects'!$BG$5:$BG$504,">="&$B76,'Prospects'!$BG$5:$BG$504,"<="&EOMONTH($B76,0),'Prospects'!$N$5:$N$504,IF('Tableau de bord'!$G$4="Tous","<>§",'Tableau de bord'!$G$4)) | G76: =COUNTIFS('Prospects'!$BI$5:$BI$504,">="&$B76,'Prospects'!$BI$5:$BI$504,"<="&EOMONTH($B76,0),'Prospects'!$N$5:$N$504,IF('Tableau de bord'!$G$4="Tous","<>§",'Tableau de bord'!$G$4)) | H76: =SUMIFS('Saisie'!$AW$5:$AW$2004,'Saisie'!$A$5:$A$2004,">="&$B76,'Saisie'!$A$5:$A$2004,"<="&EOMONTH($B76,0),'Saisie'!$E$5:$E$2004,"Signature",'Saisie'!$BA$5:$BA$2004,IF('Tableau de bord'!$G$4="Tous","<>§",'Tableau de bord'!$G$4))+SUMIFS('Saisie'!$AW$5:$AW$2004,'Saisie'!$A$5:$A$2004,">="&$B76,'Saisie'!$A$5:$A$2004,"<="&EOMONTH($B76,0),'Saisie'!$E$5:$E$2004,"Vente additionnelle",'Saisie'!$BA$5:$BA$2004,IF('Tableau de bord'!$G$4="Tous","<>§",'Tableau de bord'!$G$4)) | I76: =SUMIFS('Saisie'!$AW$5:$AW$2004,'Saisie'!$A$5:$A$2004,">="&$B76,'Saisie'!$A$5:$A$2004,"<="&EOMONTH($B76,0),'Saisie'!$E$5:$E$2004,"Paiement reçu",'Saisie'!$BA$5:$BA$2004,IF('Tableau de bord'!$G$4="Tous","<>§",'Tableau de bord'!$G$4)) | J76: =SUMIFS('Saisie'!$AW$5:$AW$2004,'Saisie'!$A$5:$A$2004,">="&$B76,'Saisie'!$A$5:$A$2004,"<="&EOMONTH($B76,0),'Saisie'!$E$5:$E$2004,"Dépense")+SUM('Paramètres'!$AH$6:$AH$12) | K76: =I76-J76
B77: =DATE(YEAR(IF($C$4="Tous",TODAY(),$R$4)),12,1) | C77: =COUNTIFS('Prospects'!$B$5:$B$504,">="&$B77,'Prospects'!$B$5:$B$504,"<="&EOMONTH($B77,0),'Prospects'!$N$5:$N$504,IF('Tableau de bord'!$G$4="Tous","<>§",'Tableau de bord'!$G$4)) | D77: =COUNTIFS('Saisie'!$A$5:$A$2004,">="&$B77,'Saisie'!$A$5:$A$2004,"<="&EOMONTH($B77,0),'Saisie'!$D$5:$D$2004,"Appel",'Saisie'!$D$5:$D$2004,IF('Tableau de bord'!$G$4="Tous","<>§",'Tableau de bord'!$G$4),'Saisie'!$AU$5:$AU$2004,1) | E77: =COUNTIFS('Saisie'!$A$5:$A$2004,">="&$B77,'Saisie'!$A$5:$A$2004,"<="&EOMONTH($B77,0),'Saisie'!$D$5:$D$2004,"DM",'Saisie'!$D$5:$D$2004,IF('Tableau de bord'!$G$4="Tous","<>§",'Tableau de bord'!$G$4),'Saisie'!$AU$5:$AU$2004,1) | F77: =COUNTIFS('Prospects'!$BG$5:$BG$504,">="&$B77,'Prospects'!$BG$5:$BG$504,"<="&EOMONTH($B77,0),'Prospects'!$N$5:$N$504,IF('Tableau de bord'!$G$4="Tous","<>§",'Tableau de bord'!$G$4)) | G77: =COUNTIFS('Prospects'!$BI$5:$BI$504,">="&$B77,'Prospects'!$BI$5:$BI$504,"<="&EOMONTH($B77,0),'Prospects'!$N$5:$N$504,IF('Tableau de bord'!$G$4="Tous","<>§",'Tableau de bord'!$G$4)) | H77: =SUMIFS('Saisie'!$AW$5:$AW$2004,'Saisie'!$A$5:$A$2004,">="&$B77,'Saisie'!$A$5:$A$2004,"<="&EOMONTH($B77,0),'Saisie'!$E$5:$E$2004,"Signature",'Saisie'!$BA$5:$BA$2004,IF('Tableau de bord'!$G$4="Tous","<>§",'Tableau de bord'!$G$4))+SUMIFS('Saisie'!$AW$5:$AW$2004,'Saisie'!$A$5:$A$2004,">="&$B77,'Saisie'!$A$5:$A$2004,"<="&EOMONTH($B77,0),'Saisie'!$E$5:$E$2004,"Vente additionnelle",'Saisie'!$BA$5:$BA$2004,IF('Tableau de bord'!$G$4="Tous","<>§",'Tableau de bord'!$G$4)) | I77: =SUMIFS('Saisie'!$AW$5:$AW$2004,'Saisie'!$A$5:$A$2004,">="&$B77,'Saisie'!$A$5:$A$2004,"<="&EOMONTH($B77,0),'Saisie'!$E$5:$E$2004,"Paiement reçu",'Saisie'!$BA$5:$BA$2004,IF('Tableau de bord'!$G$4="Tous","<>§",'Tableau de bord'!$G$4)) | J77: =SUMIFS('Saisie'!$AW$5:$AW$2004,'Saisie'!$A$5:$A$2004,">="&$B77,'Saisie'!$A$5:$A$2004,"<="&EOMONTH($B77,0),'Saisie'!$E$5:$E$2004,"Dépense")+SUM('Paramètres'!$AH$6:$AH$12) | K77: =I77-J77
B78: 🏆 Record | C78: =MAX(C66:C77) | D78: =MAX(D66:D77) | E78: =MAX(E66:E77) | F78: =MAX(F66:F77) | G78: =MAX(G66:G77) | H78: =MAX(H66:H77) | I78: =MAX(I66:I77) | J78: =MAX(J66:J77) | K78: =MAX(K66:K77)
B79: Meilleur mois | C79: =IF(C78=0,"",INDEX($B$66:$B$77,MATCH(C78,C66:C77,0))) | D79: =IF(D78=0,"",INDEX($B$66:$B$77,MATCH(D78,D66:D77,0))) | E79: =IF(E78=0,"",INDEX($B$66:$B$77,MATCH(E78,E66:E77,0))) | F79: =IF(F78=0,"",INDEX($B$66:$B$77,MATCH(F78,F66:F77,0))) | G79: =IF(G78=0,"",INDEX($B$66:$B$77,MATCH(G78,G66:G77,0))) | H79: =IF(H78=0,"",INDEX($B$66:$B$77,MATCH(H78,H66:H77,0))) | I79: =IF(I78=0,"",INDEX($B$66:$B$77,MATCH(I78,I66:I77,0))) | J79: =IF(J78=0,"",INDEX($B$66:$B$77,MATCH(J78,J66:J77,0))) | K79: =IF(K78=0,"",INDEX($B$66:$B$77,MATCH(K78,K66:K77,0)))
B97: 🔍 ANALYSES POUR DÉCIDER (période choisie)
B98: Meilleurs créneaux d'appel | G98: Meilleurs jours d'appel
B99: Créneau | C99: Appels | D99: Réponses | E99: Taux | G99: Jour | H99: Appels | I99: Réponses | J99: Taux
B100: 8h - 10h | C100: =COUNTIFS('Saisie'!$A$5:$A$2004,">="&$R$4,'Saisie'!$A$5:$A$2004,"<="&$S$4,'Saisie'!$D$5:$D$2004,"Appel",'Saisie'!$AU$5:$AU$2004,1,'Saisie'!$AY$5:$AY$2004,">=8",'Saisie'!$AY$5:$AY$2004,"<10") | D100: =COUNTIFS('Saisie'!$A$5:$A$2004,">="&$R$4,'Saisie'!$A$5:$A$2004,"<="&$S$4,'Saisie'!$D$5:$D$2004,"Appel",'Saisie'!$AU$5:$AU$2004,1,'Saisie'!$AY$5:$AY$2004,">=8",'Saisie'!$AY$5:$AY$2004,"<10",'Saisie'!$AV$5:$AV$2004,1) | E100: =IFERROR(D100/C100,0) | G100: Lundi | H100: =COUNTIFS('Saisie'!$A$5:$A$2004,">="&$R$4,'Saisie'!$A$5:$A$2004,"<="&$S$4,'Saisie'!$D$5:$D$2004,"Appel",'Saisie'!$AU$5:$AU$2004,1,'Saisie'!$AZ$5:$AZ$2004,1) | I100: =COUNTIFS('Saisie'!$A$5:$A$2004,">="&$R$4,'Saisie'!$A$5:$A$2004,"<="&$S$4,'Saisie'!$D$5:$D$2004,"Appel",'Saisie'!$AU$5:$AU$2004,1,'Saisie'!$AZ$5:$AZ$2004,1,'Saisie'!$AV$5:$AV$2004,1) | J100: =IFERROR(I100/H100,0)
B101: 10h - 12h | C101: =COUNTIFS('Saisie'!$A$5:$A$2004,">="&$R$4,'Saisie'!$A$5:$A$2004,"<="&$S$4,'Saisie'!$D$5:$D$2004,"Appel",'Saisie'!$AU$5:$AU$2004,1,'Saisie'!$AY$5:$AY$2004,">=10",'Saisie'!$AY$5:$AY$2004,"<12") | D101: =COUNTIFS('Saisie'!$A$5:$A$2004,">="&$R$4,'Saisie'!$A$5:$A$2004,"<="&$S$4,'Saisie'!$D$5:$D$2004,"Appel",'Saisie'!$AU$5:$AU$2004,1,'Saisie'!$AY$5:$AY$2004,">=10",'Saisie'!$AY$5:$AY$2004,"<12",'Saisie'!$AV$5:$AV$2004,1) | E101: =IFERROR(D101/C101,0) | G101: Mardi | H101: =COUNTIFS('Saisie'!$A$5:$A$2004,">="&$R$4,'Saisie'!$A$5:$A$2004,"<="&$S$4,'Saisie'!$D$5:$D$2004,"Appel",'Saisie'!$AU$5:$AU$2004,1,'Saisie'!$AZ$5:$AZ$2004,2) | I101: =COUNTIFS('Saisie'!$A$5:$A$2004,">="&$R$4,'Saisie'!$A$5:$A$2004,"<="&$S$4,'Saisie'!$D$5:$D$2004,"Appel",'Saisie'!$AU$5:$AU$2004,1,'Saisie'!$AZ$5:$AZ$2004,2,'Saisie'!$AV$5:$AV$2004,1) | J101: =IFERROR(I101/H101,0)
B102: 12h - 14h | C102: =COUNTIFS('Saisie'!$A$5:$A$2004,">="&$R$4,'Saisie'!$A$5:$A$2004,"<="&$S$4,'Saisie'!$D$5:$D$2004,"Appel",'Saisie'!$AU$5:$AU$2004,1,'Saisie'!$AY$5:$AY$2004,">=12",'Saisie'!$AY$5:$AY$2004,"<14") | D102: =COUNTIFS('Saisie'!$A$5:$A$2004,">="&$R$4,'Saisie'!$A$5:$A$2004,"<="&$S$4,'Saisie'!$D$5:$D$2004,"Appel",'Saisie'!$AU$5:$AU$2004,1,'Saisie'!$AY$5:$AY$2004,">=12",'Saisie'!$AY$5:$AY$2004,"<14",'Saisie'!$AV$5:$AV$2004,1) | E102: =IFERROR(D102/C102,0) | G102: Mercredi | H102: =COUNTIFS('Saisie'!$A$5:$A$2004,">="&$R$4,'Saisie'!$A$5:$A$2004,"<="&$S$4,'Saisie'!$D$5:$D$2004,"Appel",'Saisie'!$AU$5:$AU$2004,1,'Saisie'!$AZ$5:$AZ$2004,3) | I102: =COUNTIFS('Saisie'!$A$5:$A$2004,">="&$R$4,'Saisie'!$A$5:$A$2004,"<="&$S$4,'Saisie'!$D$5:$D$2004,"Appel",'Saisie'!$AU$5:$AU$2004,1,'Saisie'!$AZ$5:$AZ$2004,3,'Saisie'!$AV$5:$AV$2004,1) | J102: =IFERROR(I102/H102,0)
B103: 14h - 16h | C103: =COUNTIFS('Saisie'!$A$5:$A$2004,">="&$R$4,'Saisie'!$A$5:$A$2004,"<="&$S$4,'Saisie'!$D$5:$D$2004,"Appel",'Saisie'!$AU$5:$AU$2004,1,'Saisie'!$AY$5:$AY$2004,">=14",'Saisie'!$AY$5:$AY$2004,"<16") | D103: =COUNTIFS('Saisie'!$A$5:$A$2004,">="&$R$4,'Saisie'!$A$5:$A$2004,"<="&$S$4,'Saisie'!$D$5:$D$2004,"Appel",'Saisie'!$AU$5:$AU$2004,1,'Saisie'!$AY$5:$AY$2004,">=14",'Saisie'!$AY$5:$AY$2004,"<16",'Saisie'!$AV$5:$AV$2004,1) | E103: =IFERROR(D103/C103,0) | G103: Jeudi | H103: =COUNTIFS('Saisie'!$A$5:$A$2004,">="&$R$4,'Saisie'!$A$5:$A$2004,"<="&$S$4,'Saisie'!$D$5:$D$2004,"Appel",'Saisie'!$AU$5:$AU$2004,1,'Saisie'!$AZ$5:$AZ$2004,4) | I103: =COUNTIFS('Saisie'!$A$5:$A$2004,">="&$R$4,'Saisie'!$A$5:$A$2004,"<="&$S$4,'Saisie'!$D$5:$D$2004,"Appel",'Saisie'!$AU$5:$AU$2004,1,'Saisie'!$AZ$5:$AZ$2004,4,'Saisie'!$AV$5:$AV$2004,1) | J103: =IFERROR(I103/H103,0)
B104: 16h - 18h | C104: =COUNTIFS('Saisie'!$A$5:$A$2004,">="&$R$4,'Saisie'!$A$5:$A$2004,"<="&$S$4,'Saisie'!$D$5:$D$2004,"Appel",'Saisie'!$AU$5:$AU$2004,1,'Saisie'!$AY$5:$AY$2004,">=16",'Saisie'!$AY$5:$AY$2004,"<18") | D104: =COUNTIFS('Saisie'!$A$5:$A$2004,">="&$R$4,'Saisie'!$A$5:$A$2004,"<="&$S$4,'Saisie'!$D$5:$D$2004,"Appel",'Saisie'!$AU$5:$AU$2004,1,'Saisie'!$AY$5:$AY$2004,">=16",'Saisie'!$AY$5:$AY$2004,"<18",'Saisie'!$AV$5:$AV$2004,1) | E104: =IFERROR(D104/C104,0) | G104: Vendredi | H104: =COUNTIFS('Saisie'!$A$5:$A$2004,">="&$R$4,'Saisie'!$A$5:$A$2004,"<="&$S$4,'Saisie'!$D$5:$D$2004,"Appel",'Saisie'!$AU$5:$AU$2004,1,'Saisie'!$AZ$5:$AZ$2004,5) | I104: =COUNTIFS('Saisie'!$A$5:$A$2004,">="&$R$4,'Saisie'!$A$5:$A$2004,"<="&$S$4,'Saisie'!$D$5:$D$2004,"Appel",'Saisie'!$AU$5:$AU$2004,1,'Saisie'!$AZ$5:$AZ$2004,5,'Saisie'!$AV$5:$AV$2004,1) | J104: =IFERROR(I104/H104,0)
B105: 18h - 21h | C105: =COUNTIFS('Saisie'!$A$5:$A$2004,">="&$R$4,'Saisie'!$A$5:$A$2004,"<="&$S$4,'Saisie'!$D$5:$D$2004,"Appel",'Saisie'!$AU$5:$AU$2004,1,'Saisie'!$AY$5:$AY$2004,">=18",'Saisie'!$AY$5:$AY$2004,"<21") | D105: =COUNTIFS('Saisie'!$A$5:$A$2004,">="&$R$4,'Saisie'!$A$5:$A$2004,"<="&$S$4,'Saisie'!$D$5:$D$2004,"Appel",'Saisie'!$AU$5:$AU$2004,1,'Saisie'!$AY$5:$AY$2004,">=18",'Saisie'!$AY$5:$AY$2004,"<21",'Saisie'!$AV$5:$AV$2004,1) | E105: =IFERROR(D105/C105,0) | G105: Samedi | H105: =COUNTIFS('Saisie'!$A$5:$A$2004,">="&$R$4,'Saisie'!$A$5:$A$2004,"<="&$S$4,'Saisie'!$D$5:$D$2004,"Appel",'Saisie'!$AU$5:$AU$2004,1,'Saisie'!$AZ$5:$AZ$2004,6) | I105: =COUNTIFS('Saisie'!$A$5:$A$2004,">="&$R$4,'Saisie'!$A$5:$A$2004,"<="&$S$4,'Saisie'!$D$5:$D$2004,"Appel",'Saisie'!$AU$5:$AU$2004,1,'Saisie'!$AZ$5:$AZ$2004,6,'Saisie'!$AV$5:$AV$2004,1) | J105: =IFERROR(I105/H105,0)
B108: Accroches et modèles de message (test A/B) | H108: Objections et motifs de perte
B109: Modèle | D109: Envois | E109: Réponses | F109: Taux | H109: Objection | J109: Nombre | K109: Part
B110: =INDEX('Paramètres'!$AA$6:$AA$14,1)&"" | D110: =IF($B110="","",COUNTIFS('Saisie'!$A$5:$A$2004,">="&$R$4,'Saisie'!$A$5:$A$2004,"<="&$S$4,'Saisie'!$M$5:$M$2004,$B110,'Saisie'!$AU$5:$AU$2004,1)) | E110: =IF($B110="","",COUNTIFS('Saisie'!$A$5:$A$2004,">="&$R$4,'Saisie'!$A$5:$A$2004,"<="&$S$4,'Saisie'!$M$5:$M$2004,$B110,'Saisie'!$AU$5:$AU$2004,1,'Saisie'!$AV$5:$AV$2004,1)) | F110: =IFERROR(E110/D110,0) | H110: =INDEX('Paramètres'!$Y$6:$Y$17,1)&"" | J110: =IF($H110="","",COUNTIFS('Saisie'!$A$5:$A$2004,">="&$R$4,'Saisie'!$A$5:$A$2004,"<="&$S$4,'Saisie'!$L$5:$L$2004,$H110)) | K110: =IFERROR(J110/SUM($J$110:$J$117),0)
B111: =INDEX('Paramètres'!$AA$6:$AA$14,2)&"" | D111: =IF($B111="","",COUNTIFS('Saisie'!$A$5:$A$2004,">="&$R$4,'Saisie'!$A$5:$A$2004,"<="&$S$4,'Saisie'!$M$5:$M$2004,$B111,'Saisie'!$AU$5:$AU$2004,1)) | E111: =IF($B111="","",COUNTIFS('Saisie'!$A$5:$A$2004,">="&$R$4,'Saisie'!$A$5:$A$2004,"<="&$S$4,'Saisie'!$M$5:$M$2004,$B111,'Saisie'!$AU$5:$AU$2004,1,'Saisie'!$AV$5:$AV$2004,1)) | F111: =IFERROR(E111/D111,0) | H111: =INDEX('Paramètres'!$Y$6:$Y$17,2)&"" | J111: =IF($H111="","",COUNTIFS('Saisie'!$A$5:$A$2004,">="&$R$4,'Saisie'!$A$5:$A$2004,"<="&$S$4,'Saisie'!$L$5:$L$2004,$H111)) | K111: =IFERROR(J111/SUM($J$110:$J$117),0)
B112: =INDEX('Paramètres'!$AA$6:$AA$14,3)&"" | D112: =IF($B112="","",COUNTIFS('Saisie'!$A$5:$A$2004,">="&$R$4,'Saisie'!$A$5:$A$2004,"<="&$S$4,'Saisie'!$M$5:$M$2004,$B112,'Saisie'!$AU$5:$AU$2004,1)) | E112: =IF($B112="","",COUNTIFS('Saisie'!$A$5:$A$2004,">="&$R$4,'Saisie'!$A$5:$A$2004,"<="&$S$4,'Saisie'!$M$5:$M$2004,$B112,'Saisie'!$AU$5:$AU$2004,1,'Saisie'!$AV$5:$AV$2004,1)) | F112: =IFERROR(E112/D112,0) | H112: =INDEX('Paramètres'!$Y$6:$Y$17,3)&"" | J112: =IF($H112="","",COUNTIFS('Saisie'!$A$5:$A$2004,">="&$R$4,'Saisie'!$A$5:$A$2004,"<="&$S$4,'Saisie'!$L$5:$L$2004,$H112)) | K112: =IFERROR(J112/SUM($J$110:$J$117),0)
B113: =INDEX('Paramètres'!$AA$6:$AA$14,4)&"" | D113: =IF($B113="","",COUNTIFS('Saisie'!$A$5:$A$2004,">="&$R$4,'Saisie'!$A$5:$A$2004,"<="&$S$4,'Saisie'!$M$5:$M$2004,$B113,'Saisie'!$AU$5:$AU$2004,1)) | E113: =IF($B113="","",COUNTIFS('Saisie'!$A$5:$A$2004,">="&$R$4,'Saisie'!$A$5:$A$2004,"<="&$S$4,'Saisie'!$M$5:$M$2004,$B113,'Saisie'!$AU$5:$AU$2004,1,'Saisie'!$AV$5:$AV$2004,1)) | F113: =IFERROR(E113/D113,0) | H113: =INDEX('Paramètres'!$Y$6:$Y$17,4)&"" | J113: =IF($H113="","",COUNTIFS('Saisie'!$A$5:$A$2004,">="&$R$4,'Saisie'!$A$5:$A$2004,"<="&$S$4,'Saisie'!$L$5:$L$2004,$H113)) | K113: =IFERROR(J113/SUM($J$110:$J$117),0)
B114: =INDEX('Paramètres'!$AA$6:$AA$14,5)&"" | D114: =IF($B114="","",COUNTIFS('Saisie'!$A$5:$A$2004,">="&$R$4,'Saisie'!$A$5:$A$2004,"<="&$S$4,'Saisie'!$M$5:$M$2004,$B114,'Saisie'!$AU$5:$AU$2004,1)) | E114: =IF($B114="","",COUNTIFS('Saisie'!$A$5:$A$2004,">="&$R$4,'Saisie'!$A$5:$A$2004,"<="&$S$4,'Saisie'!$M$5:$M$2004,$B114,'Saisie'!$AU$5:$AU$2004,1,'Saisie'!$AV$5:$AV$2004,1)) | F114: =IFERROR(E114/D114,0) | H114: =INDEX('Paramètres'!$Y$6:$Y$17,5)&"" | J114: =IF($H114="","",COUNTIFS('Saisie'!$A$5:$A$2004,">="&$R$4,'Saisie'!$A$5:$A$2004,"<="&$S$4,'Saisie'!$L$5:$L$2004,$H114)) | K114: =IFERROR(J114/SUM($J$110:$J$117),0)
H115: =INDEX('Paramètres'!$Y$6:$Y$17,6)&"" | J115: =IF($H115="","",COUNTIFS('Saisie'!$A$5:$A$2004,">="&$R$4,'Saisie'!$A$5:$A$2004,"<="&$S$4,'Saisie'!$L$5:$L$2004,$H115)) | K115: =IFERROR(J115/SUM($J$110:$J$117),0)
H116: =INDEX('Paramètres'!$Y$6:$Y$17,7)&"" | J116: =IF($H116="","",COUNTIFS('Saisie'!$A$5:$A$2004,">="&$R$4,'Saisie'!$A$5:$A$2004,"<="&$S$4,'Saisie'!$L$5:$L$2004,$H116)) | K116: =IFERROR(J116/SUM($J$110:$J$117),0)
H117: =INDEX('Paramètres'!$Y$6:$Y$17,8)&"" | J117: =IF($H117="","",COUNTIFS('Saisie'!$A$5:$A$2004,">="&$R$4,'Saisie'!$A$5:$A$2004,"<="&$S$4,'Saisie'!$L$5:$L$2004,$H117)) | K117: =IFERROR(J117/SUM($J$110:$J$117),0)
B120: Secteurs qui signent le plus | I120: Vitesse et production
B121: Secteur | D121: Prospects | E121: Clients | F121: Taux | G121: CA signé | I121: Cycle de vente moyen (jours) | M121: =IFERROR(AVERAGE('Prospects'!$AU$5:$AU$504),0)
B122: =INDEX('Paramètres'!$V$6:$V$20,1)&"" | D122: =IF($B122="","",COUNTIFS('Prospects'!$BW$5:$BW$504,1,'Prospects'!$S$5:$S$504,$B122)) | E122: =IF($B122="","",COUNTIFS('Prospects'!$BW$5:$BW$504,1,'Prospects'!$S$5:$S$504,$B122,'Prospects'!$BA$5:$BA$504,7)) | F122: =IFERROR(E122/D122,0) | G122: =IF($B122="","",SUMIFS('Clients'!$O$5:$O$154,'Clients'!$H$5:$H$154,$B122)) | I122: Jours pour passer à Contacté | M122: =IFERROR(AVERAGE('Prospects'!$BJ$5:$BJ$504),0)
B123: =INDEX('Paramètres'!$V$6:$V$20,2)&"" | D123: =IF($B123="","",COUNTIFS('Prospects'!$BW$5:$BW$504,1,'Prospects'!$S$5:$S$504,$B123)) | E123: =IF($B123="","",COUNTIFS('Prospects'!$BW$5:$BW$504,1,'Prospects'!$S$5:$S$504,$B123,'Prospects'!$BA$5:$BA$504,7)) | F123: =IFERROR(E123/D123,0) | G123: =IF($B123="","",SUMIFS('Clients'!$O$5:$O$154,'Clients'!$H$5:$H$154,$B123)) | I123: Jours Contacté → Qualifié | M123: =IFERROR(AVERAGE('Prospects'!$BK$5:$BK$504),0)
B124: =INDEX('Paramètres'!$V$6:$V$20,3)&"" | D124: =IF($B124="","",COUNTIFS('Prospects'!$BW$5:$BW$504,1,'Prospects'!$S$5:$S$504,$B124)) | E124: =IF($B124="","",COUNTIFS('Prospects'!$BW$5:$BW$504,1,'Prospects'!$S$5:$S$504,$B124,'Prospects'!$BA$5:$BA$504,7)) | F124: =IFERROR(E124/D124,0) | G124: =IF($B124="","",SUMIFS('Clients'!$O$5:$O$154,'Clients'!$H$5:$H$154,$B124)) | I124: Jours Qualifié → Audit/Démo | M124: =IFERROR(AVERAGE('Prospects'!$BL$5:$BL$504),0)
B125: =INDEX('Paramètres'!$V$6:$V$20,4)&"" | D125: =IF($B125="","",COUNTIFS('Prospects'!$BW$5:$BW$504,1,'Prospects'!$S$5:$S$504,$B125)) | E125: =IF($B125="","",COUNTIFS('Prospects'!$BW$5:$BW$504,1,'Prospects'!$S$5:$S$504,$B125,'Prospects'!$BA$5:$BA$504,7)) | F125: =IFERROR(E125/D125,0) | G125: =IF($B125="","",SUMIFS('Clients'!$O$5:$O$154,'Clients'!$H$5:$H$154,$B125)) | I125: Jours Audit/Démo → RDV | M125: =IFERROR(AVERAGE('Prospects'!$BM$5:$BM$504),0)
B126: =INDEX('Paramètres'!$V$6:$V$20,5)&"" | D126: =IF($B126="","",COUNTIFS('Prospects'!$BW$5:$BW$504,1,'Prospects'!$S$5:$S$504,$B126)) | E126: =IF($B126="","",COUNTIFS('Prospects'!$BW$5:$BW$504,1,'Prospects'!$S$5:$S$504,$B126,'Prospects'!$BA$5:$BA$504,7)) | F126: =IFERROR(E126/D126,0) | G126: =IF($B126="","",SUMIFS('Clients'!$O$5:$O$154,'Clients'!$H$5:$H$154,$B126)) | I126: Jours RDV → Proposition | M126: =IFERROR(AVERAGE('Prospects'!$BN$5:$BN$504),0)
B127: =INDEX('Paramètres'!$V$6:$V$20,6)&"" | D127: =IF($B127="","",COUNTIFS('Prospects'!$BW$5:$BW$504,1,'Prospects'!$S$5:$S$504,$B127)) | E127: =IF($B127="","",COUNTIFS('Prospects'!$BW$5:$BW$504,1,'Prospects'!$S$5:$S$504,$B127,'Prospects'!$BA$5:$BA$504,7)) | F127: =IFERROR(E127/D127,0) | G127: =IF($B127="","",SUMIFS('Clients'!$O$5:$O$154,'Clients'!$H$5:$H$154,$B127)) | I127: Jours Proposition → Gagné | M127: =IFERROR(AVERAGE('Prospects'!$BO$5:$BO$504),0)
B128: =INDEX('Paramètres'!$V$6:$V$20,7)&"" | D128: =IF($B128="","",COUNTIFS('Prospects'!$BW$5:$BW$504,1,'Prospects'!$S$5:$S$504,$B128)) | E128: =IF($B128="","",COUNTIFS('Prospects'!$BW$5:$BW$504,1,'Prospects'!$S$5:$S$504,$B128,'Prospects'!$BA$5:$BA$504,7)) | F128: =IFERROR(E128/D128,0) | G128: =IF($B128="","",SUMIFS('Clients'!$O$5:$O$154,'Clients'!$H$5:$H$154,$B128)) | I128: Temps moyen par audit (min) | M128: =IFERROR(AVERAGEIFS('Saisie'!$H$5:$H$2004,'Saisie'!$E$5:$E$2004,"Audit réalisé"),0)
B129: =INDEX('Paramètres'!$V$6:$V$20,8)&"" | D129: =IF($B129="","",COUNTIFS('Prospects'!$BW$5:$BW$504,1,'Prospects'!$S$5:$S$504,$B129)) | E129: =IF($B129="","",COUNTIFS('Prospects'!$BW$5:$BW$504,1,'Prospects'!$S$5:$S$504,$B129,'Prospects'!$BA$5:$BA$504,7)) | F129: =IFERROR(E129/D129,0) | G129: =IF($B129="","",SUMIFS('Clients'!$O$5:$O$154,'Clients'!$H$5:$H$154,$B129)) | I129: Note moyenne d'audit (/100) | M129: =IFERROR(AVERAGEIFS('Saisie'!$N$5:$N$2004,'Saisie'!$E$5:$E$2004,"Audit réalisé"),0)
B130: =INDEX('Paramètres'!$V$6:$V$20,9)&"" | D130: =IF($B130="","",COUNTIFS('Prospects'!$BW$5:$BW$504,1,'Prospects'!$S$5:$S$504,$B130)) | E130: =IF($B130="","",COUNTIFS('Prospects'!$BW$5:$BW$504,1,'Prospects'!$S$5:$S$504,$B130,'Prospects'!$BA$5:$BA$504,7)) | F130: =IFERROR(E130/D130,0) | G130: =IF($B130="","",SUMIFS('Clients'!$O$5:$O$154,'Clients'!$H$5:$H$154,$B130)) | I130: Taux d'ouverture des Loom | M130: =IFERROR(COUNTIFS('Saisie'!$E$5:$E$2004,"Loom envoyé",'Saisie'!$F$5:$F$2004,"Loom vu")/COUNTIFS('Saisie'!$E$5:$E$2004,"Loom envoyé"),0)
B131: =INDEX('Paramètres'!$V$6:$V$20,10)&"" | D131: =IF($B131="","",COUNTIFS('Prospects'!$BW$5:$BW$504,1,'Prospects'!$S$5:$S$504,$B131)) | E131: =IF($B131="","",COUNTIFS('Prospects'!$BW$5:$BW$504,1,'Prospects'!$S$5:$S$504,$B131,'Prospects'!$BA$5:$BA$504,7)) | F131: =IFERROR(E131/D131,0) | G131: =IF($B131="","",SUMIFS('Clients'!$O$5:$O$154,'Clients'!$H$5:$H$154,$B131)) | I131: Clients venus par recommandation | M131: =COUNTIFS('Clients'!$J$5:$J$154,"?*")
I132: Satisfaction moyenne (/10) | M132: =IFERROR(AVERAGEIFS('Saisie'!$N$5:$N$2004,'Saisie'!$E$5:$E$2004,"Satisfaction client"),0)

Sheet Prospects
A1: =HYPERLINK("#'Saisie'!A1","↩ Saisie") | B1: 👥 PROSPECTS — automatique
A2: 100 % automatique : une ligne par prospect, construite depuis la Saisie. Étape, score, relance (séquence J+2 / J+5 / J+10) et alertes se calculent seuls. Tu peux filtrer et lire, pas modifier. Pour changer quelque chose, ajoute une ligne dans Saisie.
A3: SUIVI | J3: CONTACT | S3: FICHE | AI3: QUALIFICATION | AN3: VENTE | BA3: CALCULS
A4: ID | B4: Date d'ajout | C4: Entreprise | D4: Étape | E4: Score priorité | F4: Alerte | G4: Prochaine relance | H4: Heure de rappel | I4: Prochaine action | J4: Contact | K4: Téléphone | L4: WhatsApp | M4: Instagram | N4: Canal principal | O4: Tentatives | P4: Réponses | Q4: Dernière action | R4: Jours sans action | S4: Secteur | T4: Ville | U4: Zone | V4: Fonction | W4: Site internet | X4: Source | Y4: Recommandé par | Z4: Pub active | AA4: Date pub | AB4: Budget pub | AC4: Présence Google | AD4: Note Google | AE4: Nb avis | AF4: Taille | AG4: Concurrent | AH4: Standard | AI4: Budget OK | AJ4: Décideur | AK4: Besoin | AL4: Délai | AM4: Qualif. (/4) | AN4: Offre | AO4: Abonnement (€/mois) | AP4: Montant proposé | AQ4: Date proposition | AR4: Expiration proposition | AS4: Pipeline pondéré | AT4: Date signature | AU4: Cycle de vente (j) | AV4: Dernière objection / motif | AW4: Date perte | AX4: À recontacter le | AY4: Temps passé (min) | AZ4: Démo type du secteur | BA4: Niveau (1-7) | BB4: N° WhatsApp | BC4: Compte Insta | BD4: Date Contacté | BE4: Date Qualifié | BF4: Date Audit/Démo | BG4: Date RDV | BH4: Date Proposition | BI4: Date Gagné | BJ4: Jours → Contacté | BK4: Jours → Qualifié | BL4: Jours → Audit/Démo | BM4: Jours → RDV | BN4: Jours → Proposition | BO4: Jours → Gagné | BP4: Ligne relance | BQ4: Dernière ligne | BR4: Ligne perdu | BS4: Ligne progrès | BT4: Tri priorité | BU4: Rang relance | BV4: Rang alerte | BW4: Dans filtre | BX4: Rang client
A5: =IF(C5="","","P-"&TEXT(1,"000")) | B5: =IF(C5="","",IFERROR(1/(1/_xlfn.MINIFS('Saisie'!$A$5:$A$2004,'Saisie'!$C$5:$C$2004,C5)),"")) | C5: =IFERROR(INDEX('Saisie'!$C$5:$C$2004,MATCH(1,'Saisie'!$AX$5:$AX$2004,0)),"") | D5: =IF(C5="","",IF(AND(BR5>0,BR5>BS5,BA5<7),"Perdu",INDEX('Paramètres'!$F$6:$F$13,BA5))) | E5: =IF(C5="","",MIN(100,(Z5="Oui")*'Paramètres'!$B$38+(AB5="Régulière")*'Paramètres'!$B$39+IF(AND(N(AA5)>0,TODAY()-N(AA5)<=30),'Paramètres'!$B$40,0)+(W5="")*'Paramètres'!$B$41+(AC5="Absente")*'Paramètres'!$B$42+(AC5="Faible")*'Paramètres'!$B$43+IF(AND(N(AD5)>0,N(AD5)<4),'Paramètres'!$B$44,0)+(AF5="Moyenne")*'Paramètres'!$B$45+(AF5="Grande")*'Paramètres'!$B$46+(Y5<>"")*'Paramètres'!$B$47)) | F5: =IF(C5="","",IF(D5="Gagné","",IF(D5="Perdu",IF(AND(AX5<>"",AX5<=TODAY()),"À recontacter (perdu)",""),IF(AND(O5>='Paramètres'!$B$21,P5=0),"Stop : "&'Paramètres'!$B$21&" tentatives sans réponse",IF(AND(D5="Proposition",AR5<>"",TODAY()>N(AR5)),"Proposition expirée",IF(AND(D5="Proposition",N(R5)>='Paramètres'!$B$25),"Proposition sans réponse",IF(AND(G5<>"",N(G5)<TODAY()),"Relance en retard",IF(N(R5)>='Paramètres'!$B$24,"Sans action depuis "&R5&" j","")))))))) | G5: =IF(OR(C5="",D5="Gagné",D5="Perdu"),"",IF(AND(BP5>0,BP5=BQ5),INDEX('Saisie'!$J$5:$J$2004,BP5-4),IF(OR(O5=0,AND(O5>='Paramètres'!$B$21,P5=0)),"",Q5+IF(O5<=1,'Paramètres'!$B$18,IF(O5=2,'Paramètres'!$B$19,'Paramètres'!$B$20))))) | H5: =IF(OR(G5="",BP5<>BQ5),"",IF(INDEX('Saisie'!$K$5:$K$2004,BP5-4)="","",INDEX('Saisie'!$K$5:$K$2004,BP5-4))) | I5: =IF(C5="","",IF(OR(D5="Gagné",D5="Perdu"),"",IFERROR(INDEX('Saisie'!$I$5:$I$2004,_xlfn.MAXIFS('Saisie'!$AS$5:$AS$2004,'Saisie'!$C$5:$C$2004,C5,'Saisie'!$I$5:$I$2004,"<>")-4),""))) | J5: =IF(C5="","",IFERROR(INDEX('Saisie'!$U$5:$U$2004,_xlfn.MAXIFS('Saisie'!$AS$5:$AS$2004,'Saisie'!$C$5:$C$2004,C5,'Saisie'!$U$5:$U$2004,"<>")-4),"")) | K5: =IF(C5="","",IFERROR(INDEX('Saisie'!$W$5:$W$2004,_xlfn.MAXIFS('Saisie'!$AS$5:$AS$2004,'Saisie'!$C$5:$C$2004,C5,'Saisie'!$W$5:$W$2004,"<>")-4),"")) | L5: =IF(IF(BB5<>"",BB5,K5)="","",HYPERLINK("https://wa.me/"&IF(LEFT(SUBSTITUTE(SUBSTITUTE(SUBSTITUTE(IF(BB5<>"",BB5,K5)," ",""),".",""),"+",""),1)="0",'Paramètres'!$B$35&MID(SUBSTITUTE(SUBSTITUTE(SUBSTITUTE(IF(BB5<>"",BB5,K5)," ",""),".",""),"+",""),2,20),SUBSTITUTE(SUBSTITUTE(SUBSTITUTE(IF(BB5<>"",BB5,K5)," ",""),".",""),"+","")),"WhatsApp")) | M5: =IF(BC5="","",HYPERLINK(IF(LEFT(BC5,4)="http",BC5,"https://www.instagram.com/"&SUBSTITUTE(SUBSTITUTE(BC5,"@","")," ","")),BC5)) | N5: =IF(C5="","",IFERROR(INDEX('Saisie'!$D$5:$D$2004,_xlfn.MINIFS('Saisie'!$AS$5:$AS$2004,'Saisie'!$C$5:$C$2004,C5,'Saisie'!$AU$5:$AU$2004,1)-4),IFERROR(INDEX('Saisie'!$D$5:$D$2004,_xlfn.MINIFS('Saisie'!$AS$5:$AS$2004,'Saisie'!$C$5:$C$2004,C5,'Saisie'!$D$5:$D$2004,"<>")-4),""))) | O5: =IF(C5="","",COUNTIFS('Saisie'!$C$5:$C$2004,C5,'Saisie'!$AU$5:$AU$2004,1)) | P5: =IF(C5="","",COUNTIFS('Saisie'!$C$5:$C$2004,C5,'Saisie'!$AV$5:$AV$2004,1)) | Q5: =IF(C5="","",IFERROR(1/(1/_xlfn.MAXIFS('Saisie'!$A$5:$A$2004,'Saisie'!$C$5:$C$2004,C5)),"")) | R5: =IF(C5="","",IF(Q5="","",TODAY()-Q5)) | S5: =IF(C5="","",IFERROR(INDEX('Saisie'!$R$5:$R$2004,_xlfn.MAXIFS('Saisie'!$AS$5:$AS$2004,'Saisie'!$C$5:$C$2004,C5,'Saisie'!$R$5:$R$2004,"<>")-4),"")) | T5: =IF(C5="","",IFERROR(INDEX('Saisie'!$S$5:$S$2004,_xlfn.MAXIFS('Saisie'!$AS$5:$AS$2004,'Saisie'!$C$5:$C$2004,C5,'Saisie'!$S$5:$S$2004,"<>")-4),"")) | U5: =IF(C5="","",IFERROR(INDEX('Saisie'!$T$5:$T$2004,_xlfn.MAXIFS('Saisie'!$AS$5:$AS$2004,'Saisie'!$C$5:$C$2004,C5,'Saisie'!$T$5:$T$2004,"<>")-4),"")) | V5: =IF(C5="","",IFERROR(INDEX('Saisie'!$V$5:$V$2004,_xlfn.MAXIFS('Saisie'!$AS$5:$AS$2004,'Saisie'!$C$5:$C$2004,C5,'Saisie'!$V$5:$V$2004,"<>")-4),"")) | W5: =IF(C5="","",IFERROR(INDEX('Saisie'!$Z$5:$Z$2004,_xlfn.MAXIFS('Saisie'!$AS$5:$AS$2004,'Saisie'!$C$5:$C$2004,C5,'Saisie'!$Z$5:$Z$2004,"<>")-4),"")) | X5: =IF(C5="","",IFERROR(INDEX('Saisie'!$AA$5:$AA$2004,_xlfn.MAXIFS('Saisie'!$AS$5:$AS$2004,'Saisie'!$C$5:$C$2004,C5,'Saisie'!$AA$5:$AA$2004,"<>")-4),"")) | Y5: =IF(C5="","",IFERROR(INDEX('Saisie'!$AB$5:$AB$2004,_xlfn.MAXIFS('Saisie'!$AS$5:$AS$2004,'Saisie'!$C$5:$C$2004,C5,'Saisie'!$AB$5:$AB$2004,"<>")-4),"")) | Z5: =IF(C5="","",IFERROR(INDEX('Saisie'!$AC$5:$AC$2004,_xlfn.MAXIFS('Saisie'!$AS$5:$AS$2004,'Saisie'!$C$5:$C$2004,C5,'Saisie'!$AC$5:$AC$2004,"<>")-4),"")) | AA5: =IF(C5="","",IFERROR(INDEX('Saisie'!$AD$5:$AD$2004,_xlfn.MAXIFS('Saisie'!$AS$5:$AS$2004,'Saisie'!$C$5:$C$2004,C5,'Saisie'!$AD$5:$AD$2004,"<>")-4),"")) | AB5: =IF(C5="","",IFERROR(INDEX('Saisie'!$AE$5:$AE$2004,_xlfn.MAXIFS('Saisie'!$AS$5:$AS$2004,'Saisie'!$C$5:$C$2004,C5,'Saisie'!$AE$5:$AE$2004,"<>")-4),"")) | AC5: =IF(C5="","",IFERROR(INDEX('Saisie'!$AF$5:$AF$2004,_xlfn.MAXIFS('Saisie'!$AS$5:$AS$2004,'Saisie'!$C$5:$C$2004,C5,'Saisie'!$AF$5:$AF$2004,"<>")-4),"")) | AD5: =IF(C5="","",IFERROR(INDEX('Saisie'!$AG$5:$AG$2004,_xlfn.MAXIFS('Saisie'!$AS$5:$AS$2004,'Saisie'!$C$5:$C$2004,C5,'Saisie'!$AG$5:$AG$2004,"<>")-4),"")) | AE5: =IF(C5="","",IFERROR(INDEX('Saisie'!$AH$5:$AH$2004,_xlfn.MAXIFS('Saisie'!$AS$5:$AS$2004,'Saisie'!$C$5:$C$2004,C5,'Saisie'!$AH$5:$AH$2004,"<>")-4),"")) | AF5: =IF(C5="","",IFERROR(INDEX('Saisie'!$AI$5:$AI$2004,_xlfn.MAXIFS('Saisie'!$AS$5:$AS$2004,'Saisie'!$C$5:$C$2004,C5,'Saisie'!$AI$5:$AI$2004,"<>")-4),"")) | AG5: =IF(C5="","",IFERROR(INDEX('Saisie'!$AJ$5:$AJ$2004,_xlfn.MAXIFS('Saisie'!$AS$5:$AS$2004,'Saisie'!$C$5:$C$2004,C5,'Saisie'!$AJ$5:$AJ$2004,"<>")-4),"")) | AH5: =IF(C5="","",IFERROR(INDEX('Saisie'!$AK$5:$AK$2004,_xlfn.MAXIFS('Saisie'!$AS$5:$AS$2004,'Saisie'!$C$5:$C$2004,C5,'Saisie'!$AK$5:$AK$2004,"<>")-4),"")) | AI5: =IF(C5="","",IFERROR(INDEX('Saisie'!$AN$5:$AN$2004,_xlfn.MAXIFS('Saisie'!$AS$5:$AS$2004,'Saisie'!$C$5:$C$2004,C5,'Saisie'!$AN$5:$AN$2004,"<>")-4),"")) | AJ5: =IF(C5="","",IFERROR(INDEX('Saisie'!$AO$5:$AO$2004,_xlfn.MAXIFS('Saisie'!$AS$5:$AS$2004,'Saisie'!$C$5:$C$2004,C5,'Saisie'!$AO$5:$AO$2004,"<>")-4),"")) | AK5: =IF(C5="","",IFERROR(INDEX('Saisie'!$AP$5:$AP$2004,_xlfn.MAXIFS('Saisie'!$AS$5:$AS$2004,'Saisie'!$C$5:$C$2004,C5,'Saisie'!$AP$5:$AP$2004,"<>")-4),"")) | AL5: =IF(C5="","",IFERROR(INDEX('Saisie'!$AQ$5:$AQ$2004,_xlfn.MAXIFS('Saisie'!$AS$5:$AS$2004,'Saisie'!$C$5:$C$2004,C5,'Saisie'!$AQ$5:$AQ$2004,"<>")-4),"")) | AM5: =IF(C5="","",((AI5="Oui")+(AJ5="Oui")+(AK5="Oui")+OR(AL5="Immédiat",AL5="< 1 mois"))&"/4") | AN5: =IF(C5="","",IFERROR(INDEX('Saisie'!$AL$5:$AL$2004,_xlfn.MAXIFS('Saisie'!$AS$5:$AS$2004,'Saisie'!$C$5:$C$2004,C5,'Saisie'!$AL$5:$AL$2004,"<>")-4),"")) | AO5: =IF(C5="","",IF(IFERROR(INDEX('Saisie'!$AM$5:$AM$2004,_xlfn.MAXIFS('Saisie'!$AS$5:$AS$2004,'Saisie'!$C$5:$C$2004,C5,'Saisie'!$AM$5:$AM$2004,"<>")-4),"")<>"",IFERROR(INDEX('Saisie'!$AM$5:$AM$2004,_xlfn.MAXIFS('Saisie'!$AS$5:$AS$2004,'Saisie'!$C$5:$C$2004,C5,'Saisie'!$AM$5:$AM$2004,"<>")-4),""),IFERROR(INDEX('Paramètres'!$S$6:$S$15,MATCH(AN5,'Paramètres'!$Q$6:$Q$15,0)),""))) | AP5: =IF(C5="","",IFERROR(INDEX('Saisie'!$AW$5:$AW$2004,_xlfn.MAXIFS('Saisie'!$AS$5:$AS$2004,'Saisie'!$C$5:$C$2004,C5,'Saisie'!$E$5:$E$2004,"Proposition envoyée")-4),"")) | AQ5: =IF(C5="","",IFERROR(1/(1/_xlfn.MAXIFS('Saisie'!$A$5:$A$2004,'Saisie'!$C$5:$C$2004,C5,'Saisie'!$E$5:$E$2004,"Proposition envoyée")),"")) | AR5: =IF(C5="","",IF(AQ5="","",AQ5+'Paramètres'!$B$26)) | AS5: =IF(OR(C5="",D5="Gagné",D5="Perdu"),0,N(AP5)*IFERROR(INDEX('Paramètres'!$G$6:$G$13,MATCH(D5,'Paramètres'!$F$6:$F$13,0)),0)) | AT5: =IF(C5="","",IFERROR(1/(1/_xlfn.MINIFS('Saisie'!$A$5:$A$2004,'Saisie'!$C$5:$C$2004,C5,'Saisie'!$E$5:$E$2004,"Signature")),"")) | AU5: =IF(C5="","",IF(OR(AT5="",B5=""),"",AT5-B5)) | AV5: =IF(C5="","",IFERROR(INDEX('Saisie'!$L$5:$L$2004,_xlfn.MAXIFS('Saisie'!$AS$5:$AS$2004,'Saisie'!$C$5:$C$2004,C5,'Saisie'!$L$5:$L$2004,"<>")-4),"")) | AW5: =IF(C5="","",IF(D5<>"Perdu","",IFERROR(1/(1/_xlfn.MAXIFS('Saisie'!$A$5:$A$2004,'Saisie'!$C$5:$C$2004,C5,'Saisie'!$E$5:$E$2004,"Perdu")),""))) | AX5: =IF(C5="","",IF(AW5="","",AW5+'Paramètres'!$B$28)) | AY5: =IF(C5="","",SUMIFS('Saisie'!$H$5:$H$2004,'Saisie'!$C$5:$C$2004,C5)) | AZ5: =IF(C5="","",IFERROR(INDEX('Paramètres'!$W$6:$W$20,MATCH(S5,'Paramètres'!$V$6:$V$20,0))&"","")) | BA5: =IF(C5="","",MAX(1,_xlfn.MAXIFS('Saisie'!$AT$5:$AT$2004,'Saisie'!$C$5:$C$2004,C5))) | BB5: =IF(C5="","",IFERROR(INDEX('Saisie'!$X$5:$X$2004,_xlfn.MAXIFS('Saisie'!$AS$5:$AS$2004,'Saisie'!$C$5:$C$2004,C5,'Saisie'!$X$5:$X$2004,"<>")-4),"")) | BC5: =IF(C5="","",IFERROR(INDEX('Saisie'!$Y$5:$Y$2004,_xlfn.MAXIFS('Saisie'!$AS$5:$AS$2004,'Saisie'!$C$5:$C$2004,C5,'Saisie'!$Y$5:$Y$2004,"<>")-4),"")) | BD5: =IF(C5="","",IFERROR(1/(1/_xlfn.MINIFS('Saisie'!$A$5:$A$2004,'Saisie'!$C$5:$C$2004,C5,'Saisie'!$AT$5:$AT$2004,">=2")),"")) | BE5: =IF(C5="","",IFERROR(1/(1/_xlfn.MINIFS('Saisie'!$A$5:$A$2004,'Saisie'!$C$5:$C$2004,C5,'Saisie'!$AT$5:$AT$2004,">=3")),"")) | BF5: =IF(C5="","",IFERROR(1/(1/_xlfn.MINIFS('Saisie'!$A$5:$A$2004,'Saisie'!$C$5:$C$2004,C5,'Saisie'!$AT$5:$AT$2004,">=4")),"")) | BG5: =IF(C5="","",IFERROR(1/(1/_xlfn.MINIFS('Saisie'!$A$5:$A$2004,'Saisie'!$C$5:$C$2004,C5,'Saisie'!$AT$5:$AT$2004,">=5")),"")) | BH5: =IF(C5="","",IFERROR(1/(1/_xlfn.MINIFS('Saisie'!$A$5:$A$2004,'Saisie'!$C$5:$C$2004,C5,'Saisie'!$AT$5:$AT$2004,">=6")),"")) | BI5: =IF(C5="","",IFERROR(1/(1/_xlfn.MINIFS('Saisie'!$A$5:$A$2004,'Saisie'!$C$5:$C$2004,C5,'Saisie'!$AT$5:$AT$2004,">=7")),"")) | BJ5: =IF(OR(BD5="",B5=""),"",BD5-B5) | BK5: =IF(OR(BE5="",BD5=""),"",BE5-BD5) | BL5: =IF(OR(BF5="",BE5=""),"",BF5-BE5) | BM5: =IF(OR(BG5="",BF5=""),"",BG5-BF5) | BN5: =IF(OR(BH5="",BG5=""),"",BH5-BG5) | BO5: =IF(OR(BI5="",BH5=""),"",BI5-BH5) | BP5: =IF(C5="","",_xlfn.MAXIFS('Saisie'!$AS$5:$AS$2004,'Saisie'!$C$5:$C$2004,C5,'Saisie'!$J$5:$J$2004,"<>")) | BQ5: =IF(C5="","",_xlfn.MAXIFS('Saisie'!$AS$5:$AS$2004,'Saisie'!$C$5:$C$2004,C5)) | BR5: =IF(C5="","",_xlfn.MAXIFS('Saisie'!$AS$5:$AS$2004,'Saisie'!$C$5:$C$2004,C5,'Saisie'!$E$5:$E$2004,"Perdu")) | BS5: =IF(C5="","",_xlfn.MAXIFS('Saisie'!$AS$5:$AS$2004,'Saisie'!$C$5:$C$2004,C5,'Saisie'!$AT$5:$AT$2004,">0")) | BT5: =IF(AND(C5<>"",OR(D5="Nouveau",D5="Contacté",D5="Qualifié"),OR(G5="",N(G5)<=TODAY()),NOT(AND(O5>='Paramètres'!$B$21,P5=0))),E5+1/10000,"") | BU5: =IF(AND(G5<>"",N(G5)<=TODAY()),MAX($BU$4:BU4)+1,"") | BV5: =IF(AND(F5<>"",F5<>"Relance en retard"),MAX($BV$4:BV4)+1,"") | BW5: =IF(C5="","",IF(AND(B5>='Tableau de bord'!$R$4,B5<='Tableau de bord'!$S$4,OR('Tableau de bord'!$G$4="Tous",N5='Tableau de bord'!$G$4)),1,0)) | BX5: =IF(AND(C5<>"",N(BA5)=7),MAX($BX$4:BX4)+1,"")
A6: =IF(C6="","","P-"&TEXT(2,"000")) | B6: =IF(C6="","",IFERROR(1/(1/_xlfn.MINIFS('Saisie'!$A$5:$A$2004,'Saisie'!$C$5:$C$2004,C6)),"")) | C6: =IFERROR(INDEX('Saisie'!$C$5:$C$2004,MATCH(2,'Saisie'!$AX$5:$AX$2004,0)),"") | D6: =IF(C6="","",IF(AND(BR6>0,BR6>BS6,BA6<7),"Perdu",INDEX('Paramètres'!$F$6:$F$13,BA6))) | E6: =IF(C6="","",MIN(100,(Z6="Oui")*'Paramètres'!$B$38+(AB6="Régulière")*'Paramètres'!$B$39+IF(AND(N(AA6)>0,TODAY()-N(AA6)<=30),'Paramètres'!$B$40,0)+(W6="")*'Paramètres'!$B$41+(AC6="Absente")*'Paramètres'!$B$42+(AC6="Faible")*'Paramètres'!$B$43+IF(AND(N(AD6)>0,N(AD6)<4),'Paramètres'!$B$44,0)+(AF6="Moyenne")*'Paramètres'!$B$45+(AF6="Grande")*'Paramètres'!$B$46+(Y6<>"")*'Paramètres'!$B$47)) | F6: =IF(C6="","",IF(D6="Gagné","",IF(D6="Perdu",IF(AND(AX6<>"",AX6<=TODAY()),"À recontacter (perdu)",""),IF(AND(O6>='Paramètres'!$B$21,P6=0),"Stop : "&'Paramètres'!$B$21&" tentatives sans réponse",IF(AND(D6="Proposition",AR6<>"",TODAY()>N(AR6)),"Proposition expirée",IF(AND(D6="Proposition",N(R6)>='Paramètres'!$B$25),"Proposition sans réponse",IF(AND(G6<>"",N(G6)<TODAY()),"Relance en retard",IF(N(R6)>='Paramètres'!$B$24,"Sans action depuis "&R6&" j","")))))))) | G6: =IF(OR(C6="",D6="Gagné",D6="Perdu"),"",IF(AND(BP6>0,BP6=BQ6),INDEX('Saisie'!$J$5:$J$2004,BP6-4),IF(OR(O6=0,AND(O6>='Paramètres'!$B$21,P6=0)),"",Q6+IF(O6<=1,'Paramètres'!$B$18,IF(O6=2,'Paramètres'!$B$19,'Paramètres'!$B$20))))) | H6: =IF(OR(G6="",BP6<>BQ6),"",IF(INDEX('Saisie'!$K$5:$K$2004,BP6-4)="","",INDEX('Saisie'!$K$5:$K$2004,BP6-4))) | I6: =IF(C6="","",IF(OR(D6="Gagné",D6="Perdu"),"",IFERROR(INDEX('Saisie'!$I$5:$I$2004,_xlfn.MAXIFS('Saisie'!$AS$5:$AS$2004,'Saisie'!$C$5:$C$2004,C6,'Saisie'!$I$5:$I$2004,"<>")-4),""))) | J6: =IF(C6="","",IFERROR(INDEX('Saisie'!$U$5:$U$2004,_xlfn.MAXIFS('Saisie'!$AS$5:$AS$2004,'Saisie'!$C$5:$C$2004,C6,'Saisie'!$U$5:$U$2004,"<>")-4),"")) | K6: =IF(C6="","",IFERROR(INDEX('Saisie'!$W$5:$W$2004,_xlfn.MAXIFS('Saisie'!$AS$5:$AS$2004,'Saisie'!$C$5:$C$2004,C6,'Saisie'!$W$5:$W$2004,"<>")-4),"")) | L6: =IF(IF(BB6<>"",BB6,K6)="","",HYPERLINK("https://wa.me/"&IF(LEFT(SUBSTITUTE(SUBSTITUTE(SUBSTITUTE(IF(BB6<>"",BB6,K6)," ",""),".",""),"+",""),1)="0",'Paramètres'!$B$35&MID(SUBSTITUTE(SUBSTITUTE(SUBSTITUTE(IF(BB6<>"",BB6,K6)," ",""),".",""),"+",""),2,20),SUBSTITUTE(SUBSTITUTE(SUBSTITUTE(IF(BB6<>"",BB6,K6)," ",""),".",""),"+","")),"WhatsApp")) | M6: =IF(BC6="","",HYPERLINK(IF(LEFT(BC6,4)="http",BC6,"https://www.instagram.com/"&SUBSTITUTE(SUBSTITUTE(BC6,"@","")," ","")),BC6)) | N6: =IF(C6="","",IFERROR(INDEX('Saisie'!$D$5:$D$2004,_xlfn.MINIFS('Saisie'!$AS$5:$AS$2004,'Saisie'!$C$5:$C$2004,C6,'Saisie'!$AU$5:$AU$2004,1)-4),IFERROR(INDEX('Saisie'!$D$5:$D$2004,_xlfn.MINIFS('Saisie'!$AS$5:$AS$2004,'Saisie'!$C$5:$C$2004,C6,'Saisie'!$D$5:$D$2004,"<>")-4),""))) | O6: =IF(C6="","",COUNTIFS('Saisie'!$C$5:$C$2004,C6,'Saisie'!$AU$5:$AU$2004,1)) | P6: =IF(C6="","",COUNTIFS('Saisie'!$C$5:$C$2004,C6,'Saisie'!$AV$5:$AV$2004,1)) | Q6: =IF(C6="","",IFERROR(1/(1/_xlfn.MAXIFS('Saisie'!$A$5:$A$2004,'Saisie'!$C$5:$C$2004,C6)),"")) | R6: =IF(C6="","",IF(Q6="","",TODAY()-Q6)) | S6: =IF(C6="","",IFERROR(INDEX('Saisie'!$R$5:$R$2004,_xlfn.MAXIFS('Saisie'!$AS$5:$AS$2004,'Saisie'!$C$5:$C$2004,C6,'Saisie'!$R$5:$R$2004,"<>")-4),"")) | T6: =IF(C6="","",IFERROR(INDEX('Saisie'!$S$5:$S$2004,_xlfn.MAXIFS('Saisie'!$AS$5:$AS$2004,'Saisie'!$C$5:$C$2004,C6,'Saisie'!$S$5:$S$2004,"<>")-4),"")) | U6: =IF(C6="","",IFERROR(INDEX('Saisie'!$T$5:$T$2004,_xlfn.MAXIFS('Saisie'!$AS$5:$AS$2004,'Saisie'!$C$5:$C$2004,C6,'Saisie'!$T$5:$T$2004,"<>")-4),"")) | V6: =IF(C6="","",IFERROR(INDEX('Saisie'!$V$5:$V$2004,_xlfn.MAXIFS('Saisie'!$AS$5:$AS$2004,'Saisie'!$C$5:$C$2004,C6,'Saisie'!$V$5:$V$2004,"<>")-4),"")) | W6: =IF(C6="","",IFERROR(INDEX('Saisie'!$Z$5:$Z$2004,_xlfn.MAXIFS('Saisie'!$AS$5:$AS$2004,'Saisie'!$C$5:$C$2004,C6,'Saisie'!$Z$5:$Z$2004,"<>")-4),"")) | X6: =IF(C6="","",IFERROR(INDEX('Saisie'!$AA$5:$AA$2004,_xlfn.MAXIFS('Saisie'!$AS$5:$AS$2004,'Saisie'!$C$5:$C$2004,C6,'Saisie'!$AA$5:$AA$2004,"<>")-4),"")) | Y6: =IF(C6="","",IFERROR(INDEX('Saisie'!$AB$5:$AB$2004,_xlfn.MAXIFS('Saisie'!$AS$5:$AS$2004,'Saisie'!$C$5:$C$2004,C6,'Saisie'!$AB$5:$AB$2004,"<>")-4),"")) | Z6: =IF(C6="","",IFERROR(INDEX('Saisie'!$AC$5:$AC$2004,_xlfn.MAXIFS('Saisie'!$AS$5:$AS$2004,'Saisie'!$C$5:$C$2004,C6,'Saisie'!$AC$5:$AC$2004,"<>")-4),"")) | AA6: =IF(C6="","",IFERROR(INDEX('Saisie'!$AD$5:$AD$2004,_xlfn.MAXIFS('Saisie'!$AS$5:$AS$2004,'Saisie'!$C$5:$C$2004,C6,'Saisie'!$AD$5:$AD$2004,"<>")-4),"")) | AB6: =IF(C6="","",IFERROR(INDEX('Saisie'!$AE$5:$AE$2004,_xlfn.MAXIFS('Saisie'!$AS$5:$AS$2004,'Saisie'!$C$5:$C$2004,C6,'Saisie'!$AE$5:$AE$2004,"<>")-4),"")) | AC6: =IF(C6="","",IFERROR(INDEX('Saisie'!$AF$5:$AF$2004,_xlfn.MAXIFS('Saisie'!$AS$5:$AS$2004,'Saisie'!$C$5:$C$2004,C6,'Saisie'!$AF$5:$AF$2004,"<>")-4),"")) | AD6: =IF(C6="","",IFERROR(INDEX('Saisie'!$AG$5:$AG$2004,_xlfn.MAXIFS('Saisie'!$AS$5:$AS$2004,'Saisie'!$C$5:$C$2004,C6,'Saisie'!$AG$5:$AG$2004,"<>")-4),"")) | AE6: =IF(C6="","",IFERROR(INDEX('Saisie'!$AH$5:$AH$2004,_xlfn.MAXIFS('Saisie'!$AS$5:$AS$2004,'Saisie'!$C$5:$C$2004,C6,'Saisie'!$AH$5:$AH$2004,"<>")-4),"")) | AF6: =IF(C6="","",IFERROR(INDEX('Saisie'!$AI$5:$AI$2004,_xlfn.MAXIFS('Saisie'!$AS$5:$AS$2004,'Saisie'!$C$5:$C$2004,C6,'Saisie'!$AI$5:$AI$2004,"<>")-4),"")) | AG6: =IF(C6="","",IFERROR(INDEX('Saisie'!$AJ$5:$AJ$2004,_xlfn.MAXIFS('Saisie'!$AS$5:$AS$2004,'Saisie'!$C$5:$C$2004,C6,'Saisie'!$AJ$5:$AJ$2004,"<>")-4),"")) | AH6: =IF(C6="","",IFERROR(INDEX('Saisie'!$AK$5:$AK$2004,_xlfn.MAXIFS('Saisie'!$AS$5:$AS$2004,'Saisie'!$C$5:$C$2004,C6,'Saisie'!$AK$5:$AK$2004,"<>")-4),"")) | AI6: =IF(C6="","",IFERROR(INDEX('Saisie'!$AN$5:$AN$2004,_xlfn.MAXIFS('Saisie'!$AS$5:$AS$2004,'Saisie'!$C$5:$C$2004,C6,'Saisie'!$AN$5:$AN$2004,"<>")-4),"")) | AJ6: =IF(C6="","",IFERROR(INDEX('Saisie'!$AO$5:$AO$2004,_xlfn.MAXIFS('Saisie'!$AS$5:$AS$2004,'Saisie'!$C$5:$C$2004,C6,'Saisie'!$AO$5:$AO$2004,"<>")-4),"")) | AK6: =IF(C6="","",IFERROR(INDEX('Saisie'!$AP$5:$AP$2004,_xlfn.MAXIFS('Saisie'!$AS$5:$AS$2004,'Saisie'!$C$5:$C$2004,C6,'Saisie'!$AP$5:$AP$2004,"<>")-4),"")) | AL6: =IF(C6="","",IFERROR(INDEX('Saisie'!$AQ$5:$AQ$2004,_xlfn.MAXIFS('Saisie'!$AS$5:$AS$2004,'Saisie'!$C$5:$C$2004,C6,'Saisie'!$AQ$5:$AQ$2004,"<>")-4),"")) | AM6: =IF(C6="","",((AI6="Oui")+(AJ6="Oui")+(AK6="Oui")+OR(AL6="Immédiat",AL6="< 1 mois"))&"/4") | AN6: =IF(C6="","",IFERROR(INDEX('Saisie'!$AL$5:$AL$2004,_xlfn.MAXIFS('Saisie'!$AS$5:$AS$2004,'Saisie'!$C$5:$C$2004,C6,'Saisie'!$AL$5:$AL$2004,"<>")-4),"")) | AO6: =IF(C6="","",IF(IFERROR(INDEX('Saisie'!$AM$5:$AM$2004,_xlfn.MAXIFS('Saisie'!$AS$5:$AS$2004,'Saisie'!$C$5:$C$2004,C6,'Saisie'!$AM$5:$AM$2004,"<>")-4),"")<>"",IFERROR(INDEX('Saisie'!$AM$5:$AM$2004,_xlfn.MAXIFS('Saisie'!$AS$5:$AS$2004,'Saisie'!$C$5:$C$2004,C6,'Saisie'!$AM$5:$AM$2004,"<>")-4),""),IFERROR(INDEX('Paramètres'!$S$6:$S$15,MATCH(AN6,'Paramètres'!$Q$6:$Q$15,0)),""))) | AP6: =IF(C6="","",IFERROR(INDEX('Saisie'!$AW$5:$AW$2004,_xlfn.MAXIFS('Saisie'!$AS$5:$AS$2004,'Saisie'!$C$5:$C$2004,C6,'Saisie'!$E$5:$E$2004,"Proposition envoyée")-4),"")) | AQ6: =IF(C6="","",IFERROR(1/(1/_xlfn.MAXIFS('Saisie'!$A$5:$A$2004,'Saisie'!$C$5:$C$2004,C6,'Saisie'!$E$5:$E$2004,"Proposition envoyée")),"")) | AR6: =IF(C6="","",IF(AQ6="","",AQ6+'Paramètres'!$B$26)) | AS6: =IF(OR(C6="",D6="Gagné",D6="Perdu"),0,N(AP6)*IFERROR(INDEX('Paramètres'!$G$6:$G$13,MATCH(D6,'Paramètres'!$F$6:$F$13,0)),0)) | AT6: =IF(C6="","",IFERROR(1/(1/_xlfn.MINIFS('Saisie'!$A$5:$A$2004,'Saisie'!$C$5:$C$2004,C6,'Saisie'!$E$5:$E$2004,"Signature")),"")) | AU6: =IF(C6="","",IF(OR(AT6="",B6=""),"",AT6-B6)) | AV6: =IF(C6="","",IFERROR(INDEX('Saisie'!$L$5:$L$2004,_xlfn.MAXIFS('Saisie'!$AS$5:$AS$2004,'Saisie'!$C$5:$C$2004,C6,'Saisie'!$L$5:$L$2004,"<>")-4),"")) | AW6: =IF(C6="","",IF(D6<>"Perdu","",IFERROR(1/(1/_xlfn.MAXIFS('Saisie'!$A$5:$A$2004,'Saisie'!$C$5:$C$2004,C6,'Saisie'!$E$5:$E$2004,"Perdu")),""))) | AX6: =IF(C6="","",IF(AW6="","",AW6+'Paramètres'!$B$28)) | AY6: =IF(C6="","",SUMIFS('Saisie'!$H$5:$H$2004,'Saisie'!$C$5:$C$2004,C6)) | AZ6: =IF(C6="","",IFERROR(INDEX('Paramètres'!$W$6:$W$20,MATCH(S6,'Paramètres'!$V$6:$V$20,0))&"","")) | BA6: =IF(C6="","",MAX(1,_xlfn.MAXIFS('Saisie'!$AT$5:$AT$2004,'Saisie'!$C$5:$C$2004,C6))) | BB6: =IF(C6="","",IFERROR(INDEX('Saisie'!$X$5:$X$2004,_xlfn.MAXIFS('Saisie'!$AS$5:$AS$2004,'Saisie'!$C$5:$C$2004,C6,'Saisie'!$X$5:$X$2004,"<>")-4),"")) | BC6: =IF(C6="","",IFERROR(INDEX('Saisie'!$Y$5:$Y$2004,_xlfn.MAXIFS('Saisie'!$AS$5:$AS$2004,'Saisie'!$C$5:$C$2004,C6,'Saisie'!$Y$5:$Y$2004,"<>")-4),"")) | BD6: =IF(C6="","",IFERROR(1/(1/_xlfn.MINIFS('Saisie'!$A$5:$A$2004,'Saisie'!$C$5:$C$2004,C6,'Saisie'!$AT$5:$AT$2004,">=2")),"")) | BE6: =IF(C6="","",IFERROR(1/(1/_xlfn.MINIFS('Saisie'!$A$5:$A$2004,'Saisie'!$C$5:$C$2004,C6,'Saisie'!$AT$5:$AT$2004,">=3")),"")) | BF6: =IF(C6="","",IFERROR(1/(1/_xlfn.MINIFS('Saisie'!$A$5:$A$2004,'Saisie'!$C$5:$C$2004,C6,'Saisie'!$AT$5:$AT$2004,">=4")),"")) | BG6: =IF(C6="","",IFERROR(1/(1/_xlfn.MINIFS('Saisie'!$A$5:$A$2004,'Saisie'!$C$5:$C$2004,C6,'Saisie'!$AT$5:$AT$2004,">=5")),"")) | BH6: =IF(C6="","",IFERROR(1/(1/_xlfn.MINIFS('Saisie'!$A$5:$A$2004,'Saisie'!$C$5:$C$2004,C6,'Saisie'!$AT$5:$AT$2004,">=6")),"")) | BI6: =IF(C6="","",IFERROR(1/(1/_xlfn.MINIFS('Saisie'!$A$5:$A$2004,'Saisie'!$C$5:$C$2004,C6,'Saisie'!$AT$5:$AT$2004,">=7")),"")) | BJ6: =IF(OR(BD6="",B6=""),"",BD6-B6) | BK6: =IF(OR(BE6="",BD6=""),"",BE6-BD6) | BL6: =IF(OR(BF6="",BE6=""),"",BF6-BE6) | BM6: =IF(OR(BG6="",BF6=""),"",BG6-BF6) | BN6: =IF(OR(BH6="",BG6=""),"",BH6-BG6) | BO6: =IF(OR(BI6="",BH6=""),"",BI6-BH6) | BP6: =IF(C6="","",_xlfn.MAXIFS('Saisie'!$AS$5:$AS$2004,'Saisie'!$C$5:$C$2004,C6,'Saisie'!$J$5:$J$2004,"<>")) | BQ6: =IF(C6="","",_xlfn.MAXIFS('Saisie'!$AS$5:$AS$2004,'Saisie'!$C$5:$C$2004,C6)) | BR6: =IF(C6="","",_xlfn.MAXIFS('Saisie'!$AS$5:$AS$2004,'Saisie'!$C$5:$C$2004,C6,'Saisie'!$E$5:$E$2004,"Perdu")) | BS6: =IF(C6="","",_xlfn.MAXIFS('Saisie'!$AS$5:$AS$2004,'Saisie'!$C$5:$C$2004,C6,'Saisie'!$AT$5:$AT$2004,">0")) | BT6: =IF(AND(C6<>"",OR(D6="Nouveau",D6="Contacté",D6="Qualifié"),OR(G6="",N(G6)<=TODAY()),NOT(AND(O6>='Paramètres'!$B$21,P6=0))),E6+2/10000,"") | BU6: =IF(AND(G6<>"",N(G6)<=TODAY()),MAX($BU$4:BU5)+1,"") | BV6: =IF(AND(F6<>"",F6<>"Relance en retard"),MAX($BV$4:BV5)+1,"") | BW6: =IF(C6="","",IF(AND(B6>='Tableau de bord'!$R$4,B6<='Tableau de bord'!$S$4,OR('Tableau de bord'!$G$4="Tous",N6='Tableau de bord'!$G$4)),1,0)) | BX6: =IF(AND(C6<>"",N(BA6)=7),MAX($BX$4:BX5)+1,"")
A7: =IF(C7="","","P-"&TEXT(3,"000")) | B7: =IF(C7="","",IFERROR(1/(1/_xlfn.MINIFS('Saisie'!$A$5:$A$2004,'Saisie'!$C$5:$C$2004,C7)),"")) | C7: =IFERROR(INDEX('Saisie'!$C$5:$C$2004,MATCH(3,'Saisie'!$AX$5:$AX$2004,0)),"") | D7: =IF(C7="","",IF(AND(BR7>0,BR7>BS7,BA7<7),"Perdu",INDEX('Paramètres'!$F$6:$F$13,BA7))) | E7: =IF(C7="","",MIN(100,(Z7="Oui")*'Paramètres'!$B$38+(AB7="Régulière")*'Paramètres'!$B$39+IF(AND(N(AA7)>0,TODAY()-N(AA7)<=30),'Paramètres'!$B$40,0)+(W7="")*'Paramètres'!$B$41+(AC7="Absente")*'Paramètres'!$B$42+(AC7="Faible")*'Paramètres'!$B$43+IF(AND(N(AD7)>0,N(AD7)<4),'Paramètres'!$B$44,0)+(AF7="Moyenne")*'Paramètres'!$B$45+(AF7="Grande")*'Paramètres'!$B$46+(Y7<>"")*'Paramètres'!$B$47)) | F7: =IF(C7="","",IF(D7="Gagné","",IF(D7="Perdu",IF(AND(AX7<>"",AX7<=TODAY()),"À recontacter (perdu)",""),IF(AND(O7>='Paramètres'!$B$21,P7=0),"Stop : "&'Paramètres'!$B$21&" tentatives sans réponse",IF(AND(D7="Proposition",AR7<>"",TODAY()>N(AR7)),"Proposition expirée",IF(AND(D7="Proposition",N(R7)>='Paramètres'!$B$25),"Proposition sans réponse",IF(AND(G7<>"",N(G7)<TODAY()),"Relance en retard",IF(N(R7)>='Paramètres'!$B$24,"Sans action depuis "&R7&" j","")))))))) | G7: =IF(OR(C7="",D7="Gagné",D7="Perdu"),"",IF(AND(BP7>0,BP7=BQ7),INDEX('Saisie'!$J$5:$J$2004,BP7-4),IF(OR(O7=0,AND(O7>='Paramètres'!$B$21,P7=0)),"",Q7+IF(O7<=1,'Paramètres'!$B$18,IF(O7=2,'Paramètres'!$B$19,'Paramètres'!$B$20))))) | H7: =IF(OR(G7="",BP7<>BQ7),"",IF(INDEX('Saisie'!$K$5:$K$2004,BP7-4)="","",INDEX('Saisie'!$K$5:$K$2004,BP7-4))) | I7: =IF(C7="","",IF(OR(D7="Gagné",D7="Perdu"),"",IFERROR(INDEX('Saisie'!$I$5:$I$2004,_xlfn.MAXIFS('Saisie'!$AS$5:$AS$2004,'Saisie'!$C$5:$C$2004,C7,'Saisie'!$I$5:$I$2004,"<>")-4),""))) | J7: =IF(C7="","",IFERROR(INDEX('Saisie'!$U$5:$U$2004,_xlfn.MAXIFS('Saisie'!$AS$5:$AS$2004,'Saisie'!$C$5:$C$2004,C7,'Saisie'!$U$5:$U$2004,"<>")-4),"")) | K7: =IF(C7="","",IFERROR(INDEX('Saisie'!$W$5:$W$2004,_xlfn.MAXIFS('Saisie'!$AS$5:$AS$2004,'Saisie'!$C$5:$C$2004,C7,'Saisie'!$W$5:$W$2004,"<>")-4),"")) | L7: =IF(IF(BB7<>"",BB7,K7)="","",HYPERLINK("https://wa.me/"&IF(LEFT(SUBSTITUTE(SUBSTITUTE(SUBSTITUTE(IF(BB7<>"",BB7,K7)," ",""),".",""),"+",""),1)="0",'Paramètres'!$B$35&MID(SUBSTITUTE(SUBSTITUTE(SUBSTITUTE(IF(BB7<>"",BB7,K7)," ",""),".",""),"+",""),2,20),SUBSTITUTE(SUBSTITUTE(SUBSTITUTE(IF(BB7<>"",BB7,K7)," ",""),".",""),"+","")),"WhatsApp")) | M7: =IF(BC7="","",HYPERLINK(IF(LEFT(BC7,4)="http",BC7,"https://www.instagram.com/"&SUBSTITUTE(SUBSTITUTE(BC7,"@","")," ","")),BC7)) | N7: =IF(C7="","",IFERROR(INDEX('Saisie'!$D$5:$D$2004,_xlfn.MINIFS('Saisie'!$AS$5:$AS$2004,'Saisie'!$C$5:$C$2004,C7,'Saisie'!$AU$5:$AU$2004,1)-4),IFERROR(INDEX('Saisie'!$D$5:$D$2004,_xlfn.MINIFS('Saisie'!$AS$5:$AS$2004,'Saisie'!$C$5:$C$2004,C7,'Saisie'!$D$5:$D$2004,"<>")-4),""))) | O7: =IF(C7="","",COUNTIFS('Saisie'!$C$5:$C$2004,C7,'Saisie'!$AU$5:$AU$2004,1)) | P7: =IF(C7="","",COUNTIFS('Saisie'!$C$5:$C$2004,C7,'Saisie'!$AV$5:$AV$2004,1)) | Q7: =IF(C7="","",IFERROR(1/(1/_xlfn.MAXIFS('Saisie'!$A$5:$A$2004,'Saisie'!$C$5:$C$2004,C7)),"")) | R7: =IF(C7="","",IF(Q7="","",TODAY()-Q7)) | S7: =IF(C7="","",IFERROR(INDEX('Saisie'!$R$5:$R$2004,_xlfn.MAXIFS('Saisie'!$AS$5:$AS$2004,'Saisie'!$C$5:$C$2004,C7,'Saisie'!$R$5:$R$2004,"<>")-4),"")) | T7: =IF(C7="","",IFERROR(INDEX('Saisie'!$S$5:$S$2004,_xlfn.MAXIFS('Saisie'!$AS$5:$AS$2004,'Saisie'!$C$5:$C$2004,C7,'Saisie'!$S$5:$S$2004,"<>")-4),"")) | U7: =IF(C7="","",IFERROR(INDEX('Saisie'!$T$5:$T$2004,_xlfn.MAXIFS('Saisie'!$AS$5:$AS$2004,'Saisie'!$C$5:$C$2004,C7,'Saisie'!$T$5:$T$2004,"<>")-4),"")) | V7: =IF(C7="","",IFERROR(INDEX('Saisie'!$V$5:$V$2004,_xlfn.MAXIFS('Saisie'!$AS$5:$AS$2004,'Saisie'!$C$5:$C$2004,C7,'Saisie'!$V$5:$V$2004,"<>")-4),"")) | W7: =IF(C7="","",IFERROR(INDEX('Saisie'!$Z$5:$Z$2004,_xlfn.MAXIFS('Saisie'!$AS$5:$AS$2004,'Saisie'!$C$5:$C$2004,C7,'Saisie'!$Z$5:$Z$2004,"<>")-4),"")) | X7: =IF(C7="","",IFERROR(INDEX('Saisie'!$AA$5:$AA$2004,_xlfn.MAXIFS('Saisie'!$AS$5:$AS$2004,'Saisie'!$C$5:$C$2004,C7,'Saisie'!$AA$5:$AA$2004,"<>")-4),"")) | Y7: =IF(C7="","",IFERROR(INDEX('Saisie'!$AB$5:$AB$2004,_xlfn.MAXIFS('Saisie'!$AS$5:$AS$2004,'Saisie'!$C$5:$C$2004,C7,'Saisie'!$AB$5:$AB$2004,"<>")-4),"")) | Z7: =IF(C7="","",IFERROR(INDEX('Saisie'!$AC$5:$AC$2004,_xlfn.MAXIFS('Saisie'!$AS$5:$AS$2004,'Saisie'!$C$5:$C$2004,C7,'Saisie'!$AC$5:$AC$2004,"<>")-4),"")) | AA7: =IF(C7="","",IFERROR(INDEX('Saisie'!$AD$5:$AD$2004,_xlfn.MAXIFS('Saisie'!$AS$5:$AS$2004,'Saisie'!$C$5:$C$2004,C7,'Saisie'!$AD$5:$AD$2004,"<>")-4),"")) | AB7: =IF(C7="","",IFERROR(INDEX('Saisie'!$AE$5:$AE$2004,_xlfn.MAXIFS('Saisie'!$AS$5:$AS$2004,'Saisie'!$C$5:$C$2004,C7,'Saisie'!$AE$5:$AE$2004,"<>")-4),"")) | AC7: =IF(C7="","",IFERROR(INDEX('Saisie'!$AF$5:$AF$2004,_xlfn.MAXIFS('Saisie'!$AS$5:$AS$2004,'Saisie'!$C$5:$C$2004,C7,'Saisie'!$AF$5:$AF$2004,"<>")-4),"")) | AD7: =IF(C7="","",IFERROR(INDEX('Saisie'!$AG$5:$AG$2004,_xlfn.MAXIFS('Saisie'!$AS$5:$AS$2004,'Saisie'!$C$5:$C$2004,C7,'Saisie'!$AG$5:$AG$2004,"<>")-4),"")) | AE7: =IF(C7="","",IFERROR(INDEX('Saisie'!$AH$5:$AH$2004,_xlfn.MAXIFS('Saisie'!$AS$5:$AS$2004,'Saisie'!$C$5:$C$2004,C7,'Saisie'!$AH$5:$AH$2004,"<>")-4),"")) | AF7: =IF(C7="","",IFERROR(INDEX('Saisie'!$AI$5:$AI$2004,_xlfn.MAXIFS('Saisie'!$AS$5:$AS$2004,'Saisie'!$C$5:$C$2004,C7,'Saisie'!$AI$5:$AI$2004,"<>")-4),"")) | AG7: =IF(C7="","",IFERROR(INDEX('Saisie'!$AJ$5:$AJ$2004,_xlfn.MAXIFS('Saisie'!$AS$5:$AS$2004,'Saisie'!$C$5:$C$2004,C7,'Saisie'!$AJ$5:$AJ$2004,"<>")-4),"")) | AH7: =IF(C7="","",IFERROR(INDEX('Saisie'!$AK$5:$AK$2004,_xlfn.MAXIFS('Saisie'!$AS$5:$AS$2004,'Saisie'!$C$5:$C$2004,C7,'Saisie'!$AK$5:$AK$2004,"<>")-4),"")) | AI7: =IF(C7="","",IFERROR(INDEX('Saisie'!$AN$5:$AN$2004,_xlfn.MAXIFS('Saisie'!$AS$5:$AS$2004,'Saisie'!$C$5:$C$2004,C7,'Saisie'!$AN$5:$AN$2004,"<>")-4),"")) | AJ7: =IF(C7="","",IFERROR(INDEX('Saisie'!$AO$5:$AO$2004,_xlfn.MAXIFS('Saisie'!$AS$5:$AS$2004,'Saisie'!$C$5:$C$2004,C7,'Saisie'!$AO$5:$AO$2004,"<>")-4),"")) | AK7: =IF(C7="","",IFERROR(INDEX('Saisie'!$AP$5:$AP$2004,_xlfn.MAXIFS('Saisie'!$AS$5:$AS$2004,'Saisie'!$C$5:$C$2004,C7,'Saisie'!$AP$5:$AP$2004,"<>")-4),"")) | AL7: =IF(C7="","",IFERROR(INDEX('Saisie'!$AQ$5:$AQ$2004,_xlfn.MAXIFS('Saisie'!$AS$5:$AS$2004,'Saisie'!$C$5:$C$2004,C7,'Saisie'!$AQ$5:$AQ$2004,"<>")-4),"")) | AM7: =IF(C7="","",((AI7="Oui")+(AJ7="Oui")+(AK7="Oui")+OR(AL7="Immédiat",AL7="< 1 mois"))&"/4") | AN7: =IF(C7="","",IFERROR(INDEX('Saisie'!$AL$5:$AL$2004,_xlfn.MAXIFS('Saisie'!$AS$5:$AS$2004,'Saisie'!$C$5:$C$2004,C7,'Saisie'!$AL$5:$AL$2004,"<>")-4),"")) | AO7: =IF(C7="","",IF(IFERROR(INDEX('Saisie'!$AM$5:$AM$2004,_xlfn.MAXIFS('Saisie'!$AS$5:$AS$2004,'Saisie'!$C$5:$C$2004,C7,'Saisie'!$AM$5:$AM$2004,"<>")-4),"")<>"",IFERROR(INDEX('Saisie'!$AM$5:$AM$2004,_xlfn.MAXIFS('Saisie'!$AS$5:$AS$2004,'Saisie'!$C$5:$C$2004,C7,'Saisie'!$AM$5:$AM$2004,"<>")-4),""),IFERROR(INDEX('Paramètres'!$S$6:$S$15,MATCH(AN7,'Paramètres'!$Q$6:$Q$15,0)),""))) | AP7: =IF(C7="","",IFERROR(INDEX('Saisie'!$AW$5:$AW$2004,_xlfn.MAXIFS('Saisie'!$AS$5:$AS$2004,'Saisie'!$C$5:$C$2004,C7,'Saisie'!$E$5:$E$2004,"Proposition envoyée")-4),"")) | AQ7: =IF(C7="","",IFERROR(1/(1/_xlfn.MAXIFS('Saisie'!$A$5:$A$2004,'Saisie'!$C$5:$C$2004,C7,'Saisie'!$E$5:$E$2004,"Proposition envoyée")),"")) | AR7: =IF(C7="","",IF(AQ7="","",AQ7+'Paramètres'!$B$26)) | AS7: =IF(OR(C7="",D7="Gagné",D7="Perdu"),0,N(AP7)*IFERROR(INDEX('Paramètres'!$G$6:$G$13,MATCH(D7,'Paramètres'!$F$6:$F$13,0)),0)) | AT7: =IF(C7="","",IFERROR(1/(1/_xlfn.MINIFS('Saisie'!$A$5:$A$2004,'Saisie'!$C$5:$C$2004,C7,'Saisie'!$E$5:$E$2004,"Signature")),"")) | AU7: =IF(C7="","",IF(OR(AT7="",B7=""),"",AT7-B7)) | AV7: =IF(C7="","",IFERROR(INDEX('Saisie'!$L$5:$L$2004,_xlfn.MAXIFS('Saisie'!$AS$5:$AS$2004,'Saisie'!$C$5:$C$2004,C7,'Saisie'!$L$5:$L$2004,"<>")-4),"")) | AW7: =IF(C7="","",IF(D7<>"Perdu","",IFERROR(1/(1/_xlfn.MAXIFS('Saisie'!$A$5:$A$2004,'Saisie'!$C$5:$C$2004,C7,'Saisie'!$E$5:$E$2004,"Perdu")),""))) | AX7: =IF(C7="","",IF(AW7="","",AW7+'Paramètres'!$B$28)) | AY7: =IF(C7="","",SUMIFS('Saisie'!$H$5:$H$2004,'Saisie'!$C$5:$C$2004,C7)) | AZ7: =IF(C7="","",IFERROR(INDEX('Paramètres'!$W$6:$W$20,MATCH(S7,'Paramètres'!$V$6:$V$20,0))&"","")) | BA7: =IF(C7="","",MAX(1,_xlfn.MAXIFS('Saisie'!$AT$5:$AT$2004,'Saisie'!$C$5:$C$2004,C7))) | BB7: =IF(C7="","",IFERROR(INDEX('Saisie'!$X$5:$X$2004,_xlfn.MAXIFS('Saisie'!$AS$5:$AS$2004,'Saisie'!$C$5:$C$2004,C7,'Saisie'!$X$5:$X$2004,"<>")-4),"")) | BC7: =IF(C7="","",IFERROR(INDEX('Saisie'!$Y$5:$Y$2004,_xlfn.MAXIFS('Saisie'!$AS$5:$AS$2004,'Saisie'!$C$5:$C$2004,C7,'Saisie'!$Y$5:$Y$2004,"<>")-4),"")) | BD7: =IF(C7="","",IFERROR(1/(1/_xlfn.MINIFS('Saisie'!$A$5:$A$2004,'Saisie'!$C$5:$C$2004,C7,'Saisie'!$AT$5:$AT$2004,">=2")),"")) | BE7: =IF(C7="","",IFERROR(1/(1/_xlfn.MINIFS('Saisie'!$A$5:$A$2004,'Saisie'!$C$5:$C$2004,C7,'Saisie'!$AT$5:$AT$2004,">=3")),"")) | BF7: =IF(C7="","",IFERROR(1/(1/_xlfn.MINIFS('Saisie'!$A$5:$A$2004,'Saisie'!$C$5:$C$2004,C7,'Saisie'!$AT$5:$AT$2004,">=4")),"")) | BG7: =IF(C7="","",IFERROR(1/(1/_xlfn.MINIFS('Saisie'!$A$5:$A$2004,'Saisie'!$C$5:$C$2004,C7,'Saisie'!$AT$5:$AT$2004,">=5")),"")) | BH7: =IF(C7="","",IFERROR(1/(1/_xlfn.MINIFS('Saisie'!$A$5:$A$2004,'Saisie'!$C$5:$C$2004,C7,'Saisie'!$AT$5:$AT$2004,">=6")),"")) | BI7: =IF(C7="","",IFERROR(1/(1/_xlfn.MINIFS('Saisie'!$A$5:$A$2004,'Saisie'!$C$5:$C$2004,C7,'Saisie'!$AT$5:$AT$2004,">=7")),"")) | BJ7: =IF(OR(BD7="",B7=""),"",BD7-B7) | BK7: =IF(OR(BE7="",BD7=""),"",BE7-BD7) | BL7: =IF(OR(BF7="",BE7=""),"",BF7-BE7) | BM7: =IF(OR(BG7="",BF7=""),"",BG7-BF7) | BN7: =IF(OR(BH7="",BG7=""),"",BH7-BG7) | BO7: =IF(OR(BI7="",BH7=""),"",BI7-BH7) | BP7: =IF(C7="","",_xlfn.MAXIFS('Saisie'!$AS$5:$AS$2004,'Saisie'!$C$5:$C$2004,C7,'Saisie'!$J$5:$J$2004,"<>")) | BQ7: =IF(C7="","",_xlfn.MAXIFS('Saisie'!$AS$5:$AS$2004,'Saisie'!$C$5:$C$2004,C7)) | BR7: =IF(C7="","",_xlfn.MAXIFS('Saisie'!$AS$5:$AS$2004,'Saisie'!$C$5:$C$2004,C7,'Saisie'!$E$5:$E$2004,"Perdu")) | BS7: =IF(C7="","",_xlfn.MAXIFS('Saisie'!$AS$5:$AS$2004,'Saisie'!$C$5:$C$2004,C7,'Saisie'!$AT$5:$AT$2004,">0")) | BT7: =IF(AND(C7<>"",OR(D7="Nouveau",D7="Contacté",D7="Qualifié"),OR(G7="",N(G7)<=TODAY()),NOT(AND(O7>='Paramètres'!$B$21,P7=0))),E7+3/10000,"") | BU7: =IF(AND(G7<>"",N(G7)<=TODAY()),MAX($BU$4:BU6)+1,"") | BV7: =IF(AND(F7<>"",F7<>"Relance en retard"),MAX($BV$4:BV6)+1,"") | BW7: =IF(C7="","",IF(AND(B7>='Tableau de bord'!$R$4,B7<='Tableau de bord'!$S$4,OR('Tableau de bord'!$G$4="Tous",N7='Tableau de bord'!$G$4)),1,0)) | BX7: =IF(AND(C7<>"",N(BA7)=7),MAX($BX$4:BX6)+1,"")
A8: =IF(C8="","","P-"&TEXT(4,"000")) | B8: =IF(C8="","",IFERROR(1/(1/_xlfn.MINIFS('Saisie'!$A$5:$A$2004,'Saisie'!$C$5:$C$2004,C8)),"")) | C8: =IFERROR(INDEX('Saisie'!$C$5:$C$2004,MATCH(4,'Saisie'!$AX$5:$AX$2004,0)),"") | D8: =IF(C8="","",IF(AND(BR8>0,BR8>BS8,BA8<7),"Perdu",INDEX('Paramètres'!$F$6:$F$13,BA8))) | E8: =IF(C8="","",MIN(100,(Z8="Oui")*'Paramètres'!$B$38+(AB8="Régulière")*'Paramètres'!$B$39+IF(AND(N(AA8)>0,TODAY()-N(AA8)<=30),'Paramètres'!$B$40,0)+(W8="")*'Paramètres'!$B$41+(AC8="Absente")*'Paramètres'!$B$42+(AC8="Faible")*'Paramètres'!$B$43+IF(AND(N(AD8)>0,N(AD8)<4),'Paramètres'!$B$44,0)+(AF8="Moyenne")*'Paramètres'!$B$45+(AF8="Grande")*'Paramètres'!$B$46+(Y8<>"")*'Paramètres'!$B$47)) | F8: =IF(C8="","",IF(D8="Gagné","",IF(D8="Perdu",IF(AND(AX8<>"",AX8<=TODAY()),"À recontacter (perdu)",""),IF(AND(O8>='Paramètres'!$B$21,P8=0),"Stop : "&'Paramètres'!$B$21&" tentatives sans réponse",IF(AND(D8="Proposition",AR8<>"",TODAY()>N(AR8)),"Proposition expirée",IF(AND(D8="Proposition",N(R8)>='Paramètres'!$B$25),"Proposition sans réponse",IF(AND(G8<>"",N(G8)<TODAY()),"Relance en retard",IF(N(R8)>='Paramètres'!$B$24,"Sans action depuis "&R8&" j","")))))))) | G8: =IF(OR(C8="",D8="Gagné",D8="Perdu"),"",IF(AND(BP8>0,BP8=BQ8),INDEX('Saisie'!$J$5:$J$2004,BP8-4),IF(OR(O8=0,AND(O8>='Paramètres'!$B$21,P8=0)),"",Q8+IF(O8<=1,'Paramètres'!$B$18,IF(O8=2,'Paramètres'!$B$19,'Paramètres'!$B$20))))) | H8: =IF(OR(G8="",BP8<>BQ8),"",IF(INDEX('Saisie'!$K$5:$K$2004,BP8-4)="","",INDEX('Saisie'!$K$5:$K$2004,BP8-4))) | I8: =IF(C8="","",IF(OR(D8="Gagné",D8="Perdu"),"",IFERROR(INDEX('Saisie'!$I$5:$I$2004,_xlfn.MAXIFS('Saisie'!$AS$5:$AS$2004,'Saisie'!$C$5:$C$2004,C8,'Saisie'!$I$5:$I$2004,"<>")-4),""))) | J8: =IF(C8="","",IFERROR(INDEX('Saisie'!$U$5:$U$2004,_xlfn.MAXIFS('Saisie'!$AS$5:$AS$2004,'Saisie'!$C$5:$C$2004,C8,'Saisie'!$U$5:$U$2004,"<>")-4),"")) | K8: =IF(C8="","",IFERROR(INDEX('Saisie'!$W$5:$W$2004,_xlfn.MAXIFS('Saisie'!$AS$5:$AS$2004,'Saisie'!$C$5:$C$2004,C8,'Saisie'!$W$5:$W$2004,"<>")-4),"")) | L8: =IF(IF(BB8<>"",BB8,K8)="","",HYPERLINK("https://wa.me/"&IF(LEFT(SUBSTITUTE(SUBSTITUTE(SUBSTITUTE(IF(BB8<>"",BB8,K8)," ",""),".",""),"+",""),1)="0",'Paramètres'!$B$35&MID(SUBSTITUTE(SUBSTITUTE(SUBSTITUTE(IF(BB8<>"",BB8,K8)," ",""),".",""),"+",""),2,20),SUBSTITUTE(SUBSTITUTE(SUBSTITUTE(IF(BB8<>"",BB8,K8)," ",""),".",""),"+","")),"WhatsApp")) | M8: =IF(BC8="","",HYPERLINK(IF(LEFT(BC8,4)="http",BC8,"https://www.instagram.com/"&SUBSTITUTE(SUBSTITUTE(BC8,"@","")," ","")),BC8)) | N8: =IF(C8="","",IFERROR(INDEX('Saisie'!$D$5:$D$2004,_xlfn.MINIFS('Saisie'!$AS$5:$AS$2004,'Saisie'!$C$5:$C$2004,C8,'Saisie'!$AU$5:$AU$2004,1)-4),IFERROR(INDEX('Saisie'!$D$5:$D$2004,_xlfn.MINIFS('Saisie'!$AS$5:$AS$2004,'Saisie'!$C$5:$C$2004,C8,'Saisie'!$D$5:$D$2004,"<>")-4),""))) | O8: =IF(C8="","",COUNTIFS('Saisie'!$C$5:$C$2004,C8,'Saisie'!$AU$5:$AU$2004,1)) | P8: =IF(C8="","",COUNTIFS('Saisie'!$C$5:$C$2004,C8,'Saisie'!$AV$5:$AV$2004,1)) | Q8: =IF(C8="","",IFERROR(1/(1/_xlfn.MAXIFS('Saisie'!$A$5:$A$2004,'Saisie'!$C$5:$C$2004,C8)),"")) | R8: =IF(C8="","",IF(Q8="","",TODAY()-Q8)) | S8: =IF(C8="","",IFERROR(INDEX('Saisie'!$R$5:$R$2004,_xlfn.MAXIFS('Saisie'!$AS$5:$AS$2004,'Saisie'!$C$5:$C$2004,C8,'Saisie'!$R$5:$R$2004,"<>")-4),"")) | T8: =IF(C8="","",IFERROR(INDEX('Saisie'!$S$5:$S$2004,_xlfn.MAXIFS('Saisie'!$AS$5:$AS$2004,'Saisie'!$C$5:$C$2004,C8,'Saisie'!$S$5:$S$2004,"<>")-4),"")) | U8: =IF(C8="","",IFERROR(INDEX('Saisie'!$T$5:$T$2004,_xlfn.MAXIFS('Saisie'!$AS$5:$AS$2004,'Saisie'!$C$5:$C$2004,C8,'Saisie'!$T$5:$T$2004,"<>")-4),"")) | V8: =IF(C8="","",IFERROR(INDEX('Saisie'!$V$5:$V$2004,_xlfn.MAXIFS('Saisie'!$AS$5:$AS$2004,'Saisie'!$C$5:$C$2004,C8,'Saisie'!$V$5:$V$2004,"<>")-4),"")) | W8: =IF(C8="","",IFERROR(INDEX('Saisie'!$Z$5:$Z$2004,_xlfn.MAXIFS('Saisie'!$AS$5:$AS$2004,'Saisie'!$C$5:$C$2004,C8,'Saisie'!$Z$5:$Z$2004,"<>")-4),"")) | X8: =IF(C8="","",IFERROR(INDEX('Saisie'!$AA$5:$AA$2004,_xlfn.MAXIFS('Saisie'!$AS$5:$AS$2004,'Saisie'!$C$5:$C$2004,C8,'Saisie'!$AA$5:$AA$2004,"<>")-4),"")) | Y8: =IF(C8="","",IFERROR(INDEX('Saisie'!$AB$5:$AB$2004,_xlfn.MAXIFS('Saisie'!$AS$5:$AS$2004,'Saisie'!$C$5:$C$2004,C8,'Saisie'!$AB$5:$AB$2004,"<>")-4),"")) | Z8: =IF(C8="","",IFERROR(INDEX('Saisie'!$AC$5:$AC$2004,_xlfn.MAXIFS('Saisie'!$AS$5:$AS$2004,'Saisie'!$C$5:$C$2004,C8,'Saisie'!$AC$5:$AC$2004,"<>")-4),"")) | AA8: =IF(C8="","",IFERROR(INDEX('Saisie'!$AD$5:$AD$2004,_xlfn.MAXIFS('Saisie'!$AS$5:$AS$2004,'Saisie'!$C$5:$C$2004,C8,'Saisie'!$AD$5:$AD$2004,"<>")-4),"")) | AB8: =IF(C8="","",IFERROR(INDEX('Saisie'!$AE$5:$AE$2004,_xlfn.MAXIFS('Saisie'!$AS$5:$AS$2004,'Saisie'!$C$5:$C$2004,C8,'Saisie'!$AE$5:$AE$2004,"<>")-4),"")) | AC8: =IF(C8="","",IFERROR(INDEX('Saisie'!$AF$5:$AF$2004,_xlfn.MAXIFS('Saisie'!$AS$5:$AS$2004,'Saisie'!$C$5:$C$2004,C8,'Saisie'!$AF$5:$AF$2004,"<>")-4),"")) | AD8: =IF(C8="","",IFERROR(INDEX('Saisie'!$AG$5:$AG$2004,_xlfn.MAXIFS('Saisie'!$AS$5:$AS$2004,'Saisie'!$C$5:$C$2004,C8,'Saisie'!$AG$5:$AG$2004,"<>")-4),"")) | AE8: =IF(C8="","",IFERROR(INDEX('Saisie'!$AH$5:$AH$2004,_xlfn.MAXIFS('Saisie'!$AS$5:$AS$2004,'Saisie'!$C$5:$C$2004,C8,'Saisie'!$AH$5:$AH$2004,"<>")-4),"")) | AF8: =IF(C8="","",IFERROR(INDEX('Saisie'!$AI$5:$AI$2004,_xlfn.MAXIFS('Saisie'!$AS$5:$AS$2004,'Saisie'!$C$5:$C$2004,C8,'Saisie'!$AI$5:$AI$2004,"<>")-4),"")) | AG8: =IF(C8="","",IFERROR(INDEX('Saisie'!$AJ$5:$AJ$2004,_xlfn.MAXIFS('Saisie'!$AS$5:$AS$2004,'Saisie'!$C$5:$C$2004,C8,'Saisie'!$AJ$5:$AJ$2004,"<>")-4),"")) | AH8: =IF(C8="","",IFERROR(INDEX('Saisie'!$AK$5:$AK$2004,_xlfn.MAXIFS('Saisie'!$AS$5:$AS$2004,'Saisie'!$C$5:$C$2004,C8,'Saisie'!$AK$5:$AK$2004,"<>")-4),"")) | AI8: =IF(C8="","",IFERROR(INDEX('Saisie'!$AN$5:$AN$2004,_xlfn.MAXIFS('Saisie'!$AS$5:$AS$2004,'Saisie'!$C$5:$C$2004,C8,'Saisie'!$AN$5:$AN$2004,"<>")-4),"")) | AJ8: =IF(C8="","",IFERROR(INDEX('Saisie'!$AO$5:$AO$2004,_xlfn.MAXIFS('Saisie'!$AS$5:$AS$2004,'Saisie'!$C$5:$C$2004,C8,'Saisie'!$AO$5:$AO$2004,"<>")-4),"")) | AK8: =IF(C8="","",IFERROR(INDEX('Saisie'!$AP$5:$AP$2004,_xlfn.MAXIFS('Saisie'!$AS$5:$AS$2004,'Saisie'!$C$5:$C$2004,C8,'Saisie'!$AP$5:$AP$2004,"<>")-4),"")) | AL8: =IF(C8="","",IFERROR(INDEX('Saisie'!$AQ$5:$AQ$2004,_xlfn.MAXIFS('Saisie'!$AS$5:$AS$2004,'Saisie'!$C$5:$C$2004,C8,'Saisie'!$AQ$5:$AQ$2004,"<>")-4),"")) | AM8: =IF(C8="","",((AI8="Oui")+(AJ8="Oui")+(AK8="Oui")+OR(AL8="Immédiat",AL8="< 1 mois"))&"/4") | AN8: =IF(C8="","",IFERROR(INDEX('Saisie'!$AL$5:$AL$2004,_xlfn.MAXIFS('Saisie'!$AS$5:$AS$2004,'Saisie'!$C$5:$C$2004,C8,'Saisie'!$AL$5:$AL$2004,"<>")-4),"")) | AO8: =IF(C8="","",IF(IFERROR(INDEX('Saisie'!$AM$5:$AM$2004,_xlfn.MAXIFS('Saisie'!$AS$5:$AS$2004,'Saisie'!$C$5:$C$2004,C8,'Saisie'!$AM$5:$AM$2004,"<>")-4),"")<>"",IFERROR(INDEX('Saisie'!$AM$5:$AM$2004,_xlfn.MAXIFS('Saisie'!$AS$5:$AS$2004,'Saisie'!$C$5:$C$2004,C8,'Saisie'!$AM$5:$AM$2004,"<>")-4),""),IFERROR(INDEX('Paramètres'!$S$6:$S$15,MATCH(AN8,'Paramètres'!$Q$6:$Q$15,0)),""))) | AP8: =IF(C8="","",IFERROR(INDEX('Saisie'!$AW$5:$AW$2004,_xlfn.MAXIFS('Saisie'!$AS$5:$AS$2004,'Saisie'!$C$5:$C$2004,C8,'Saisie'!$E$5:$E$2004,"Proposition envoyée")-4),"")) | AQ8: =IF(C8="","",IFERROR(1/(1/_xlfn.MAXIFS('Saisie'!$A$5:$A$2004,'Saisie'!$C$5:$C$2004,C8,'Saisie'!$E$5:$E$2004,"Proposition envoyée")),"")) | AR8: =IF(C8="","",IF(AQ8="","",AQ8+'Paramètres'!$B$26)) | AS8: =IF(OR(C8="",D8="Gagné",D8="Perdu"),0,N(AP8)*IFERROR(INDEX('Paramètres'!$G$6:$G$13,MATCH(D8,'Paramètres'!$F$6:$F$13,0)),0)) | AT8: =IF(C8="","",IFERROR(1/(1/_xlfn.MINIFS('Saisie'!$A$5:$A$2004,'Saisie'!$C$5:$C$2004,C8,'Saisie'!$E$5:$E$2004,"Signature")),"")) | AU8: =IF(C8="","",IF(OR(AT8="",B8=""),"",AT8-B8)) | AV8: =IF(C8="","",IFERROR(INDEX('Saisie'!$L$5:$L$2004,_xlfn.MAXIFS('Saisie'!$AS$5:$AS$2004,'Saisie'!$C$5:$C$2004,C8,'Saisie'!$L$5:$L$2004,"<>")-4),"")) | AW8: =IF(C8="","",IF(D8<>"Perdu","",IFERROR(1/(1/_xlfn.MAXIFS('Saisie'!$A$5:$A$2004,'Saisie'!$C$5:$C$2004,C8,'Saisie'!$E$5:$E$2004,"Perdu")),""))) | AX8: =IF(C8="","",IF(AW8="","",AW8+'Paramètres'!$B$28)) | AY8: =IF(C8="","",SUMIFS('Saisie'!$H$5:$H$2004,'Saisie'!$C$5:$C$2004,C8)) | AZ8: =IF(C8="","",IFERROR(INDEX('Paramètres'!$W$6:$W$20,MATCH(S8,'Paramètres'!$V$6:$V$20,0))&"","")) | BA8: =IF(C8="","",MAX(1,_xlfn.MAXIFS('Saisie'!$AT$5:$AT$2004,'Saisie'!$C$5:$C$2004,C8))) | BB8: =IF(C8="","",IFERROR(INDEX('Saisie'!$X$5:$X$2004,_xlfn.MAXIFS('Saisie'!$AS$5:$AS$2004,'Saisie'!$C$5:$C$2004,C8,'Saisie'!$X$5:$X$2004,"<>")-4),"")) | BC8: =IF(C8="","",IFERROR(INDEX('Saisie'!$Y$5:$Y$2004,_xlfn.MAXIFS('Saisie'!$AS$5:$AS$2004,'Saisie'!$C$5:$C$2004,C8,'Saisie'!$Y$5:$Y$2004,"<>")-4),"")) | BD8: =IF(C8="","",IFERROR(1/(1/_xlfn.MINIFS('Saisie'!$A$5:$A$2004,'Saisie'!$C$5:$C$2004,C8,'Saisie'!$AT$5:$AT$2004,">=2")),"")) | BE8: =IF(C8="","",IFERROR(1/(1/_xlfn.MINIFS('Saisie'!$A$5:$A$2004,'Saisie'!$C$5:$C$2004,C8,'Saisie'!$AT$5:$AT$2004,">=3")),"")) | BF8: =IF(C8="","",IFERROR(1/(1/_xlfn.MINIFS('Saisie'!$A$5:$A$2004,'Saisie'!$C$5:$C$2004,C8,'Saisie'!$AT$5:$AT$2004,">=4")),"")) | BG8: =IF(C8="","",IFERROR(1/(1/_xlfn.MINIFS('Saisie'!$A$5:$A$2004,'Saisie'!$C$5:$C$2004,C8,'Saisie'!$AT$5:$AT$2004,">=5")),"")) | BH8: =IF(C8="","",IFERROR(1/(1/_xlfn.MINIFS('Saisie'!$A$5:$A$2004,'Saisie'!$C$5:$C$2004,C8,'Saisie'!$AT$5:$AT$2004,">=6")),"")) | BI8: =IF(C8="","",IFERROR(1/(1/_xlfn.MINIFS('Saisie'!$A$5:$A$2004,'Saisie'!$C$5:$C$2004,C8,'Saisie'!$AT$5:$AT$2004,">=7")),"")) | BJ8: =IF(OR(BD8="",B8=""),"",BD8-B8) | BK8: =IF(OR(BE8="",BD8=""),"",BE8-BD8) | BL8: =IF(OR(BF8="",BE8=""),"",BF8-BE8) | BM8: =IF(OR(BG8="",BF8=""),"",BG8-BF8) | BN8: =IF(OR(BH8="",BG8=""),"",BH8-BG8) | BO8: =IF(OR(BI8="",BH8=""),"",BI8-BH8) | BP8: =IF(C8="","",_xlfn.MAXIFS('Saisie'!$AS$5:$AS$2004,'Saisie'!$C$5:$C$2004,C8,'Saisie'!$J$5:$J$2004,"<>")) | BQ8: =IF(C8="","",_xlfn.MAXIFS('Saisie'!$AS$5:$AS$2004,'Saisie'!$C$5:$C$2004,C8)) | BR8: =IF(C8="","",_xlfn.MAXIFS('Saisie'!$AS$5:$AS$2004,'Saisie'!$C$5:$C$2004,C8,'Saisie'!$E$5:$E$2004,"Perdu")) | BS8: =IF(C8="","",_xlfn.MAXIFS('Saisie'!$AS$5:$AS$2004,'Saisie'!$C$5:$C$2004,C8,'Saisie'!$AT$5:$AT$2004,">0")) | BT8: =IF(AND(C8<>"",OR(D8="Nouveau",D8="Contacté",D8="Qualifié"),OR(G8="",N(G8)<=TODAY()),NOT(AND(O8>='Paramètres'!$B$21,P8=0))),E8+4/10000,"") | BU8: =IF(AND(G8<>"",N(G8)<=TODAY()),MAX($BU$4:BU7)+1,"") | BV8: =IF(AND(F8<>"",F8<>"Relance en retard"),MAX($BV$4:BV7)+1,"") | BW8: =IF(C8="","",IF(AND(B8>='Tableau de bord'!$R$4,B8<='Tableau de bord'!$S$4,OR('Tableau de bord'!$G$4="Tous",N8='Tableau de bord'!$G$4)),1,0)) | BX8: =IF(AND(C8<>"",N(BA8)=7),MAX($BX$4:BX7)+1,"")
